Workbook

Sheet Start Here
A1: BIBLE JOURNEY · MASTER CANON LEDGER v1.0
A2: Single source of truth unifying Canon Maps v0.1–v0.9. Tracks 66 canonical books, 1,189 chapters, source-map provenance, editorial uncertainty, and release gates.
A4: Master purpose: unify coverage and editorial traceability without pretending that every book or passage has a single settled chronological placement. Canonical completeness, transparent uncertainty, and intact Scripture remain non-negotiable.
A6: Canonical Chapters | C6: Books Fully Covered | E6: Source Maps Unified | G6: Master CRS Records | I6: Master Reading Blocks
A7: =COUNTA('Master Chapter Coverage'!A5:A2000) -> 1189 | C7: =COUNTIF('Book Summary'!G5:G100,"PASS") -> 66 | E7: =COUNTA('Map Registry'!A5:A50) -> 9 | G7: =COUNTA('Master CRS Ledger'!A5:A1000) -> 514 | I7: =COUNTA('Master Reading Blocks'!A5:A1500) -> 667
A10: Open Editorial Decisions | C10: Duplicate Canon Keys | E10: Missing Canon Keys | G10: Source Registry Records | I10: Dependency / Policy Records
A11: =COUNTIF('Open Decisions Master'!J5:J500,"Open") -> 85 | C11: =COUNTIF('Master Chapter Coverage'!P5:P2000,"DUPLICATE") -> 0 | E11: =COUNTIF('Master Chapter Coverage'!P5:P2000,"MISSING") -> 0 | G11: =COUNTA('Source Registry'!A5:A500) -> 118 | I11: =COUNTA('Master Link Registry'!A5:A1000) -> 337
A14: What v1.0 proves | F14: Immediate leadership decision
A15: • Every chapter in the 66-book canon has one master coverage record. • The master preserves provenance: every CRS, block, source, decision, and dependency points back to its originating map. • Parallel accounts, poetry, prophetic blocks, letters, and apocalyptic literature remain intact rather than being merged into synthetic Scripture. • The master does not declare the final event-by-event global stream resolved. It identifies where a Harmonization Engine must attach parallel and contextual records. • Release readiness is governed by audit gates, not by visual completeness alone. | F15: The canon is now mapped at coverage level. The next critical build is not more chapter mapping; it is a Harmonization Engine that determines the final user-facing order of connected CRS records. It must resolve, with explicit confidence and profiles: 1. Samuel / Kings / Chronicles interleaving. 2. Prophets within reigns and historical horizons. 3. Psalms and wisdom as evidence-scored connections. 4. Gospel parallel accounts. 5. Acts and epistolary placements. 6. Canonical fallback and literary-sequence behavior.
A23: Release Gate | B23: Current Status | C23: Owner | D23: Why It Matters | E23: Next Action
A24: Master chapter coverage | B24: PASS | C24: Editorial QA | D24: A Bible Stream cannot claim completeness with missing or duplicate canonical keys. | E24: Maintain this audit automatically on every import.
A25: Verse-level continuity | B25: BLOCKED | C25: Editorial + Engineering | D25: Chapter mapping cannot detect missing/overlapping verse intervals, especially in Gospel segments and split chapters. | E25: Build PassageBlock / verse-interval validator.
A26: Cross-map harmonization | B26: BLOCKED | C26: Editorial Council | D26: Source maps contain valid components but not a finalized user-facing global event order. | E26: Create Harmonization Engine v1.0.
A27: Open-decision triage | B27: BLOCKED | C27: Editorial Council | D27: High-risk chronology and interpretive questions need policy, profile, or disclosure. | E27: Classify as resolve / disclose / out-of-scope.
A28: Translation licensing | B28: IN PROGRESS | C28: Legal + Partnerships | D28: Reader text availability depends on licensed translations and permitted display rules. | E28: Continue RVR60/NVI license pilot workflow; retain reference mode fallback.

Sheet Map Registry
A1: MAP REGISTRY
A2: Inventory of source workbooks merged into the Master Canon Ledger. Map-level counts are formula-driven from normalized master sheets.
A4: Map Version | B4: Map Name | C4: Source Workbook | D4: Scope | E4: Source Coverage Sheet | F4: Integration Stage | G4: Integration Gate | H4: CRS Count | I4: Block Count | J4: Chapter Coverage Count | K4: Open Decisions | L4: Load Status
A5: v0.1 | B5: Genesis to 2 Samuel | C5: Bible_Journey_Canon_Map_v0_1_Genesis_to_2Samuel.xlsx | D5: Genesis through 2 Samuel | E5: Chapter Map | F5: Canonical narrative spine | G5: Verse-level scene splits; David/Psalms linking policy | H5: =COUNTIF('Master CRS Ledger'!$A$5:$A$1000,A5) -> 116 | I5: =COUNTIF('Master Reading Blocks'!$A$5:$A$1500,A5) -> 135 | J5: =COUNTIF('Master Chapter Coverage'!$G$5:$G$2000,A5) -> 291 | K5: =COUNTIF('Open Decisions Master'!$A$5:$A$500,A5) -> 12 | L5: Imported
A6: v0.2 | B6: Chronicles, Psalms, Job, 1 Kings | C6: Bible_Journey_Canon_Map_v0_2_Chronicles_Psalms_Job_1Kings.xlsx | D6: 1 Chronicles, Psalms, Job, 1 Kings | E6: Chapter Map | F6: Parallel accounts, poetry, wisdom, United Monarchy | G6: Cross-map attachment to Samuel/Kings; Psalm evidence policy | H6: =COUNTIF('Master CRS Ledger'!$A$5:$A$1000,A6) -> 94 | I6: =COUNTIF('Master Reading Blocks'!$A$5:$A$1500,A6) -> 94 | J6: =COUNTIF('Master Chapter Coverage'!$G$5:$G$2000,A6) -> 243 | K6: =COUNTIF('Open Decisions Master'!$A$5:$A$500,A6) -> 14 | L6: Imported
A7: v0.3 | B7: 2 Chronicles, Wisdom, 2 Kings | C7: Bible_Journey_Canon_Map_v0_3_2Chronicles_Wisdom_2Kings.xlsx | D7: 2 Chronicles, Proverbs, Ecclesiastes, Song of Songs, 2 Kings | E7: Chapter Map | F7: Kingdom division and wisdom interlude | G7: Kings/Chronicles interleaving and wisdom placement disclosure | H7: =COUNTIF('Master CRS Ledger'!$A$5:$A$1000,A7) -> 47 | I7: =COUNTIF('Master Reading Blocks'!$A$5:$A$1500,A7) -> 67 | J7: =COUNTIF('Master Chapter Coverage'!$G$5:$G$2000,A7) -> 112 | K7: =COUNTIF('Open Decisions Master'!$A$5:$A$500,A7) -> 9 | L7: Imported
A8: v0.4 | B8: Prophets and Exile | C8: Bible_Journey_Canon_Map_v0_4_Prophets_Exile.xlsx | D8: Isaiah through Lamentations (mapped prophetic corpus) | E8: Chapter Map | F8: Prophets inside Israel/Judah history | G8: Prophetic placement, Jeremiah reordering, Isaiah horizons | H8: =COUNTIF('Master CRS Ledger'!$A$5:$A$1000,A8) -> 52 | I8: =COUNTIF('Master Reading Blocks'!$A$5:$A$1500,A8) -> 54 | J8: =COUNTIF('Master Chapter Coverage'!$G$5:$G$2000,A8) -> 166 | K8: =COUNTIF('Open Decisions Master'!$A$5:$A$500,A8) -> 9 | L8: Imported
A9: v0.5 | B9: Exile, Return, Persia | C9: Bible_Journey_Canon_Map_v0_5_Exile_Return_Persia.xlsx | D9: Habakkuk, Obadiah, Ezekiel, Daniel, Ezra, Nehemiah, Haggai, Zechariah, Malachi | E9: Coverage Audit | F9: Exile, return, Persian transition | G9: Dated prophetic splits, Ezra flash-forward handling, post-exilic placement | H9: =COUNTIF('Master CRS Ledger'!$A$5:$A$1000,A9) -> 46 | I9: =COUNTIF('Master Reading Blocks'!$A$5:$A$1500,A9) -> 46 | J9: =COUNTIF('Master Chapter Coverage'!$G$5:$G$2000,A9) -> 107 | K9: =COUNTIF('Open Decisions Master'!$A$5:$A$500,A9) -> 11 | L9: Imported
A10: v0.6 | B10: Esther and Intertestamental Bridge | C10: Bible_Journey_Canon_Map_v0_6_Esther_Intertestamental_Bridge.xlsx | D10: Esther plus historical bridge cards | E10: Coverage Audit | F10: Persian diaspora and historical bridge | G10: Canon-profile policy and historical context-card governance | H10: =COUNTIF('Master CRS Ledger'!$A$5:$A$1000,A10) -> 4 | I10: =COUNTIF('Master Reading Blocks'!$A$5:$A$1500,A10) -> 4 | J10: =COUNTIF('Master Chapter Coverage'!$G$5:$G$2000,A10) -> 10 | K10: =COUNTIF('Open Decisions Master'!$A$5:$A$500,A10) -> 8 | L10: Imported
A11: v0.7 | B11: Gospel Chronology | C11: Bible_Journey_Canon_Map_v0_7_Gospel_Chronology.xlsx | D11: Matthew, Mark, Luke, John | E11: Coverage Index | F11: Four-Gospel event engine | G11: Verse-level coverage QA and harmony policy approval | H11: =COUNTIF('Master CRS Ledger'!$A$5:$A$1000,A11) -> 90 | I11: =COUNTIF('Master Reading Blocks'!$A$5:$A$1500,A11) -> 202 | J11: =COUNTIF('Master Chapter Coverage'!$G$5:$G$2000,A11) -> 89 | K11: =COUNTIF('Open Decisions Master'!$A$5:$A$500,A11) -> 11 | L11: Imported
A12: v0.8 | B12: Acts and Pauline Letters | C12: Bible_Journey_Canon_Map_v0_8_Acts_Pauline_Letters.xlsx | D12: Acts and 13 Pauline letters | E12: Canon Coverage | F12: Acts narrative + epistolary placements | G12: Acts–letters profiles, prison letters, pastorals, Galatians decision | H12: =COUNTIF('Master CRS Ledger'!$A$5:$A$1000,A12) -> 40 | I12: =COUNTIF('Master Reading Blocks'!$A$5:$A$1500,A12) -> 40 | J12: =COUNTIF('Master Chapter Coverage'!$G$5:$G$2000,A12) -> 115 | K12: =COUNTIF('Open Decisions Master'!$A$5:$A$500,A12) -> 9 | L12: Imported
A13: v0.9 | B13: General Letters and Revelation | C13: Bible_Journey_Canon_Map_v0_9_General_Letters_Revelation.xlsx | D13: Hebrews, General Letters, Revelation | E13: Canon Coverage | F13: Canonical fallback and apocalyptic literary flow | G13: General-letter chronology disclosure and Revelation interpretation policy | H13: =COUNTIF('Master CRS Ledger'!$A$5:$A$1000,A13) -> 25 | I13: =COUNTIF('Master Reading Blocks'!$A$5:$A$1500,A13) -> 25 | J13: =COUNTIF('Master Chapter Coverage'!$G$5:$G$2000,A13) -> 56 | K13: =COUNTIF('Open Decisions Master'!$A$5:$A$500,A13) -> 9 | L13: Imported

Sheet Master CRS Ledger
A1: MASTER CRS LEDGER
A2: Normalized CRS inventory from Canon Maps v0.1–v0.9. Source-map order is preserved; this is not yet the final user-facing global stream order.
A4: Map Version | B4: Source Workbook | C4: Local CRS ID | D4: Local Order | E4: Map Sequence | F4: Scope / Book | G4: Era / Window | H4: Section / Act / Anchor | I4: Reading Set Title | J4: Primary / Required Scripture | K4: Event Confidence | L4: Placement Confidence | M4: Integration / Disposition | N4: Complete Reading Rule | O4: Narrative Flow Rule | P4: Compare / Group | Q4: Journey Link / Tags | R4: Cross-Map Anchor | S4: Source Keys | T4: Research Owner | U4: QA / Review Status | V4: Open Decision Flag | W4: Editorial Note
A5: v0.1 | B5: Bible_Journey_Canon_Map_v0_1_Genesis_to_2Samuel.xlsx | C5: CRS-GEN-001 | D5: 10 | E5: 1 | F5: Genesis | G5: Primeval History | H5: Origins | I5: Creation, garden, and fall | J5: Genesis 1-3 | K5: High | L5: High | N5: Read the assigned main-spine block in full. | O5: Read primary block; continue to next chronological set. | P5: No | Q5: Creation & Covenant | S5: SRC-TEXT-TORAH; SRC-TORAH-OVERVIEW | T5: Editorial | U5: Needs Review | V5: Draft | W5: Chapter-level v0.1 grouping. Future verse-level mapping can split Genesis 2:1-3 from 2:4 onward.
A6: v0.1 | B6: Bible_Journey_Canon_Map_v0_1_Genesis_to_2Samuel.xlsx | C6: CRS-GEN-002 | D6: 20 | E6: 1 | F6: Genesis | G6: Primeval History | H6: Origins | I6: Cain, Seth, and the pre-flood line | J6: Genesis 4-5 | K6: High | L6: High | N6: Read the assigned main-spine block in full. | O6: Read primary block; continue to next chronological set. | P6: No | Q6: Creation & Covenant | S6: SRC-TEXT-TORAH; SRC-TORAH-OVERVIEW | T6: Editorial | U6: Needs Review | V6: Draft
A7: v0.1 | B7: Bible_Journey_Canon_Map_v0_1_Genesis_to_2Samuel.xlsx | C7: CRS-GEN-003 | D7: 30 | E7: 1 | F7: Genesis | G7: Primeval History | H7: Flood | I7: The flood and Noahic covenant | J7: Genesis 6-9 | K7: High | L7: High | N7: Read the assigned main-spine block in full. | O7: Read primary block; continue to next chronological set. | P7: No | Q7: Creation & Covenant | S7: SRC-TEXT-TORAH; SRC-TORAH-OVERVIEW | T7: Editorial | U7: Needs Review | V7: Draft
A8: v0.1 | B8: Bible_Journey_Canon_Map_v0_1_Genesis_to_2Samuel.xlsx | C8: CRS-GEN-004 | D8: 40 | E8: 1 | F8: Genesis | G8: Primeval History | H8: Nations and Babel | I8: Nations and the tower of Babel | J8: Genesis 10-11 | K8: High | L8: High | N8: Read the assigned main-spine block in full. | O8: Read primary block; continue to next chronological set. | P8: No | Q8: Creation & Covenant | S8: SRC-TEXT-TORAH; SRC-TORAH-OVERVIEW | T8: Editorial | U8: Needs Review | V8: Draft
A9: v0.1 | B9: Bible_Journey_Canon_Map_v0_1_Genesis_to_2Samuel.xlsx | C9: CRS-GEN-005 | D9: 50 | E9: 1 | F9: Genesis | G9: Patriarchs | H9: Abraham | I9: Abram's call, separation, and rescue of Lot | J9: Genesis 12-14 | K9: High | L9: High | N9: Read the assigned main-spine block in full. | O9: Read primary block; continue to next chronological set. | P9: No | Q9: Abraham | S9: SRC-TEXT-TORAH; SRC-TORAH-OVERVIEW | T9: Editorial | U9: Needs Review | V9: Draft
A10: v0.1 | B10: Bible_Journey_Canon_Map_v0_1_Genesis_to_2Samuel.xlsx | C10: CRS-GEN-006 | D10: 60 | E10: 1 | F10: Genesis | G10: Patriarchs | H10: Abraham | I10: Covenant, Hagar, and the promised son | J10: Genesis 15-17 | K10: High | L10: High | N10: Read the assigned main-spine block in full. | O10: Read primary block; continue to next chronological set. | P10: No | Q10: Abraham | S10: SRC-TEXT-TORAH; SRC-TORAH-OVERVIEW | T10: Editorial | U10: Needs Review | V10: Draft
A11: v0.1 | B11: Bible_Journey_Canon_Map_v0_1_Genesis_to_2Samuel.xlsx | C11: CRS-GEN-007 | D11: 70 | E11: 1 | F11: Genesis | G11: Patriarchs | H11: Abraham | I11: Sodom, Gomorrah, and Lot's escape | J11: Genesis 18-19 | K11: High | L11: High | N11: Read the assigned main-spine block in full. | O11: Read primary block; continue to next chronological set. | P11: No | Q11: Abraham | S11: SRC-TEXT-TORAH; SRC-TORAH-OVERVIEW | T11: Editorial | U11: Needs Review | V11: Draft
A12: v0.1 | B12: Bible_Journey_Canon_Map_v0_1_Genesis_to_2Samuel.xlsx | C12: CRS-GEN-008 | D12: 80 | E12: 1 | F12: Genesis | G12: Patriarchs | H12: Abraham | I12: Abimelech, Isaac's birth, and Moriah | J12: Genesis 20-22 | K12: High | L12: High | N12: Read the assigned main-spine block in full. | O12: Read primary block; continue to next chronological set. | P12: No | Q12: Abraham | S12: SRC-TEXT-TORAH; SRC-TORAH-OVERVIEW | T12: Editorial | U12: Needs Review | V12: Draft
A13: v0.1 | B13: Bible_Journey_Canon_Map_v0_1_Genesis_to_2Samuel.xlsx | C13: CRS-GEN-009 | D13: 90 | E13: 1 | F13: Genesis | G13: Patriarchs | H13: Transition to Isaac | I13: Sarah's burial, Rebekah, and Abraham's final years | J13: Genesis 23-25 | K13: High | L13: High | N13: Read the assigned main-spine block in full. | O13: Read primary block; continue to next chronological set. | P13: No | Q13: Abraham; Isaac | S13: SRC-TEXT-TORAH; SRC-TORAH-OVERVIEW | T13: Editorial | U13: Needs Review | V13: Draft
A14: v0.1 | B14: Bible_Journey_Canon_Map_v0_1_Genesis_to_2Samuel.xlsx | C14: CRS-GEN-010 | D14: 100 | E14: 1 | F14: Genesis | G14: Patriarchs | H14: Jacob | I14: Isaac's household and Jacob's departure | J14: Genesis 26-28 | K14: High | L14: High | N14: Read the assigned main-spine block in full. | O14: Read primary block; continue to next chronological set. | P14: No | Q14: Jacob | S14: SRC-TEXT-TORAH; SRC-TORAH-OVERVIEW | T14: Editorial | U14: Needs Review | V14: Draft
A15: v0.1 | B15: Bible_Journey_Canon_Map_v0_1_Genesis_to_2Samuel.xlsx | C15: CRS-GEN-011 | D15: 110 | E15: 1 | F15: Genesis | G15: Patriarchs | H15: Jacob | I15: Jacob in Haran | J15: Genesis 29-31 | K15: High | L15: High | N15: Read the assigned main-spine block in full. | O15: Read primary block; continue to next chronological set. | P15: No | Q15: Jacob | S15: SRC-TEXT-TORAH; SRC-TORAH-OVERVIEW | T15: Editorial | U15: Needs Review | V15: Draft
A16: v0.1 | B16: Bible_Journey_Canon_Map_v0_1_Genesis_to_2Samuel.xlsx | C16: CRS-GEN-012 | D16: 120 | E16: 1 | F16: Genesis | G16: Patriarchs | H16: Jacob | I16: Jacob returns and is reconciled with Esau | J16: Genesis 32-33 | K16: High | L16: High | N16: Read the assigned main-spine block in full. | O16: Read primary block; continue to next chronological set. | P16: No | Q16: Jacob | S16: SRC-TEXT-TORAH; SRC-TORAH-OVERVIEW | T16: Editorial | U16: Needs Review | V16: Draft
A17: v0.1 | B17: Bible_Journey_Canon_Map_v0_1_Genesis_to_2Samuel.xlsx | C17: CRS-GEN-013 | D17: 130 | E17: 1 | F17: Genesis | G17: Patriarchs | H17: Jacob | I17: Dinah, Bethel, and Esau's line | J17: Genesis 34-36 | K17: High | L17: High | N17: Read the assigned main-spine block in full. | O17: Read primary block; continue to next chronological set. | P17: No | Q17: Jacob | S17: SRC-TEXT-TORAH; SRC-TORAH-OVERVIEW | T17: Editorial | U17: Needs Review | V17: Draft
... A66: v0.1 | B66: Bible_Journey_Canon_Map_v0_1_Genesis_to_2Samuel.xlsx | C66: CRS-JOS-006 | D66: 620 | E66: 1 | F66: Joshua | G66: Conquest & Settlement | H66: Northern campaign | I66: Northern campaign and conquest summary | J66: Joshua 11-12 | K66: High | L66: High | N66: Read the assigned main-spine block in full. | O66: Read primary block; continue to next chronological set. | P66: No | Q66: Conquest | S66: SRC-TEXT-JOSHUA; SRC-DET-HISTORY | T66: Editorial | U66: Needs Review | V66: Draft
A67: v0.1 | B67: Bible_Journey_Canon_Map_v0_1_Genesis_to_2Samuel.xlsx | C67: CRS-JOS-007 | D67: 630 | E67: 1 | F67: Joshua | G67: Conquest & Settlement | H67: Allotment | I67: Tribal allotments | J67: Joshua 13-19 | K67: High | L67: High | N67: Read the assigned main-spine block in full. | O67: Read primary block; continue to next chronological set. | P67: No | Q67: Conquest | S67: SRC-TEXT-JOSHUA; SRC-DET-HISTORY | T67: Editorial | U67: Needs Review | V67: Draft | W67: Reading section rather than a single battlefield event; retain maps and territory layers as optional study context.
A68: v0.1 | B68: Bible_Journey_Canon_Map_v0_1_Genesis_to_2Samuel.xlsx | C68: CRS-JOS-008 | D68: 640 | E68: 1 | F68: Joshua | G68: Conquest & Settlement | H68: Settlement | I68: Cities of refuge, Levites, and the eastern altar | J68: Joshua 20-22 | K68: High | L68: High | N68: Read the assigned main-spine block in full. | O68: Read primary block; continue to next chronological set. | P68: No | Q68: Conquest | S68: SRC-TEXT-JOSHUA; SRC-DET-HISTORY | T68: Editorial | U68: Needs Review | V68: Draft
A69: v0.1 | B69: Bible_Journey_Canon_Map_v0_1_Genesis_to_2Samuel.xlsx | C69: CRS-JOS-009 | D69: 650 | E69: 1 | F69: Joshua | G69: Conquest & Settlement | H69: Covenant | I69: Joshua's farewell and covenant renewal | J69: Joshua 23-24 | K69: High | L69: High | N69: Read the assigned main-spine block in full. | O69: Read primary block; continue to next chronological set. | P69: No | Q69: Conquest | S69: SRC-TEXT-JOSHUA; SRC-DET-HISTORY | T69: Editorial | U69: Needs Review | V69: Draft
A70: v0.1 | B70: Bible_Journey_Canon_Map_v0_1_Genesis_to_2Samuel.xlsx | C70: CRS-JDG-001 | D70: 660 | E70: 1 | F70: Judges | G70: Judges | H70: Opening cycles | I70: Incomplete conquest and the pattern of the judges | J70: Judges 1-3 | K70: High | L70: High | N70: Read the assigned main-spine block in full. | O70: Read primary block; continue to next chronological set. | P70: No | Q70: Judges | S70: SRC-TEXT-JUDGES; SRC-DET-HISTORY | T70: Editorial | U70: Needs Review | V70: Draft | W70: Chapter 3 contains both cycle introduction and early judges. Keep chapter-level v0.1 grouping; verse-level segmentation is a later refinement.
A71: v0.1 | B71: Bible_Journey_Canon_Map_v0_1_Genesis_to_2Samuel.xlsx | C71: CRS-JDG-002 | D71: 670 | E71: 1 | F71: Judges | G71: Judges | H71: Deborah and Barak | I71: Deborah, Barak, and the song of deliverance | J71: Judges 4-5 | K71: High | L71: High | N71: Read the assigned main-spine block in full. | O71: Read primary block; continue to next chronological set. | P71: No | Q71: Judges | S71: SRC-TEXT-JUDGES; SRC-DET-HISTORY | T71: Editorial | U71: Needs Review | V71: Draft
A72: v0.1 | B72: Bible_Journey_Canon_Map_v0_1_Genesis_to_2Samuel.xlsx | C72: CRS-JDG-003 | D72: 680 | E72: 1 | F72: Judges | G72: Judges | H72: Gideon | I72: Gideon's calling, victory, and legacy | J72: Judges 6-8 | K72: High | L72: High | N72: Read the assigned main-spine block in full. | O72: Read primary block; continue to next chronological set. | P72: No | Q72: Judges | S72: SRC-TEXT-JUDGES; SRC-DET-HISTORY | T72: Editorial | U72: Needs Review | V72: Draft
A73: v0.1 | B73: Bible_Journey_Canon_Map_v0_1_Genesis_to_2Samuel.xlsx | C73: CRS-JDG-004 | D73: 690 | E73: 1 | F73: Judges | G73: Judges | H73: Abimelech | I73: Abimelech's rise and fall | J73: Judges 9 | K73: High | L73: High | N73: Read the assigned main-spine block in full. | O73: Read primary block; continue to next chronological set. | P73: No | Q73: Judges | S73: SRC-TEXT-JUDGES; SRC-DET-HISTORY | T73: Editorial | U73: Needs Review | V73: Draft
A74: v0.1 | B74: Bible_Journey_Canon_Map_v0_1_Genesis_to_2Samuel.xlsx | C74: CRS-JDG-005 | D74: 700 | E74: 1 | F74: Judges | G74: Judges | H74: Eastern judges | I74: Jephthah and the eastern judges | J74: Judges 10-12 | K74: High | L74: High | N74: Read the assigned main-spine block in full. | O74: Read primary block; continue to next chronological set. | P74: No | Q74: Judges | S74: SRC-TEXT-JUDGES; SRC-DET-HISTORY | T74: Editorial | U74: Needs Review | V74: Draft
A75: v0.1 | B75: Bible_Journey_Canon_Map_v0_1_Genesis_to_2Samuel.xlsx | C75: CRS-JDG-006 | D75: 710 | E75: 1 | F75: Judges | G75: Judges | H75: Samson | I75: Samson's birth, conflicts, and death | J75: Judges 13-16 | K75: High | L75: High | N75: Read the assigned main-spine block in full. | O75: Read primary block; continue to next chronological set. | P75: No | Q75: Judges | S75: SRC-TEXT-JUDGES; SRC-DET-HISTORY | T75: Editorial | U75: Needs Review | V75: Draft
A76: v0.1 | B76: Bible_Journey_Canon_Map_v0_1_Genesis_to_2Samuel.xlsx | C76: CRS-JDG-007 | D76: 720 | E76: 1 | F76: Judges | G76: Judges | H76: Tribal disorder | I76: Micah, the Levite, and the tribe of Dan | J76: Judges 17-18 | K76: High | L76: Probable | N76: Read the assigned main-spine block in full. | O76: Read primary block; continue to next chronological set. | P76: No | Q76: Judges | S76: SRC-TEXT-JUDGES; SRC-DET-HISTORY | T76: Editorial | U76: Needs Review | V76: Draft | W76: These chapters are not necessarily placed in strict historical sequence by the narrative. V0.1 keeps canonical order and flags the section as an editorial placement.
A77: v0.1 | B77: Bible_Journey_Canon_Map_v0_1_Genesis_to_2Samuel.xlsx | C77: CRS-JDG-008 | D77: 730 | E77: 1 | F77: Judges | G77: Judges | H77: Tribal disorder | I77: Gibeah and the civil war | J77: Judges 19-21 | K77: High | L77: Probable | N77: Read the assigned main-spine block in full. | O77: Read primary block; continue to next chronological set. | P77: No | Q77: Judges | S77: SRC-TEXT-JUDGES; SRC-DET-HISTORY | T77: Editorial | U77: Needs Review | V77: Draft | W77: These chapters are not necessarily placed in strict historical sequence by the narrative. V0.1 keeps canonical order and flags the section as an editorial placement.
A78: v0.1 | B78: Bible_Journey_Canon_Map_v0_1_Genesis_to_2Samuel.xlsx | C78: CRS-RUT-001 | D78: 740 | E78: 1 | F78: Ruth | G78: Judges | H78: Ruth | I78: Ruth, Naomi, Boaz, and the Davidic line | J78: Ruth 1-4 | K78: High | L78: Probable | N78: Read the assigned main-spine block in full. | O78: Read primary block; continue to next chronological set. | P78: No | Q78: Ruth; Davidic Line | S78: SRC-TEXT-RUTH | T78: Editorial | U78: Needs Review | V78: Draft | W78: The book is set 'in the days when the judges ruled'; its precise placement within the judges period is not stated.
A79: v0.1 | B79: Bible_Journey_Canon_Map_v0_1_Genesis_to_2Samuel.xlsx | C79: CRS-1SA-001 | D79: 750 | E79: 1 | F79: 1 Samuel | G79: Rise of the Monarchy | H79: Samuel | I79: Samuel's birth, dedication, and call | J79: 1 Samuel 1-3 | K79: High | L79: High | N79: Read the assigned main-spine block in full. | O79: Read primary block; continue to next chronological set. | P79: No | Q79: Samuel; Rise of the Monarchy | S79: SRC-TEXT-1SAM; SRC-SAMUEL-OVERVIEW; SRC-DAVID-OVERVIEW | T79: Editorial | U79: Needs Review | V79: Draft
A80: v0.1 | B80: Bible_Journey_Canon_Map_v0_1_Genesis_to_2Samuel.xlsx | C80: CRS-1SA-002 | D80: 760 | E80: 1 | F80: 1 Samuel | G80: Rise of the Monarchy | H80: Ark narrative | I80: The ark captured, returned, and restored | J80: 1 Samuel 4-7 | K80: High | L80: High | N80: Read the assigned main-spine block in full. | O80: Read primary block; continue to next chronological set. | P80: No | Q80: Samuel; Rise of the Monarchy | S80: SRC-TEXT-1SAM; SRC-SAMUEL-OVERVIEW; SRC-DAVID-OVERVIEW | T80: Editorial | U80: Needs Review | V80: Draft
A81: v0.1 | B81: Bible_Journey_Canon_Map_v0_1_Genesis_to_2Samuel.xlsx | C81: CRS-1SA-003 | D81: 770 | E81: 1 | F81: 1 Samuel | G81: Rise of the Monarchy | H81: Saul | I81: Israel asks for a king and Saul is chosen | J81: 1 Samuel 8-10 | K81: High | L81: High | N81: Read the assigned main-spine block in full. | O81: Read primary block; continue to next chronological set. | P81: No | Q81: Saul; Rise of the Monarchy | S81: SRC-TEXT-1SAM; SRC-SAMUEL-OVERVIEW; SRC-DAVID-OVERVIEW | T81: Editorial | U81: Needs Review | V81: Draft
A82: v0.1 | B82: Bible_Journey_Canon_Map_v0_1_Genesis_to_2Samuel.xlsx | C82: CRS-1SA-004 | D82: 780 | E82: 1 | F82: 1 Samuel | G82: Rise of the Monarchy | H82: Saul | I82: Saul delivers Jabesh and the kingdom is renewed | J82: 1 Samuel 11-12 | K82: High | L82: High | N82: Read the assigned main-spine block in full. | O82: Read primary block; continue to next chronological set. | P82: No | Q82: Saul; Rise of the Monarchy | S82: SRC-TEXT-1SAM; SRC-SAMUEL-OVERVIEW; SRC-DAVID-OVERVIEW | T82: Editorial | U82: Needs Review | V82: Draft
A83: v0.1 | B83: Bible_Journey_Canon_Map_v0_1_Genesis_to_2Samuel.xlsx | C83: CRS-1SA-005 | D83: 790 | E83: 1 | F83: 1 Samuel | G83: Rise of the Monarchy | H83: Saul | I83: Saul's early reign and rejection | J83: 1 Samuel 13-15 | K83: High | L83: High | N83: Read the assigned main-spine block in full. | O83: Read primary block; continue to next chronological set. | P83: No | Q83: Saul; Rise of the Monarchy | S83: SRC-TEXT-1SAM; SRC-SAMUEL-OVERVIEW; SRC-DAVID-OVERVIEW | T83: Editorial | U83: Needs Review | V83: Draft
A84: v0.1 | B84: Bible_Journey_Canon_Map_v0_1_Genesis_to_2Samuel.xlsx | C84: CRS-1SA-006 | D84: 800 | E84: 1 | F84: 1 Samuel | G84: Rise of the Monarchy | H84: David / Act I: The Chosen One | I84: David anointed and enters Saul's service | J84: 1 Samuel 16 | K84: High | L84: Probable | N84: Read the assigned main-spine block in full. | O84: Read primary block; continue to next chronological set. | P84: No | Q84: The Life of David; Saul | S84: SRC-TEXT-1SAM; SRC-SAMUEL-OVERVIEW; SRC-DAVID-OVERVIEW | T84: Editorial | U84: Needs Review | V84: Draft | W84: V0.1 follows the canonical sequence. The relation between David's early court service and the Goliath narrative is a documented editorial / source-critical discussion to be tracked separately.
A85: v0.1 | B85: Bible_Journey_Canon_Map_v0_1_Genesis_to_2Samuel.xlsx | C85: CRS-1SA-007 | D85: 810 | E85: 1 | F85: 1 Samuel | G85: Rise of the Monarchy | H85: David / Act I: The Chosen One | I85: David and Goliath | J85: 1 Samuel 17 | K85: High | L85: Probable | N85: Read the assigned main-spine block in full. | O85: Read primary block; continue to next chronological set. | P85: No | Q85: The Life of David | S85: SRC-TEXT-1SAM; SRC-SAMUEL-OVERVIEW; SRC-DAVID-OVERVIEW | T85: Editorial | U85: Needs Review | V85: Draft
A86: v0.1 | B86: Bible_Journey_Canon_Map_v0_1_Genesis_to_2Samuel.xlsx | C86: CRS-1SA-008 | D86: 820 | E86: 1 | F86: 1 Samuel | G86: Rise of the Monarchy | H86: David / Act I: The Chosen One | I86: David in Saul's court and covenant with Jonathan | J86: 1 Samuel 18 | K86: High | L86: Probable | N86: Read the assigned main-spine block in full. | O86: Read primary block; continue to next chronological set. | P86: No | Q86: The Life of David; Jonathan | S86: SRC-TEXT-1SAM; SRC-SAMUEL-OVERVIEW; SRC-DAVID-OVERVIEW | T86: Editorial | U86: Needs Review | V86: Draft
A87: v0.1 | B87: Bible_Journey_Canon_Map_v0_1_Genesis_to_2Samuel.xlsx | C87: CRS-1SA-009 | D87: 830 | E87: 1 | F87: 1 Samuel | G87: Rise of the Monarchy | H87: David / Act II: The Fugitive | I87: David escapes Saul's first pursuit | J87: 1 Samuel 19 | K87: High | L87: Probable | N87: Read all assigned blocks; external links marked required in Full Stream must be completed before full-event completion. | O87: Read primary block; clearly surface linked accounts as pending, never auto-complete. | P87: No | Q87: The Life of David | S87: SRC-TEXT-1SAM; SRC-SAMUEL-OVERVIEW; SRC-DAVID-OVERVIEW | T87: Editorial | U87: Needs Review | V87: Draft
A88: v0.1 | B88: Bible_Journey_Canon_Map_v0_1_Genesis_to_2Samuel.xlsx | C88: CRS-1SA-010 | D88: 840 | E88: 1 | F88: 1 Samuel | G88: Rise of the Monarchy | H88: David / Act II: The Fugitive | I88: David and Jonathan's covenant renewed | J88: 1 Samuel 20 | K88: High | L88: Probable | N88: Read the assigned main-spine block in full. | O88: Read primary block; continue to next chronological set. | P88: No | Q88: The Life of David; Jonathan | S88: SRC-TEXT-1SAM; SRC-SAMUEL-OVERVIEW; SRC-DAVID-OVERVIEW | T88: Editorial | U88: Needs Review | V88: Draft
A89: v0.1 | B89: Bible_Journey_Canon_Map_v0_1_Genesis_to_2Samuel.xlsx | C89: CRS-1SA-011 | D89: 850 | E89: 1 | F89: 1 Samuel | G89: Rise of the Monarchy | H89: David / Act II: The Fugitive | I89: David at Nob and Gath | J89: 1 Samuel 21 | K89: High | L89: Probable | N89: Read all assigned blocks; external links marked required in Full Stream must be completed before full-event completion. | O89: Read primary block; clearly surface linked accounts as pending, never auto-complete. | P89: No | Q89: The Life of David | S89: SRC-TEXT-1SAM; SRC-SAMUEL-OVERVIEW; SRC-DAVID-OVERVIEW | T89: Editorial | U89: Needs Review | V89: Draft
A90: v0.1 | B90: Bible_Journey_Canon_Map_v0_1_Genesis_to_2Samuel.xlsx | C90: CRS-1SA-012 | D90: 860 | E90: 1 | F90: 1 Samuel | G90: Rise of the Monarchy | H90: David / Act II: The Fugitive | I90: Adullam, the priests of Nob, and Doeg | J90: 1 Samuel 22 | K90: High | L90: Probable | N90: Read all assigned blocks; external links marked required in Full Stream must be completed before full-event completion. | O90: Read primary block; clearly surface linked accounts as pending, never auto-complete. | P90: No | Q90: The Life of David | S90: SRC-TEXT-1SAM; SRC-SAMUEL-OVERVIEW; SRC-DAVID-OVERVIEW | T90: Editorial | U90: Needs Review | V90: Draft
A91: v0.1 | B91: Bible_Journey_Canon_Map_v0_1_Genesis_to_2Samuel.xlsx | C91: CRS-1SA-013 | D91: 870 | E91: 1 | F91: 1 Samuel | G91: Rise of the Monarchy | H91: David / Act II: The Fugitive | I91: Keilah, Ziph, and David's wilderness flight | J91: 1 Samuel 23 | K91: High | L91: Probable | N91: Read all assigned blocks; external links marked required in Full Stream must be completed before full-event completion. | O91: Read primary block; clearly surface linked accounts as pending, never auto-complete. | P91: No | Q91: The Life of David | S91: SRC-TEXT-1SAM; SRC-SAMUEL-OVERVIEW; SRC-DAVID-OVERVIEW | T91: Editorial | U91: Needs Review | V91: Draft
A92: v0.1 | B92: Bible_Journey_Canon_Map_v0_1_Genesis_to_2Samuel.xlsx | C92: CRS-1SA-014 | D92: 880 | E92: 1 | F92: 1 Samuel | G92: Rise of the Monarchy | H92: David / Act II: The Fugitive | I92: David spares Saul at En-gedi | J92: 1 Samuel 24 | K92: High | L92: Probable | N92: Read all assigned blocks; external links marked required in Full Stream must be completed before full-event completion. | O92: Read primary block; clearly surface linked accounts as pending, never auto-complete. | P92: No | Q92: The Life of David | S92: SRC-TEXT-1SAM; SRC-SAMUEL-OVERVIEW; SRC-DAVID-OVERVIEW | T92: Editorial | U92: Needs Review | V92: Draft
A93: v0.1 | B93: Bible_Journey_Canon_Map_v0_1_Genesis_to_2Samuel.xlsx | C93: CRS-1SA-015 | D93: 890 | E93: 1 | F93: 1 Samuel | G93: Rise of the Monarchy | H93: David / Act II: The Fugitive | I93: Nabal, Abigail, and David's restraint | J93: 1 Samuel 25 | K93: High | L93: Probable | N93: Read the assigned main-spine block in full. | O93: Read primary block; continue to next chronological set. | P93: No | Q93: The Life of David | S93: SRC-TEXT-1SAM; SRC-SAMUEL-OVERVIEW; SRC-DAVID-OVERVIEW | T93: Editorial | U93: Needs Review | V93: Draft
A94: v0.1 | B94: Bible_Journey_Canon_Map_v0_1_Genesis_to_2Samuel.xlsx | C94: CRS-1SA-016 | D94: 900 | E94: 1 | F94: 1 Samuel | G94: Rise of the Monarchy | H94: David / Act II: The Fugitive | I94: David spares Saul in the wilderness of Ziph | J94: 1 Samuel 26 | K94: High | L94: Probable | N94: Read the assigned main-spine block in full. | O94: Read primary block; continue to next chronological set. | P94: No | Q94: The Life of David | S94: SRC-TEXT-1SAM; SRC-SAMUEL-OVERVIEW; SRC-DAVID-OVERVIEW | T94: Editorial | U94: Needs Review | V94: Draft
A95: v0.1 | B95: Bible_Journey_Canon_Map_v0_1_Genesis_to_2Samuel.xlsx | C95: CRS-1SA-017 | D95: 910 | E95: 1 | F95: 1 Samuel | G95: Rise of the Monarchy | H95: David / Act II: The Fugitive | I95: David among the Philistines | J95: 1 Samuel 27 | K95: High | L95: Probable | N95: Read the assigned main-spine block in full. | O95: Read primary block; continue to next chronological set. | P95: No | Q95: The Life of David | S95: SRC-TEXT-1SAM; SRC-SAMUEL-OVERVIEW; SRC-DAVID-OVERVIEW | T95: Editorial | U95: Needs Review | V95: Draft
A96: v0.1 | B96: Bible_Journey_Canon_Map_v0_1_Genesis_to_2Samuel.xlsx | C96: CRS-1SA-018 | D96: 920 | E96: 1 | F96: 1 Samuel | G96: Rise of the Monarchy | H96: Saul's final crisis | I96: Saul and the medium at Endor | J96: 1 Samuel 28 | K96: High | L96: Probable | N96: Read the assigned main-spine block in full. | O96: Read primary block; continue to next chronological set. | P96: No | Q96: Saul | S96: SRC-TEXT-1SAM; SRC-SAMUEL-OVERVIEW; SRC-DAVID-OVERVIEW | T96: Editorial | U96: Needs Review | V96: Draft
... A101: v0.1 | B101: Bible_Journey_Canon_Map_v0_1_Genesis_to_2Samuel.xlsx | C101: CRS-2SA-002 | D101: 970 | E101: 1 | F101: 2 Samuel | G101: United Monarchy | H101: David / Act III: The King | I101: Abner, Ish-bosheth, and the reunification of Israel | J101: 2 Samuel 3-4 | K101: High | L101: High | N101: Read the assigned main-spine block in full. | O101: Read primary block; continue to next chronological set. | P101: No | Q101: The Life of David | S101: SRC-TEXT-2SAM; SRC-SAMUEL-OVERVIEW; SRC-DAVID-OVERVIEW | T101: Editorial | U101: Needs Review | V101: Draft
A102: v0.1 | B102: Bible_Journey_Canon_Map_v0_1_Genesis_to_2Samuel.xlsx | C102: CRS-2SA-003 | D102: 980 | E102: 1 | F102: 2 Samuel | G102: United Monarchy | H102: David / Act III: The King | I102: David becomes king over all Israel and takes Jerusalem | J102: 2 Samuel 5 | K102: High | L102: High | N102: Read all assigned blocks; external links marked required in Full Stream must be completed before full-event completion. | O102: Read primary block; clearly surface linked accounts as pending, never auto-complete. | P102: Yes | Q102: The Life of David; United Monarchy | S102: SRC-TEXT-2SAM; SRC-TEXT-1CHR; SRC-SAMUEL-OVERVIEW; SRC-CHRONICLES-OVERVIEW; SRC-DAVID-OVERVIEW | T102: Editorial | U102: Needs Review | V102: Draft | W102: The main canonical chapter is 2 Samuel 5. 1 Chronicles 14 overlaps its latter section; the future verse-level model must prevent duplicate completion when the reader reaches the parallel.
A103: v0.1 | B103: Bible_Journey_Canon_Map_v0_1_Genesis_to_2Samuel.xlsx | C103: CRS-2SA-004 | D103: 990 | E103: 1 | F103: 2 Samuel | G103: United Monarchy | H103: David / Act III: The King | I103: The ark's first journey and Uzzah's death | J103: 2 Samuel 6 | K103: High | L103: High | N103: Read all assigned blocks; external links marked required in Full Stream must be completed before full-event completion. | O103: Read primary block; clearly surface linked accounts as pending, never auto-complete. | P103: Yes | Q103: The Life of David; Ark & Temple | S103: SRC-TEXT-2SAM; SRC-TEXT-1CHR; SRC-SAMUEL-OVERVIEW; SRC-CHRONICLES-OVERVIEW; SRC-DAVID-OVERVIEW | T103: Editorial | U103: Needs Review | V103: Draft | W103: 2 Samuel 6 combines the failed and successful ark movements; the future verse-level CRS must split this chapter into two precise Reading Sets to avoid duplicate placement. V0.1 marks this as a known refinement.
A104: v0.1 | B104: Bible_Journey_Canon_Map_v0_1_Genesis_to_2Samuel.xlsx | C104: CRS-2SA-005 | D104: 1000 | E104: 1 | F104: 2 Samuel | G104: United Monarchy | H104: David / Act III: The King | I104: The Davidic covenant | J104: 2 Samuel 7 | K104: High | L104: High | N104: Read all assigned blocks; external links marked required in Full Stream must be completed before full-event completion. | O104: Read primary block; clearly surface linked accounts as pending, never auto-complete. | P104: Yes | Q104: The Life of David; Covenant | S104: SRC-TEXT-2SAM; SRC-TEXT-1CHR; SRC-SAMUEL-OVERVIEW; SRC-CHRONICLES-OVERVIEW; SRC-DAVID-OVERVIEW | T104: Editorial | U104: Needs Review | V104: Draft
A105: v0.1 | B105: Bible_Journey_Canon_Map_v0_1_Genesis_to_2Samuel.xlsx | C105: CRS-2SA-006 | D105: 1010 | E105: 1 | F105: 2 Samuel | G105: United Monarchy | H105: David / Act III: The King | I105: David's victories and administration | J105: 2 Samuel 8 | K105: High | L105: High | N105: Read all assigned blocks; external links marked required in Full Stream must be completed before full-event completion. | O105: Read primary block; clearly surface linked accounts as pending, never auto-complete. | P105: Yes | Q105: The Life of David; United Monarchy | S105: SRC-TEXT-2SAM; SRC-TEXT-1CHR; SRC-SAMUEL-OVERVIEW; SRC-CHRONICLES-OVERVIEW; SRC-DAVID-OVERVIEW | T105: Editorial | U105: Needs Review | V105: Draft
A106: v0.1 | B106: Bible_Journey_Canon_Map_v0_1_Genesis_to_2Samuel.xlsx | C106: CRS-2SA-007 | D106: 1020 | E106: 1 | F106: 2 Samuel | G106: United Monarchy | H106: David / Act III: The King | I106: David and Mephibosheth | J106: 2 Samuel 9 | K106: High | L106: High | N106: Read the assigned main-spine block in full. | O106: Read primary block; continue to next chronological set. | P106: No | Q106: The Life of David; Jonathan | S106: SRC-TEXT-2SAM; SRC-SAMUEL-OVERVIEW; SRC-DAVID-OVERVIEW | T106: Editorial | U106: Needs Review | V106: Draft
A107: v0.1 | B107: Bible_Journey_Canon_Map_v0_1_Genesis_to_2Samuel.xlsx | C107: CRS-2SA-008 | D107: 1030 | E107: 1 | F107: 2 Samuel | G107: United Monarchy | H107: David / Act III: The King | I107: War with Ammon and Aram | J107: 2 Samuel 10 | K107: High | L107: High | N107: Read all assigned blocks; external links marked required in Full Stream must be completed before full-event completion. | O107: Read primary block; clearly surface linked accounts as pending, never auto-complete. | P107: Yes | Q107: The Life of David; United Monarchy | S107: SRC-TEXT-2SAM; SRC-TEXT-1CHR; SRC-SAMUEL-OVERVIEW; SRC-CHRONICLES-OVERVIEW; SRC-DAVID-OVERVIEW | T107: Editorial | U107: Needs Review | V107: Draft
A108: v0.1 | B108: Bible_Journey_Canon_Map_v0_1_Genesis_to_2Samuel.xlsx | C108: CRS-2SA-009 | D108: 1040 | E108: 1 | F108: 2 Samuel | G108: United Monarchy | H108: David / Act IV: The Fall | I108: David, Bathsheba, and Uriah | J108: 2 Samuel 11 | K108: High | L108: High | N108: Read the assigned main-spine block in full. | O108: Read primary block; continue to next chronological set. | P108: No | Q108: The Life of David | S108: SRC-TEXT-2SAM; SRC-SAMUEL-OVERVIEW; SRC-DAVID-OVERVIEW | T108: Editorial | U108: Needs Review | V108: Draft
A109: v0.1 | B109: Bible_Journey_Canon_Map_v0_1_Genesis_to_2Samuel.xlsx | C109: CRS-2SA-010 | D109: 1050 | E109: 1 | F109: 2 Samuel | G109: United Monarchy | H109: David / Act IV: The Fall | I109: Nathan confronts David and the consequences begin | J109: 2 Samuel 12 | K109: High | L109: High | N109: Read the assigned main-spine block in full. | O109: Read primary block; continue to next chronological set. | P109: No | Q109: The Life of David | S109: SRC-TEXT-2SAM; SRC-SAMUEL-OVERVIEW; SRC-DAVID-OVERVIEW | T109: Editorial | U109: Needs Review | V109: Draft
A110: v0.1 | B110: Bible_Journey_Canon_Map_v0_1_Genesis_to_2Samuel.xlsx | C110: CRS-2SA-011 | D110: 1060 | E110: 1 | F110: 2 Samuel | G110: United Monarchy | H110: David / Act IV: The Fall | I110: Amnon, Tamar, and Absalom | J110: 2 Samuel 13 | K110: High | L110: High | N110: Read the assigned main-spine block in full. | O110: Read primary block; continue to next chronological set. | P110: No | Q110: The Life of David | S110: SRC-TEXT-2SAM; SRC-SAMUEL-OVERVIEW; SRC-DAVID-OVERVIEW | T110: Editorial | U110: Needs Review | V110: Draft
A111: v0.1 | B111: Bible_Journey_Canon_Map_v0_1_Genesis_to_2Samuel.xlsx | C111: CRS-2SA-012 | D111: 1070 | E111: 1 | F111: 2 Samuel | G111: United Monarchy | H111: David / Act IV: The Fall | I111: Absalom returns to Jerusalem | J111: 2 Samuel 14 | K111: High | L111: High | N111: Read the assigned main-spine block in full. | O111: Read primary block; continue to next chronological set. | P111: No | Q111: The Life of David | S111: SRC-TEXT-2SAM; SRC-SAMUEL-OVERVIEW; SRC-DAVID-OVERVIEW | T111: Editorial | U111: Needs Review | V111: Draft
A112: v0.1 | B112: Bible_Journey_Canon_Map_v0_1_Genesis_to_2Samuel.xlsx | C112: CRS-2SA-013 | D112: 1080 | E112: 1 | F112: 2 Samuel | G112: United Monarchy | H112: David / Act IV: The Fall | I112: Absalom's rebellion begins | J112: 2 Samuel 15 | K112: High | L112: High | N112: Read the assigned main-spine block in full. | O112: Read primary block; continue to next chronological set. | P112: No | Q112: The Life of David | S112: SRC-TEXT-2SAM; SRC-SAMUEL-OVERVIEW; SRC-DAVID-OVERVIEW | T112: Editorial | U112: Needs Review | V112: Draft
A113: v0.1 | B113: Bible_Journey_Canon_Map_v0_1_Genesis_to_2Samuel.xlsx | C113: CRS-2SA-014 | D113: 1090 | E113: 1 | F113: 2 Samuel | G113: United Monarchy | H113: David / Act IV: The Fall | I113: David flees Jerusalem | J113: 2 Samuel 16 | K113: High | L113: High | N113: Read the assigned main-spine block in full. | O113: Read primary block; continue to next chronological set. | P113: No | Q113: The Life of David | S113: SRC-TEXT-2SAM; SRC-SAMUEL-OVERVIEW; SRC-DAVID-OVERVIEW | T113: Editorial | U113: Needs Review | V113: Draft
A114: v0.1 | B114: Bible_Journey_Canon_Map_v0_1_Genesis_to_2Samuel.xlsx | C114: CRS-2SA-015 | D114: 1100 | E114: 1 | F114: 2 Samuel | G114: United Monarchy | H114: David / Act IV: The Fall | I114: Counsel, pursuit, and Hushai's intervention | J114: 2 Samuel 17 | K114: High | L114: High | N114: Read the assigned main-spine block in full. | O114: Read primary block; continue to next chronological set. | P114: No | Q114: The Life of David | S114: SRC-TEXT-2SAM; SRC-SAMUEL-OVERVIEW; SRC-DAVID-OVERVIEW | T114: Editorial | U114: Needs Review | V114: Draft
A115: v0.1 | B115: Bible_Journey_Canon_Map_v0_1_Genesis_to_2Samuel.xlsx | C115: CRS-2SA-016 | D115: 1110 | E115: 1 | F115: 2 Samuel | G115: United Monarchy | H115: David / Act IV: The Fall | I115: Absalom's defeat and death | J115: 2 Samuel 18 | K115: High | L115: High | N115: Read the assigned main-spine block in full. | O115: Read primary block; continue to next chronological set. | P115: No | Q115: The Life of David | S115: SRC-TEXT-2SAM; SRC-SAMUEL-OVERVIEW; SRC-DAVID-OVERVIEW | T115: Editorial | U115: Needs Review | V115: Draft
A116: v0.1 | B116: Bible_Journey_Canon_Map_v0_1_Genesis_to_2Samuel.xlsx | C116: CRS-2SA-017 | D116: 1120 | E116: 1 | F116: 2 Samuel | G116: United Monarchy | H116: David / Act IV: The Fall | I116: David returns and Sheba rebels | J116: 2 Samuel 19-20 | K116: High | L116: High | N116: Read the assigned main-spine block in full. | O116: Read primary block; continue to next chronological set. | P116: No | Q116: The Life of David | S116: SRC-TEXT-2SAM; SRC-SAMUEL-OVERVIEW; SRC-DAVID-OVERVIEW | T116: Editorial | U116: Needs Review | V116: Draft
A117: v0.1 | B117: Bible_Journey_Canon_Map_v0_1_Genesis_to_2Samuel.xlsx | C117: CRS-2SA-018 | D117: 1130 | E117: 1 | F117: 2 Samuel | G117: United Monarchy | H117: David / Act V: The Legacy | I117: Famine, Gibeonites, and Philistine warriors | J117: 2 Samuel 21 | K117: High | L117: Debated | N117: Read all assigned blocks; external links marked required in Full Stream must be completed before full-event completion. | O117: Read primary block; clearly surface linked accounts as pending, never auto-complete. | P117: Yes | Q117: The Life of David; United Monarchy | S117: SRC-TEXT-2SAM; SRC-TEXT-1CHR; SRC-SAMUEL-OVERVIEW; SRC-CHRONICLES-OVERVIEW; SRC-DAVID-OVERVIEW | T117: Editorial | U117: Needs Review | V117: Draft | W117: 2 Samuel 21-24 functions as a literary appendix in the canonical book. Do not present the relative chronology as settled.
A118: v0.1 | B118: Bible_Journey_Canon_Map_v0_1_Genesis_to_2Samuel.xlsx | C118: CRS-2SA-019 | D118: 1140 | E118: 1 | F118: 2 Samuel | G118: United Monarchy | H118: David / Act V: The Legacy | I118: David's song of deliverance | J118: 2 Samuel 22 | K118: High | L118: Debated | N118: Read all assigned blocks; external links marked required in Full Stream must be completed before full-event completion. | O118: Read primary block; clearly surface linked accounts as pending, never auto-complete. | P118: Yes | Q118: The Life of David; Psalms | S118: SRC-TEXT-2SAM; SRC-SAMUEL-OVERVIEW; SRC-DAVID-OVERVIEW | T118: Editorial | U118: Needs Review | V118: Draft | W118: Placement is marked debated because the canonical appendix sequence does not necessarily establish a precise end-of-reign date.
A119: v0.1 | B119: Bible_Journey_Canon_Map_v0_1_Genesis_to_2Samuel.xlsx | C119: CRS-2SA-020 | D119: 1150 | E119: 1 | F119: 2 Samuel | G119: United Monarchy | H119: David / Act V: The Legacy | I119: David's final words and mighty men | J119: 2 Samuel 23 | K119: High | L119: Debated | N119: Read all assigned blocks; external links marked required in Full Stream must be completed before full-event completion. | O119: Read primary block; clearly surface linked accounts as pending, never auto-complete. | P119: Yes | Q119: The Life of David; United Monarchy | S119: SRC-TEXT-2SAM; SRC-TEXT-1CHR; SRC-SAMUEL-OVERVIEW; SRC-CHRONICLES-OVERVIEW; SRC-DAVID-OVERVIEW | T119: Editorial | U119: Needs Review | V119: Draft | W119: Placement is marked debated because 2 Samuel 21-24 is a literary appendix.
A120: v0.1 | B120: Bible_Journey_Canon_Map_v0_1_Genesis_to_2Samuel.xlsx | C120: CRS-2SA-021 | D120: 1160 | E120: 1 | F120: 2 Samuel | G120: United Monarchy | H120: David / Act V: The Legacy | I120: David's census and the altar site | J120: 2 Samuel 24 | K120: High | L120: Debated | N120: Read all assigned blocks; external links marked required in Full Stream must be completed before full-event completion. | O120: Read primary block; clearly surface linked accounts as pending, never auto-complete. | P120: Yes | Q120: The Life of David; Ark & Temple | S120: SRC-TEXT-2SAM; SRC-TEXT-1CHR; SRC-SAMUEL-OVERVIEW; SRC-CHRONICLES-OVERVIEW; SRC-DAVID-OVERVIEW | T120: Editorial | U120: Needs Review | V120: Draft | W120: Placement is marked debated because 2 Samuel 21-24 is a literary appendix; the event identity and parallel relationship are high confidence.
A121: v0.2 | B121: Bible_Journey_Canon_Map_v0_2_Chronicles_Psalms_Job_1Kings.xlsx | C121: CRS-1CH-007 | D121: 950.1 | E121: 2 | F121: 1 Chronicles | G121: Rise of the Monarchy | H121: Saul's death | I121: Saul dies at Gilboa: Chronicles account | J121: 1 Chronicles 10 | K121: High | L121: High | M121: Attach to v0.1 event | N121: Read this block as part of the linked event before Full Stream completion. | O121: Show as a linked account; keep it pending unless the reader chooses to continue this event. | P121: Yes | Q121: Saul; The Life of David | R121: CRS-1SA-021 | S121: SRC-TEXT-1CHR; SRC-CHRONICLES-OVERVIEW; SRC-CHRONICLES-BP | T121: Editorial | U121: Needs Review | W121: Parallel Chronicles account of Saul's death. Read after 1 Samuel 31 in Complete Chronological Reading.
A122: v0.2 | B122: Bible_Journey_Canon_Map_v0_2_Chronicles_Psalms_Job_1Kings.xlsx | C122: CRS-1CH-009 | D122: 975.5 | E122: 2 | F122: 1 Chronicles | G122: United Monarchy | H122: David's supporters | I122: David's supporters gather to him | J122: 1 Chronicles 12 | K122: High | L122: Probable | M122: Contextual composite / multi-event window | N122: Read this collection window in full; chronology is disclosed as unresolved or broad. | O122: Offer as an identified collection window; never imply a precise historical date. | P122: No | Q122: The Life of David; United Monarchy | R122: CRS-1SA-011–020; CRS-2SA-001 | S122: SRC-TEXT-1CHR; SRC-CHRONICLES-OVERVIEW; SRC-CHRONICLES-BP | T122: Editorial | U122: Needs Review | W122: Chronicles gathers supporters from multiple phases of David's rise. Do not force it into a single episode without verse-level review.
A123: v0.2 | B123: Bible_Journey_Canon_Map_v0_2_Chronicles_Psalms_Job_1Kings.xlsx | C123: CRS-1CH-008 | D123: 980.1 | E123: 2 | F123: 1 Chronicles | G123: United Monarchy | H123: David becomes king | I123: David becomes king and takes Jerusalem: Chronicles account | J123: 1 Chronicles 11 | K123: High | L123: High | M123: Attach to v0.1 event | N123: Read this block as part of the linked event before Full Stream completion. | O123: Show as a linked account; keep it pending unless the reader chooses to continue this event. | P123: Yes | Q123: The Life of David; United Monarchy | R123: CRS-2SA-003 | S123: SRC-TEXT-1CHR; SRC-CHRONICLES-OVERVIEW; SRC-CHRONICLES-BP | T123: Editorial | U123: Needs Review | W123: Parallel/complimentary account attached to David's unification and capture of Jerusalem.
A124: v0.2 | B124: Bible_Journey_Canon_Map_v0_2_Chronicles_Psalms_Job_1Kings.xlsx | C124: CRS-1CH-011 | D124: 980.2 | E124: 2 | F124: 1 Chronicles | G124: United Monarchy | H124: Jerusalem and Philistine wars | I124: David's palace and wars with the Philistines: Chronicles account | J124: 1 Chronicles 14 | K124: High | L124: High | M124: Attach to v0.1 event | N124: Read this block as part of the linked event before Full Stream completion. | O124: Show as a linked account; keep it pending unless the reader chooses to continue this event. | P124: Yes | Q124: The Life of David; United Monarchy | R124: CRS-2SA-003 | S124: SRC-TEXT-1CHR; SRC-CHRONICLES-OVERVIEW; SRC-CHRONICLES-BP | T124: Editorial | U124: Needs Review | W124: Chronicles parallel to parts of 2 Samuel 5. Must be placed within the event rather than read as a later duplicate.
A125: v0.2 | B125: Bible_Journey_Canon_Map_v0_2_Chronicles_Psalms_Job_1Kings.xlsx | C125: CRS-1CH-010 | D125: 990.1 | E125: 2 | F125: 1 Chronicles | G125: United Monarchy | H125: The ark's first journey | I125: The ark's first journey and Uzzah's death: Chronicles account | J125: 1 Chronicles 13 | K125: High | L125: High | M125: Attach to v0.1 event | N125: Read this block as part of the linked event before Full Stream completion. | O125: Show as a linked account; keep it pending unless the reader chooses to continue this event. | P125: Yes | Q125: The Life of David; Ark & Temple | R125: CRS-2SA-004 | S125: SRC-TEXT-1CHR; SRC-CHRONICLES-OVERVIEW; SRC-CHRONICLES-BP | T125: Editorial | U125: Needs Review | W125: Parallel account of the failed ark transport. Requires verse-level split in 2 Samuel 6 for exact sequencing.
A126: v0.2 | B126: Bible_Journey_Canon_Map_v0_2_Chronicles_Psalms_Job_1Kings.xlsx | C126: CRS-1CH-012 | D126: 990.2 | E126: 2 | F126: 1 Chronicles | G126: United Monarchy | H126: The ark enters Jerusalem | I126: The ark enters Jerusalem and David's liturgy | J126: 1 Chronicles 15-16 | K126: High | L126: High | M126: Attach to v0.1 event | N126: Read this block as part of the linked event before Full Stream completion. | O126: Show as a linked account; keep it pending unless the reader chooses to continue this event. | P126: Yes | Q126: The Life of David; Ark & Temple; Psalms | R126: CRS-2SA-004 | S126: SRC-TEXT-1CHR; SRC-CHRONICLES-OVERVIEW; SRC-CHRONICLES-BP | T126: Editorial | U126: Needs Review | W126: Chronicles' successful ark movement overlaps 2 Samuel 6 and adds unique liturgical material in chapter 16.
A127: v0.2 | B127: Bible_Journey_Canon_Map_v0_2_Chronicles_Psalms_Job_1Kings.xlsx | C127: CRS-1CH-013 | D127: 1000.1 | E127: 2 | F127: 1 Chronicles | G127: United Monarchy | H127: Davidic covenant | I127: The Davidic covenant: Chronicles account | J127: 1 Chronicles 17 | K127: High | L127: High | M127: Attach to v0.1 event | N127: Read this block as part of the linked event before Full Stream completion. | O127: Show as a linked account; keep it pending unless the reader chooses to continue this event. | P127: Yes | Q127: The Life of David; Covenant | R127: CRS-2SA-005 | S127: SRC-TEXT-1CHR; SRC-CHRONICLES-OVERVIEW; SRC-CHRONICLES-BP | T127: Editorial | U127: Needs Review | W127: Parallel account of the covenant promise. Keep text intact and distinguish wording from 2 Samuel 7.
A128: v0.2 | B128: Bible_Journey_Canon_Map_v0_2_Chronicles_Psalms_Job_1Kings.xlsx | C128: CRS-1CH-014 | D128: 1010.1 | E128: 2 | F128: 1 Chronicles | G128: United Monarchy | H128: David's victories | I128: David's victories and administration: Chronicles account | J128: 1 Chronicles 18 | K128: High | L128: High | M128: Attach to v0.1 event | N128: Read this block as part of the linked event before Full Stream completion. | O128: Show as a linked account; keep it pending unless the reader chooses to continue this event. | P128: Yes | Q128: The Life of David; United Monarchy | R128: CRS-2SA-006 | S128: SRC-TEXT-1CHR; SRC-CHRONICLES-OVERVIEW; SRC-CHRONICLES-BP | T128: Editorial | U128: Needs Review | W128: Parallel account to David's victories and administration in 2 Samuel 8.
A129: v0.2 | B129: Bible_Journey_Canon_Map_v0_2_Chronicles_Psalms_Job_1Kings.xlsx | C129: CRS-1CH-015 | D129: 1030.1 | E129: 2 | F129: 1 Chronicles | G129: United Monarchy | H129: War with Ammon and Aram | I129: War with Ammon and Aram: Chronicles account | J129: 1 Chronicles 19 | K129: High | L129: High | M129: Attach to v0.1 event | N129: Read this block as part of the linked event before Full Stream completion. | O129: Show as a linked account; keep it pending unless the reader chooses to continue this event. | P129: Yes | Q129: The Life of David; United Monarchy | R129: CRS-2SA-008 | S129: SRC-TEXT-1CHR; SRC-CHRONICLES-OVERVIEW; SRC-CHRONICLES-BP | T129: Editorial | U129: Needs Review | W129: Parallel account to 2 Samuel 10.
A130: v0.2 | B130: Bible_Journey_Canon_Map_v0_2_Chronicles_Psalms_Job_1Kings.xlsx | C130: CRS-1CH-016 | D130: 1100.5 | E130: 2 | F130: 1 Chronicles | G130: United Monarchy | H130: Rabbah and Philistine giants | I130: Rabbah and Philistine giants: Chronicles accounts | J130: 1 Chronicles 20 | K130: High | L130: Debated | M130: Contextual composite / multi-event window | N130: Read this collection window in full; chronology is disclosed as unresolved or broad. | O130: Offer as an identified collection window; never imply a precise historical date. | P130: Yes | Q130: The Life of David; United Monarchy | R130: CRS-2SA-010; CRS-2SA-018 | S130: SRC-TEXT-1CHR; SRC-CHRONICLES-OVERVIEW; SRC-CHRONICLES-BP | T130: Editorial | U130: Needs Review | W130: Chronicles chapter combines material corresponding to the capture of Rabbah and later giant-warrior notices. It spans more than one v0.1 event.
A131: v0.2 | B131: Bible_Journey_Canon_Map_v0_2_Chronicles_Psalms_Job_1Kings.xlsx | C131: CRS-1CH-017 | D131: 1160.1 | E131: 2 | F131: 1 Chronicles | G131: United Monarchy | H131: David's census and altar | I131: David's census and altar site: Chronicles account | J131: 1 Chronicles 21 | K131: High | L131: Debated | M131: Attach to v0.1 event | N131: Read this block as part of the linked event before Full Stream completion. | O131: Show as a linked account; keep it pending unless the reader chooses to continue this event. | P131: Yes | Q131: The Life of David; Ark & Temple | R131: CRS-2SA-021 | S131: SRC-TEXT-1CHR; SRC-CHRONICLES-OVERVIEW; SRC-CHRONICLES-BP | T131: Editorial | U131: Needs Review | W131: Parallel account to David's census and altar purchase. Event identity is high; end-of-reign placement remains debated.
A132: v0.2 | B132: Bible_Journey_Canon_Map_v0_2_Chronicles_Psalms_Job_1Kings.xlsx | C132: CRS-1CH-018 | D132: 1165 | E132: 2 | F132: 1 Chronicles | G132: United Monarchy | H132: Temple preparation | I132: David prepares for the temple | J132: 1 Chronicles 22 | K132: High | L132: Probable | M132: New main-spine bridge | N132: Read the assigned primary block in full before continuing. | O132: Read primary block; continue to the next chronological set. | P132: No | Q132: The Life of David; Ark & Temple; Solomon | S132: SRC-TEXT-1CHR; SRC-CHRONICLES-OVERVIEW; SRC-CHRONICLES-BP | T132: Editorial | U132: Needs Review | W132: Unique Chronicles material that functions as a bridge from David's altar/temple site to Solomon's reign.
A133: v0.2 | B133: Bible_Journey_Canon_Map_v0_2_Chronicles_Psalms_Job_1Kings.xlsx | C133: CRS-1CH-019 | D133: 1166 | E133: 2 | F133: 1 Chronicles | G133: United Monarchy | H133: Temple administration | I133: Levites, priests, musicians, gatekeepers, officials, and military divisions | J133: 1 Chronicles 23-27 | K133: High | L133: Probable | M133: New main-spine bridge | N133: Read the assigned primary block in full before continuing. | O133: Read primary block; continue to the next chronological set. | P133: No | Q133: The Life of David; Ark & Temple; Solomon | S133: SRC-TEXT-1CHR; SRC-CHRONICLES-OVERVIEW; SRC-CHRONICLES-BP | T133: Editorial | U133: Needs Review | W133: Chronicles-specific administrative and cultic preparations. Treat as a late-David collection, not a day-by-day sequence.
A134: v0.2 | B134: Bible_Journey_Canon_Map_v0_2_Chronicles_Psalms_Job_1Kings.xlsx | C134: CRS-1CH-020 | D134: 1167 | E134: 2 | F134: 1 Chronicles | G134: United Monarchy | H134: David's final assembly and Solomon's succession | I134: David's final assembly, temple charge, and Solomon's succession | J134: 1 Chronicles 28-29 | K134: High | L134: Probable | M134: New main-spine bridge | N134: Read the assigned primary block in full before continuing. | O134: Read primary block; continue to the next chronological set. | P134: Yes | Q134: The Life of David; Solomon; Ark & Temple | R134: CRS-1KG-001; CRS-1KG-002 | S134: SRC-TEXT-1CHR; SRC-CHRONICLES-OVERVIEW; SRC-CHRONICLES-BP | T134: Editorial | U134: Needs Review | W134: Late-David conclusion that overlaps conceptually with 1 Kings 1-2 but offers distinct temple-focused framing.
A135: v0.2 | B135: Bible_Journey_Canon_Map_v0_2_Chronicles_Psalms_Job_1Kings.xlsx | C135: CRS-1KG-001 | D135: 1170 | E135: 2 | F135: 1 Kings | G135: United Monarchy | H135: Solomon's accession | I135: Adonijah's bid and Solomon's accession | J135: 1 Kings 1 | K135: High | L135: High | M135: New main-spine continuation | N135: Read the assigned primary block in full before continuing. | O135: Read primary block; continue to the next chronological set. | P135: No | Q135: The Life of David; Solomon | S135: SRC-TEXT-1KGS; SRC-KINGS-OVERVIEW; SRC-KINGS-BP; SRC-SOLOMON-OVERVIEW; SRC-DIVIDED-MONARCHY | T135: Editorial | U135: Needs Review | W135: Transition after late-David Chronicles material; later harmonization with 1 Chronicles 29 remains open.
A136: v0.2 | B136: Bible_Journey_Canon_Map_v0_2_Chronicles_Psalms_Job_1Kings.xlsx | C136: CRS-1KG-002 | D136: 1180 | E136: 2 | F136: 1 Kings | G136: United Monarchy | H136: Solomon's accession | I136: David's death and Solomon secures the throne | J136: 1 Kings 2 | K136: High | L136: High | M136: New main-spine continuation | N136: Read the assigned primary block in full before continuing. | O136: Read primary block; continue to the next chronological set. | P136: No | Q136: The Life of David; Solomon | S136: SRC-TEXT-1KGS; SRC-KINGS-OVERVIEW; SRC-KINGS-BP; SRC-SOLOMON-OVERVIEW; SRC-DIVIDED-MONARCHY | T136: Editorial | U136: Needs Review | W136: Chronological continuation of succession; compare at study level with Chronicles' final assembly framing.
A137: v0.2 | B137: Bible_Journey_Canon_Map_v0_2_Chronicles_Psalms_Job_1Kings.xlsx | C137: CRS-1KG-003 | D137: 1190 | E137: 2 | F137: 1 Kings | G137: United Monarchy | H137: Solomon's wisdom | I137: Solomon asks for wisdom at Gibeon | J137: 1 Kings 3 | K137: High | L137: High | M137: New main-spine continuation | N137: Read the assigned primary block in full before continuing. | O137: Read primary block; continue to the next chronological set. | P137: Yes | Q137: Solomon; Wisdom | S137: SRC-TEXT-1KGS; SRC-KINGS-OVERVIEW; SRC-KINGS-BP; SRC-SOLOMON-OVERVIEW; SRC-DIVIDED-MONARCHY | T137: Editorial | U137: Needs Review | W137: Future dependency: 2 Chronicles 1 provides a related account, outside current scope.
A138: v0.2 | B138: Bible_Journey_Canon_Map_v0_2_Chronicles_Psalms_Job_1Kings.xlsx | C138: CRS-1KG-004 | D138: 1200 | E138: 2 | F138: 1 Kings | G138: United Monarchy | H138: Solomon's administration | I138: Solomon's administration, prosperity, and wisdom | J138: 1 Kings 4 | K138: High | L138: High | M138: New main-spine continuation | N138: Read the assigned primary block in full before continuing. | O138: Read primary block; continue to the next chronological set. | P138: No | Q138: Solomon; Wisdom | S138: SRC-TEXT-1KGS; SRC-KINGS-OVERVIEW; SRC-KINGS-BP; SRC-SOLOMON-OVERVIEW; SRC-DIVIDED-MONARCHY | T138: Editorial | U138: Needs Review | W138: Provides narrative window for wisdom traditions, but not proof that each Solomonic work was composed here.
A139: v0.2 | B139: Bible_Journey_Canon_Map_v0_2_Chronicles_Psalms_Job_1Kings.xlsx | C139: CRS-1KG-005 | D139: 1210 | E139: 2 | F139: 1 Kings | G139: United Monarchy | H139: The temple is built | I139: Solomon builds the temple | J139: 1 Kings 5-6 | K139: High | L139: High | M139: New main-spine continuation | N139: Read the assigned primary block in full before continuing. | O139: Read primary block; continue to the next chronological set. | P139: Yes | Q139: Solomon; Ark & Temple | S139: SRC-TEXT-1KGS; SRC-KINGS-OVERVIEW; SRC-KINGS-BP; SRC-SOLOMON-OVERVIEW; SRC-DIVIDED-MONARCHY | T139: Editorial | U139: Needs Review | W139: Future dependency: 2 Chronicles 2-3 provides a parallel/complementary account.
A140: v0.2 | B140: Bible_Journey_Canon_Map_v0_2_Chronicles_Psalms_Job_1Kings.xlsx | C140: CRS-1KG-006 | D140: 1220 | E140: 2 | F140: 1 Kings | G140: United Monarchy | H140: Temple and palace | I140: Temple furnishings and Solomon's palace | J140: 1 Kings 7 | K140: High | L140: High | M140: New main-spine continuation | N140: Read the assigned primary block in full before continuing. | O140: Read primary block; continue to the next chronological set. | P140: No | Q140: Solomon; Ark & Temple | S140: SRC-TEXT-1KGS; SRC-KINGS-OVERVIEW; SRC-KINGS-BP; SRC-SOLOMON-OVERVIEW; SRC-DIVIDED-MONARCHY | T140: Editorial | U140: Needs Review | W140: Continue temple construction and royal-household account. Future 2 Chronicles linkage is partial.
A141: v0.2 | B141: Bible_Journey_Canon_Map_v0_2_Chronicles_Psalms_Job_1Kings.xlsx | C141: CRS-1KG-007 | D141: 1230 | E141: 2 | F141: 1 Kings | G141: United Monarchy | H141: Temple dedication | I141: Solomon dedicates the temple | J141: 1 Kings 8 | K141: High | L141: High | M141: New main-spine continuation | N141: Read the assigned primary block in full before continuing. | O141: Read primary block; continue to the next chronological set. | P141: Yes | Q141: Solomon; Ark & Temple | S141: SRC-TEXT-1KGS; SRC-KINGS-OVERVIEW; SRC-KINGS-BP; SRC-SOLOMON-OVERVIEW; SRC-DIVIDED-MONARCHY | T141: Editorial | U141: Needs Review | W141: Future dependency: 2 Chronicles 5-7 offers parallel/complementary accounts; treat as a Compare Accounts flagship.
A142: v0.2 | B142: Bible_Journey_Canon_Map_v0_2_Chronicles_Psalms_Job_1Kings.xlsx | C142: CRS-1KG-008 | D142: 1240 | E142: 2 | F142: 1 Kings | G142: United Monarchy | H142: Solomon's later projects | I142: Divine response, royal projects, and international trade | J142: 1 Kings 9 | K142: High | L142: High | M142: New main-spine continuation | N142: Read the assigned primary block in full before continuing. | O142: Read primary block; continue to the next chronological set. | P142: No | Q142: Solomon; Ark & Temple | S142: SRC-TEXT-1KGS; SRC-KINGS-OVERVIEW; SRC-KINGS-BP; SRC-SOLOMON-OVERVIEW; SRC-DIVIDED-MONARCHY | T142: Editorial | U142: Needs Review | W142: Includes multiple project/trade notices. Retain chapter-level grouping until finer editorial splits are reviewed.
A143: v0.2 | B143: Bible_Journey_Canon_Map_v0_2_Chronicles_Psalms_Job_1Kings.xlsx | C143: CRS-1KG-009 | D143: 1250 | E143: 2 | F143: 1 Kings | G143: United Monarchy | H143: Solomon's fame | I143: The queen of Sheba and Solomon's wealth | J143: 1 Kings 10 | K143: High | L143: High | M143: New main-spine continuation | N143: Read the assigned primary block in full before continuing. | O143: Read primary block; continue to the next chronological set. | P143: Yes | Q143: Solomon; Wisdom | S143: SRC-TEXT-1KGS; SRC-KINGS-OVERVIEW; SRC-KINGS-BP; SRC-SOLOMON-OVERVIEW; SRC-DIVIDED-MONARCHY | T143: Editorial | U143: Needs Review | W143: Future dependency: 2 Chronicles 9 has a related account.
A144: v0.2 | B144: Bible_Journey_Canon_Map_v0_2_Chronicles_Psalms_Job_1Kings.xlsx | C144: CRS-1KG-010 | D144: 1260 | E144: 2 | F144: 1 Kings | G144: United Monarchy | H144: Solomon's decline | I144: Solomon's decline and the division foretold | J144: 1 Kings 11 | K144: High | L144: High | M144: New main-spine continuation | N144: Read the assigned primary block in full before continuing. | O144: Read primary block; continue to the next chronological set. | P144: No | Q144: Solomon; Kingdom Divided | S144: SRC-TEXT-1KGS; SRC-KINGS-OVERVIEW; SRC-KINGS-BP; SRC-SOLOMON-OVERVIEW; SRC-DIVIDED-MONARCHY | T144: Editorial | U144: Needs Review | W144: Narrative transition from united monarchy to divided kingdom.
A145: v0.2 | B145: Bible_Journey_Canon_Map_v0_2_Chronicles_Psalms_Job_1Kings.xlsx | C145: CRS-1KG-011 | D145: 1270 | E145: 2 | F145: 1 Kings | G145: Divided Monarchy | H145: The kingdom divides | I145: Rehoboam and Jeroboam: the kingdom divides | J145: 1 Kings 12 | K145: High | L145: High | M145: New main-spine continuation | N145: Read the assigned primary block in full before continuing. | O145: Read primary block; continue to the next chronological set. | P145: Yes | Q145: Kingdom Divided | S145: SRC-TEXT-1KGS; SRC-KINGS-OVERVIEW; SRC-KINGS-BP; SRC-SOLOMON-OVERVIEW; SRC-DIVIDED-MONARCHY | T145: Editorial | U145: Needs Review | W145: Future dependency: 2 Chronicles 10 gives a parallel Judean-focused account.
A146: v0.2 | B146: Bible_Journey_Canon_Map_v0_2_Chronicles_Psalms_Job_1Kings.xlsx | C146: CRS-1KG-012 | D146: 1280 | E146: 2 | F146: 1 Kings | G146: Divided Monarchy | H146: Jeroboam's cult | I146: The man of God from Judah and Jeroboam's altar | J146: 1 Kings 13 | K146: High | L146: High | M146: New main-spine continuation | N146: Read the assigned primary block in full before continuing. | O146: Read primary block; continue to the next chronological set. | P146: No | Q146: Kingdom Divided; Prophets & Kings | S146: SRC-TEXT-1KGS; SRC-KINGS-OVERVIEW; SRC-KINGS-BP; SRC-SOLOMON-OVERVIEW; SRC-DIVIDED-MONARCHY | T146: Editorial | U146: Needs Review | W146: Prophetic episode during Jeroboam's reign. Keep separate from royal synchronization tables.
... A155: v0.2 | B155: Bible_Journey_Canon_Map_v0_2_Chronicles_Psalms_Job_1Kings.xlsx | C155: CRS-1KG-021 | D155: 1370 | E155: 2 | F155: 1 Kings | G155: Divided Monarchy | H155: Ahab's death | I155: Micaiah, Ahab's death, and Jehoshaphat | J155: 1 Kings 22 | K155: High | L155: High | M155: New main-spine continuation | N155: Read the assigned primary block in full before continuing. | O155: Read primary block; continue to the next chronological set. | P155: Yes | Q155: Ahab; Prophets & Kings; Kingdom Divided | S155: SRC-TEXT-1KGS; SRC-KINGS-OVERVIEW; SRC-KINGS-BP; SRC-SOLOMON-OVERVIEW; SRC-DIVIDED-MONARCHY | T155: Editorial | U155: Needs Review | W155: Future dependency: 2 Chronicles 18 offers parallel Ahab/Micaiah material.
A156: v0.2 | B156: Bible_Journey_Canon_Map_v0_2_Chronicles_Psalms_Job_1Kings.xlsx | C156: CRS-1CH-001 | E156: 2 | F156: 1 Chronicles | G156: Genealogical retrospective | H156: Origins through Judah | I156: Genealogies from Adam to Judah | J156: 1 Chronicles 1-2 | K156: High | L156: Unresolved | M156: Auxiliary collection / no fixed event placement | N156: Read this collection window in full; chronology is disclosed as unresolved or broad. | O156: Offer as an identified collection window; never imply a precise historical date. | P156: No | Q156: Genealogies; Davidic Line | S156: SRC-TEXT-1CHR; SRC-CHRONICLES-OVERVIEW; SRC-CHRONICLES-BP | T156: Editorial | U156: Needs Review | W156: Retrospective genealogies span multiple eras. Treat as a literary/genealogical collection, not a new event after 2 Samuel.
A157: v0.2 | B157: Bible_Journey_Canon_Map_v0_2_Chronicles_Psalms_Job_1Kings.xlsx | C157: CRS-1CH-002 | E157: 2 | F157: 1 Chronicles | G157: Genealogical retrospective | H157: Davidic and Judahite lines | I157: Davidic line and clans of Judah | J157: 1 Chronicles 3-4 | K157: High | L157: Unresolved | M157: Auxiliary collection / no fixed event placement | N157: Read this collection window in full; chronology is disclosed as unresolved or broad. | O157: Offer as an identified collection window; never imply a precise historical date. | P157: No | Q157: Genealogies; Davidic Line | S157: SRC-TEXT-1CHR; SRC-CHRONICLES-OVERVIEW; SRC-CHRONICLES-BP | T157: Editorial | U157: Needs Review | W157: Includes the Davidic line but also later genealogical material. Do not present as a continuous event chronology.
A158: v0.2 | B158: Bible_Journey_Canon_Map_v0_2_Chronicles_Psalms_Job_1Kings.xlsx | C158: CRS-1CH-003 | E158: 2 | F158: 1 Chronicles | G158: Genealogical retrospective | H158: Tribal lines | I158: Transjordanian tribal lines | J158: 1 Chronicles 5 | K158: High | L158: Unresolved | M158: Auxiliary collection / no fixed event placement | N158: Read this collection window in full; chronology is disclosed as unresolved or broad. | O158: Offer as an identified collection window; never imply a precise historical date. | P158: No | Q158: Genealogies; Israel's Tribes | S158: SRC-TEXT-1CHR; SRC-CHRONICLES-OVERVIEW; SRC-CHRONICLES-BP | T158: Editorial | U158: Needs Review | W158: Genealogical and tribal retrospective; includes later notices that span several periods.
A159: v0.2 | B159: Bible_Journey_Canon_Map_v0_2_Chronicles_Psalms_Job_1Kings.xlsx | C159: CRS-1CH-004 | E159: 2 | F159: 1 Chronicles | G159: Genealogical retrospective | H159: Levitical and priestly line | I159: Levi, priests, and temple line | J159: 1 Chronicles 6 | K159: High | L159: Unresolved | M159: Auxiliary collection / no fixed event placement | N159: Read this collection window in full; chronology is disclosed as unresolved or broad. | O159: Offer as an identified collection window; never imply a precise historical date. | P159: No | Q159: Genealogies; Temple & Priesthood | S159: SRC-TEXT-1CHR; SRC-CHRONICLES-OVERVIEW; SRC-CHRONICLES-BP | T159: Editorial | U159: Needs Review | W159: A genealogical account of Levitical and priestly lines; use as contextual support across the temple stream.
A160: v0.2 | B160: Bible_Journey_Canon_Map_v0_2_Chronicles_Psalms_Job_1Kings.xlsx | C160: CRS-1CH-005 | E160: 2 | F160: 1 Chronicles | G160: Genealogical retrospective | H160: Northern tribal lines | I160: Tribal lines and Benjamin | J160: 1 Chronicles 7-8 | K160: High | L160: Unresolved | M160: Auxiliary collection / no fixed event placement | N160: Read this collection window in full; chronology is disclosed as unresolved or broad. | O160: Offer as an identified collection window; never imply a precise historical date. | P160: No | Q160: Genealogies; Israel's Tribes; Saul | S160: SRC-TEXT-1CHR; SRC-CHRONICLES-OVERVIEW; SRC-CHRONICLES-BP | T160: Editorial | U160: Needs Review | W160: Retrospective tribal material culminating in Benjaminite lines relevant to Saul's house.
A161: v0.2 | B161: Bible_Journey_Canon_Map_v0_2_Chronicles_Psalms_Job_1Kings.xlsx | C161: CRS-1CH-006 | E161: 2 | F161: 1 Chronicles | G161: Postexilic retrospective | H161: Jerusalem and temple personnel | I161: Postexilic Jerusalem and temple personnel | J161: 1 Chronicles 9 | K161: High | L161: Unresolved | M161: Auxiliary collection / postexilic retrospective | N161: Read this collection window in full; chronology is disclosed as unresolved or broad. | O161: Offer as an identified collection window; never imply a precise historical date. | P161: No | Q161: Genealogies; Temple & Priesthood | S161: SRC-TEXT-1CHR; SRC-CHRONICLES-OVERVIEW; SRC-CHRONICLES-BP | T161: Editorial | U161: Needs Review | W161: Chronicles turns from broad genealogy to postexilic Jerusalem residents and temple personnel. Keep separate from David-era chronology.
...

Sheet Master Reading Blocks
A1: MASTER READING BLOCKS
A2: Normalized inventory of intact canonical blocks. These are future passage-level units for Reader, progress logic, and Compare Accounts.
A4: Map Version | B4: Source Workbook | C4: Local Block ID | D4: Parent CRS ID | E4: Display / Block Order | F4: Book | G4: Passage / Reference | H4: Block Role | I4: In Scope | J4: Required in Full Stream | K4: Narrative Flow Default | L4: Event / Setting Confidence | M4: Placement Confidence | N4: Integration / Anchor / Exception | O4: Target CRS / Compare Group | P4: End-User Label | Q4: Source Keys | R4: QA / Review Status | S4: Why It Appears Here / Notes
A5: v0.1 | B5: Bible_Journey_Canon_Map_v0_1_Genesis_to_2Samuel.xlsx | C5: BLK-GEN-001-01 | D5: CRS-GEN-001 | E5: 1 | F5: Genesis | G5: 1-3 | H5: Primary Account | I5: Yes | J5: Yes | K5: Yes | L5: High | M5: High | N5: Genesis | P5: Primary account | Q5: SRC-TEXT-TORAH; SRC-TORAH-OVERVIEW | R5: Needs Review | S5: Canonical spine reading block for Creation, garden, and fall.
A6: v0.1 | B6: Bible_Journey_Canon_Map_v0_1_Genesis_to_2Samuel.xlsx | C6: BLK-GEN-002-01 | D6: CRS-GEN-002 | E6: 1 | F6: Genesis | G6: 4-5 | H6: Primary Account | I6: Yes | J6: Yes | K6: Yes | L6: High | M6: High | N6: Genesis | P6: Primary account | Q6: SRC-TEXT-TORAH; SRC-TORAH-OVERVIEW | R6: Needs Review | S6: Canonical spine reading block for Cain, Seth, and the pre-flood line.
A7: v0.1 | B7: Bible_Journey_Canon_Map_v0_1_Genesis_to_2Samuel.xlsx | C7: BLK-GEN-003-01 | D7: CRS-GEN-003 | E7: 1 | F7: Genesis | G7: 6-9 | H7: Primary Account | I7: Yes | J7: Yes | K7: Yes | L7: High | M7: High | N7: Genesis | P7: Primary account | Q7: SRC-TEXT-TORAH; SRC-TORAH-OVERVIEW | R7: Needs Review | S7: Canonical spine reading block for The flood and Noahic covenant.
A8: v0.1 | B8: Bible_Journey_Canon_Map_v0_1_Genesis_to_2Samuel.xlsx | C8: BLK-GEN-004-01 | D8: CRS-GEN-004 | E8: 1 | F8: Genesis | G8: 10-11 | H8: Primary Account | I8: Yes | J8: Yes | K8: Yes | L8: High | M8: High | N8: Genesis | P8: Primary account | Q8: SRC-TEXT-TORAH; SRC-TORAH-OVERVIEW | R8: Needs Review | S8: Canonical spine reading block for Nations and the tower of Babel.
A9: v0.1 | B9: Bible_Journey_Canon_Map_v0_1_Genesis_to_2Samuel.xlsx | C9: BLK-GEN-005-01 | D9: CRS-GEN-005 | E9: 1 | F9: Genesis | G9: 12-14 | H9: Primary Account | I9: Yes | J9: Yes | K9: Yes | L9: High | M9: High | N9: Genesis | P9: Primary account | Q9: SRC-TEXT-TORAH; SRC-TORAH-OVERVIEW | R9: Needs Review | S9: Canonical spine reading block for Abram's call, separation, and rescue of Lot.
A10: v0.1 | B10: Bible_Journey_Canon_Map_v0_1_Genesis_to_2Samuel.xlsx | C10: BLK-GEN-006-01 | D10: CRS-GEN-006 | E10: 1 | F10: Genesis | G10: 15-17 | H10: Primary Account | I10: Yes | J10: Yes | K10: Yes | L10: High | M10: High | N10: Genesis | P10: Primary account | Q10: SRC-TEXT-TORAH; SRC-TORAH-OVERVIEW | R10: Needs Review | S10: Canonical spine reading block for Covenant, Hagar, and the promised son.
A11: v0.1 | B11: Bible_Journey_Canon_Map_v0_1_Genesis_to_2Samuel.xlsx | C11: BLK-GEN-007-01 | D11: CRS-GEN-007 | E11: 1 | F11: Genesis | G11: 18-19 | H11: Primary Account | I11: Yes | J11: Yes | K11: Yes | L11: High | M11: High | N11: Genesis | P11: Primary account | Q11: SRC-TEXT-TORAH; SRC-TORAH-OVERVIEW | R11: Needs Review | S11: Canonical spine reading block for Sodom, Gomorrah, and Lot's escape.
A12: v0.1 | B12: Bible_Journey_Canon_Map_v0_1_Genesis_to_2Samuel.xlsx | C12: BLK-GEN-008-01 | D12: CRS-GEN-008 | E12: 1 | F12: Genesis | G12: 20-22 | H12: Primary Account | I12: Yes | J12: Yes | K12: Yes | L12: High | M12: High | N12: Genesis | P12: Primary account | Q12: SRC-TEXT-TORAH; SRC-TORAH-OVERVIEW | R12: Needs Review | S12: Canonical spine reading block for Abimelech, Isaac's birth, and Moriah.
A13: v0.1 | B13: Bible_Journey_Canon_Map_v0_1_Genesis_to_2Samuel.xlsx | C13: BLK-GEN-009-01 | D13: CRS-GEN-009 | E13: 1 | F13: Genesis | G13: 23-25 | H13: Primary Account | I13: Yes | J13: Yes | K13: Yes | L13: High | M13: High | N13: Genesis | P13: Primary account | Q13: SRC-TEXT-TORAH; SRC-TORAH-OVERVIEW | R13: Needs Review | S13: Canonical spine reading block for Sarah's burial, Rebekah, and Abraham's final years.
A14: v0.1 | B14: Bible_Journey_Canon_Map_v0_1_Genesis_to_2Samuel.xlsx | C14: BLK-GEN-010-01 | D14: CRS-GEN-010 | E14: 1 | F14: Genesis | G14: 26-28 | H14: Primary Account | I14: Yes | J14: Yes | K14: Yes | L14: High | M14: High | N14: Genesis | P14: Primary account | Q14: SRC-TEXT-TORAH; SRC-TORAH-OVERVIEW | R14: Needs Review | S14: Canonical spine reading block for Isaac's household and Jacob's departure.
A15: v0.1 | B15: Bible_Journey_Canon_Map_v0_1_Genesis_to_2Samuel.xlsx | C15: BLK-GEN-011-01 | D15: CRS-GEN-011 | E15: 1 | F15: Genesis | G15: 29-31 | H15: Primary Account | I15: Yes | J15: Yes | K15: Yes | L15: High | M15: High | N15: Genesis | P15: Primary account | Q15: SRC-TEXT-TORAH; SRC-TORAH-OVERVIEW | R15: Needs Review | S15: Canonical spine reading block for Jacob in Haran.
A16: v0.1 | B16: Bible_Journey_Canon_Map_v0_1_Genesis_to_2Samuel.xlsx | C16: BLK-GEN-012-01 | D16: CRS-GEN-012 | E16: 1 | F16: Genesis | G16: 32-33 | H16: Primary Account | I16: Yes | J16: Yes | K16: Yes | L16: High | M16: High | N16: Genesis | P16: Primary account | Q16: SRC-TEXT-TORAH; SRC-TORAH-OVERVIEW | R16: Needs Review | S16: Canonical spine reading block for Jacob returns and is reconciled with Esau.
... A139: v0.1 | B139: Bible_Journey_Canon_Map_v0_1_Genesis_to_2Samuel.xlsx | C139: BLK-2SA-021-03 | D139: CRS-2SA-021 | E139: 3 | F139: 1 Chronicles | G139: 22:1 | H139: Supplementary Reading | I139: No | J139: Yes | K139: No | L139: High | M139: Debated | N139: 1 Chronicles | P139: Temple-site continuation | Q139: SRC-TEXT-1CHR; SRC-CHRONICLES-OVERVIEW | R139: Pending | S139: This verse connects the altar site to David's preparation for the temple. It is a continuation, not a duplicate.
A140: v0.2 | B140: Bible_Journey_Canon_Map_v0_2_Chronicles_Psalms_Job_1Kings.xlsx | C140: BLK-1CH-007-01 | D140: CRS-1CH-007 | E140: 1 | F140: 1 Chronicles | G140: 10 | H140: Parallel Account | I140: Yes | J140: Yes | K140: No | L140: High | M140: High | N140: Attach to v0.1 event | O140: CRS-1SA-021 | P140: Parallel Account | Q140: SRC-TEXT-1CHR; SRC-CHRONICLES-OVERVIEW; SRC-CHRONICLES-BP | R140: Needs Review | S140: Canonical-scope block for Saul dies at Gilboa: Chronicles account.
A141: v0.2 | B141: Bible_Journey_Canon_Map_v0_2_Chronicles_Psalms_Job_1Kings.xlsx | C141: BLK-1CH-009-01 | D141: CRS-1CH-009 | E141: 1 | F141: 1 Chronicles | G141: 12 | H141: Supplementary Reading | I141: Yes | J141: Yes | K141: No | L141: High | M141: Probable | N141: Contextual composite / multi-event window | O141: CRS-1SA-011–020; CRS-2SA-001 | P141: Supplementary Reading | Q141: SRC-TEXT-1CHR; SRC-CHRONICLES-OVERVIEW; SRC-CHRONICLES-BP | R141: Needs Review | S141: Canonical-scope block for David's supporters gather to him.
A142: v0.2 | B142: Bible_Journey_Canon_Map_v0_2_Chronicles_Psalms_Job_1Kings.xlsx | C142: BLK-1CH-008-01 | D142: CRS-1CH-008 | E142: 1 | F142: 1 Chronicles | G142: 11 | H142: Parallel Account | I142: Yes | J142: Yes | K142: No | L142: High | M142: High | N142: Attach to v0.1 event | O142: CRS-2SA-003 | P142: Parallel Account | Q142: SRC-TEXT-1CHR; SRC-CHRONICLES-OVERVIEW; SRC-CHRONICLES-BP | R142: Needs Review | S142: Canonical-scope block for David becomes king and takes Jerusalem: Chronicles account.
A143: v0.2 | B143: Bible_Journey_Canon_Map_v0_2_Chronicles_Psalms_Job_1Kings.xlsx | C143: BLK-1CH-011-01 | D143: CRS-1CH-011 | E143: 1 | F143: 1 Chronicles | G143: 14 | H143: Parallel Account | I143: Yes | J143: Yes | K143: No | L143: High | M143: High | N143: Attach to v0.1 event | O143: CRS-2SA-003 | P143: Parallel Account | Q143: SRC-TEXT-1CHR; SRC-CHRONICLES-OVERVIEW; SRC-CHRONICLES-BP | R143: Needs Review | S143: Canonical-scope block for David's palace and wars with the Philistines: Chronicles account.
A144: v0.2 | B144: Bible_Journey_Canon_Map_v0_2_Chronicles_Psalms_Job_1Kings.xlsx | C144: BLK-1CH-010-01 | D144: CRS-1CH-010 | E144: 1 | F144: 1 Chronicles | G144: 13 | H144: Parallel Account | I144: Yes | J144: Yes | K144: No | L144: High | M144: High | N144: Attach to v0.1 event | O144: CRS-2SA-004 | P144: Parallel Account | Q144: SRC-TEXT-1CHR; SRC-CHRONICLES-OVERVIEW; SRC-CHRONICLES-BP | R144: Needs Review | S144: Canonical-scope block for The ark's first journey and Uzzah's death: Chronicles account.
A145: v0.2 | B145: Bible_Journey_Canon_Map_v0_2_Chronicles_Psalms_Job_1Kings.xlsx | C145: BLK-1CH-012-01 | D145: CRS-1CH-012 | E145: 1 | F145: 1 Chronicles | G145: 15-16 | H145: Complementary Account | I145: Yes | J145: Yes | K145: No | L145: High | M145: High | N145: Attach to v0.1 event | O145: CRS-2SA-004 | P145: Complementary Account | Q145: SRC-TEXT-1CHR; SRC-CHRONICLES-OVERVIEW; SRC-CHRONICLES-BP | R145: Needs Review | S145: Canonical-scope block for The ark enters Jerusalem and David's liturgy.
A146: v0.2 | B146: Bible_Journey_Canon_Map_v0_2_Chronicles_Psalms_Job_1Kings.xlsx | C146: BLK-1CH-013-01 | D146: CRS-1CH-013 | E146: 1 | F146: 1 Chronicles | G146: 17 | H146: Parallel Account | I146: Yes | J146: Yes | K146: No | L146: High | M146: High | N146: Attach to v0.1 event | O146: CRS-2SA-005 | P146: Parallel Account | Q146: SRC-TEXT-1CHR; SRC-CHRONICLES-OVERVIEW; SRC-CHRONICLES-BP | R146: Needs Review | S146: Canonical-scope block for The Davidic covenant: Chronicles account.
A147: v0.2 | B147: Bible_Journey_Canon_Map_v0_2_Chronicles_Psalms_Job_1Kings.xlsx | C147: BLK-1CH-014-01 | D147: CRS-1CH-014 | E147: 1 | F147: 1 Chronicles | G147: 18 | H147: Parallel Account | I147: Yes | J147: Yes | K147: No | L147: High | M147: High | N147: Attach to v0.1 event | O147: CRS-2SA-006 | P147: Parallel Account | Q147: SRC-TEXT-1CHR; SRC-CHRONICLES-OVERVIEW; SRC-CHRONICLES-BP | R147: Needs Review | S147: Canonical-scope block for David's victories and administration: Chronicles account.
A148: v0.2 | B148: Bible_Journey_Canon_Map_v0_2_Chronicles_Psalms_Job_1Kings.xlsx | C148: BLK-1CH-015-01 | D148: CRS-1CH-015 | E148: 1 | F148: 1 Chronicles | G148: 19 | H148: Parallel Account | I148: Yes | J148: Yes | K148: No | L148: High | M148: High | N148: Attach to v0.1 event | O148: CRS-2SA-008 | P148: Parallel Account | Q148: SRC-TEXT-1CHR; SRC-CHRONICLES-OVERVIEW; SRC-CHRONICLES-BP | R148: Needs Review | S148: Canonical-scope block for War with Ammon and Aram: Chronicles account.
A149: v0.2 | B149: Bible_Journey_Canon_Map_v0_2_Chronicles_Psalms_Job_1Kings.xlsx | C149: BLK-1CH-016-01 | D149: CRS-1CH-016 | E149: 1 | F149: 1 Chronicles | G149: 20 | H149: Complementary Account | I149: Yes | J149: Yes | K149: No | L149: High | M149: Debated | N149: Contextual composite / multi-event window | O149: CRS-2SA-010; CRS-2SA-018 | P149: Complementary Account | Q149: SRC-TEXT-1CHR; SRC-CHRONICLES-OVERVIEW; SRC-CHRONICLES-BP | R149: Needs Review | S149: Canonical-scope block for Rabbah and Philistine giants: Chronicles accounts.
A150: v0.2 | B150: Bible_Journey_Canon_Map_v0_2_Chronicles_Psalms_Job_1Kings.xlsx | C150: BLK-1CH-017-01 | D150: CRS-1CH-017 | E150: 1 | F150: 1 Chronicles | G150: 21 | H150: Parallel Account | I150: Yes | J150: Yes | K150: No | L150: High | M150: Debated | N150: Attach to v0.1 event | O150: CRS-2SA-021 | P150: Parallel Account | Q150: SRC-TEXT-1CHR; SRC-CHRONICLES-OVERVIEW; SRC-CHRONICLES-BP | R150: Needs Review | S150: Canonical-scope block for David's census and altar site: Chronicles account.
A151: v0.2 | B151: Bible_Journey_Canon_Map_v0_2_Chronicles_Psalms_Job_1Kings.xlsx | C151: BLK-1CH-018-01 | D151: CRS-1CH-018 | E151: 1 | F151: 1 Chronicles | G151: 22 | H151: Primary Account | I151: Yes | J151: Yes | K151: Yes | L151: High | M151: Probable | N151: New main-spine bridge | P151: Primary account | Q151: SRC-TEXT-1CHR; SRC-CHRONICLES-OVERVIEW; SRC-CHRONICLES-BP | R151: Needs Review | S151: Canonical-scope block for David prepares for the temple.
A152: v0.2 | B152: Bible_Journey_Canon_Map_v0_2_Chronicles_Psalms_Job_1Kings.xlsx | C152: BLK-1CH-019-01 | D152: CRS-1CH-019 | E152: 1 | F152: 1 Chronicles | G152: 23-27 | H152: Primary Account | I152: Yes | J152: Yes | K152: Yes | L152: High | M152: Probable | N152: New main-spine bridge | P152: Primary account | Q152: SRC-TEXT-1CHR; SRC-CHRONICLES-OVERVIEW; SRC-CHRONICLES-BP | R152: Needs Review | S152: Canonical-scope block for Levites, priests, musicians, gatekeepers, officials, and military divisions.
A153: v0.2 | B153: Bible_Journey_Canon_Map_v0_2_Chronicles_Psalms_Job_1Kings.xlsx | C153: BLK-1CH-020-01 | D153: CRS-1CH-020 | E153: 1 | F153: 1 Chronicles | G153: 28-29 | H153: Complementary Account | I153: Yes | J153: Yes | K153: Yes | L153: High | M153: Probable | N153: New main-spine bridge | O153: CRS-1KG-001; CRS-1KG-002 | P153: Complementary Account | Q153: SRC-TEXT-1CHR; SRC-CHRONICLES-OVERVIEW; SRC-CHRONICLES-BP | R153: Needs Review | S153: Canonical-scope block for David's final assembly, temple charge, and Solomon's succession.
A154: v0.2 | B154: Bible_Journey_Canon_Map_v0_2_Chronicles_Psalms_Job_1Kings.xlsx | C154: BLK-1KG-001-01 | D154: CRS-1KG-001 | E154: 1 | F154: 1 Kings | G154: 1 | H154: Primary Account | I154: Yes | J154: Yes | K154: Yes | L154: High | M154: High | N154: New main-spine continuation | P154: Primary account | Q154: SRC-TEXT-1KGS; SRC-KINGS-OVERVIEW; SRC-KINGS-BP; SRC-SOLOMON-OVERVIEW; SRC-DIVIDED-MONARCHY | R154: Needs Review | S154: Canonical-scope block for Adonijah's bid and Solomon's accession.
A155: v0.2 | B155: Bible_Journey_Canon_Map_v0_2_Chronicles_Psalms_Job_1Kings.xlsx | C155: BLK-1KG-002-01 | D155: CRS-1KG-002 | E155: 1 | F155: 1 Kings | G155: 2 | H155: Primary Account | I155: Yes | J155: Yes | K155: Yes | L155: High | M155: High | N155: New main-spine continuation | P155: Primary account | Q155: SRC-TEXT-1KGS; SRC-KINGS-OVERVIEW; SRC-KINGS-BP; SRC-SOLOMON-OVERVIEW; SRC-DIVIDED-MONARCHY | R155: Needs Review | S155: Canonical-scope block for David's death and Solomon secures the throne.
A156: v0.2 | B156: Bible_Journey_Canon_Map_v0_2_Chronicles_Psalms_Job_1Kings.xlsx | C156: BLK-1KG-003-01 | D156: CRS-1KG-003 | E156: 1 | F156: 1 Kings | G156: 3 | H156: Primary Account | I156: Yes | J156: Yes | K156: Yes | L156: High | M156: High | N156: New main-spine continuation | O156: Future: 2 Chronicles 1 | P156: Primary account | Q156: SRC-TEXT-1KGS; SRC-KINGS-OVERVIEW; SRC-KINGS-BP; SRC-SOLOMON-OVERVIEW; SRC-DIVIDED-MONARCHY | R156: Needs Review | S156: Canonical-scope block for Solomon asks for wisdom at Gibeon.
A157: v0.2 | B157: Bible_Journey_Canon_Map_v0_2_Chronicles_Psalms_Job_1Kings.xlsx | C157: BLK-1KG-004-01 | D157: CRS-1KG-004 | E157: 1 | F157: 1 Kings | G157: 4 | H157: Primary Account | I157: Yes | J157: Yes | K157: Yes | L157: High | M157: High | N157: New main-spine continuation | P157: Primary account | Q157: SRC-TEXT-1KGS; SRC-KINGS-OVERVIEW; SRC-KINGS-BP; SRC-SOLOMON-OVERVIEW; SRC-DIVIDED-MONARCHY | R157: Needs Review | S157: Canonical-scope block for Solomon's administration, prosperity, and wisdom.
A158: v0.2 | B158: Bible_Journey_Canon_Map_v0_2_Chronicles_Psalms_Job_1Kings.xlsx | C158: BLK-1KG-005-01 | D158: CRS-1KG-005 | E158: 1 | F158: 1 Kings | G158: 5-6 | H158: Primary Account | I158: Yes | J158: Yes | K158: Yes | L158: High | M158: High | N158: New main-spine continuation | O158: Future: 2 Chronicles 2-3 | P158: Primary account | Q158: SRC-TEXT-1KGS; SRC-KINGS-OVERVIEW; SRC-KINGS-BP; SRC-SOLOMON-OVERVIEW; SRC-DIVIDED-MONARCHY | R158: Needs Review | S158: Canonical-scope block for Solomon builds the temple.
A159: v0.2 | B159: Bible_Journey_Canon_Map_v0_2_Chronicles_Psalms_Job_1Kings.xlsx | C159: BLK-1KG-006-01 | D159: CRS-1KG-006 | E159: 1 | F159: 1 Kings | G159: 7 | H159: Primary Account | I159: Yes | J159: Yes | K159: Yes | L159: High | M159: High | N159: New main-spine continuation | P159: Primary account | Q159: SRC-TEXT-1KGS; SRC-KINGS-OVERVIEW; SRC-KINGS-BP; SRC-SOLOMON-OVERVIEW; SRC-DIVIDED-MONARCHY | R159: Needs Review | S159: Canonical-scope block for Temple furnishings and Solomon's palace.
A160: v0.2 | B160: Bible_Journey_Canon_Map_v0_2_Chronicles_Psalms_Job_1Kings.xlsx | C160: BLK-1KG-007-01 | D160: CRS-1KG-007 | E160: 1 | F160: 1 Kings | G160: 8 | H160: Primary Account | I160: Yes | J160: Yes | K160: Yes | L160: High | M160: High | N160: New main-spine continuation | O160: Future: 2 Chronicles 5-7 | P160: Primary account | Q160: SRC-TEXT-1KGS; SRC-KINGS-OVERVIEW; SRC-KINGS-BP; SRC-SOLOMON-OVERVIEW; SRC-DIVIDED-MONARCHY | R160: Needs Review | S160: Canonical-scope block for Solomon dedicates the temple.
A161: v0.2 | B161: Bible_Journey_Canon_Map_v0_2_Chronicles_Psalms_Job_1Kings.xlsx | C161: BLK-1KG-008-01 | D161: CRS-1KG-008 | E161: 1 | F161: 1 Kings | G161: 9 | H161: Primary Account | I161: Yes | J161: Yes | K161: Yes | L161: High | M161: High | N161: New main-spine continuation | P161: Primary account | Q161: SRC-TEXT-1KGS; SRC-KINGS-OVERVIEW; SRC-KINGS-BP; SRC-SOLOMON-OVERVIEW; SRC-DIVIDED-MONARCHY | R161: Needs Review | S161: Canonical-scope block for Divine response, royal projects, and international trade.
A162: v0.2 | B162: Bible_Journey_Canon_Map_v0_2_Chronicles_Psalms_Job_1Kings.xlsx | C162: BLK-1KG-009-01 | D162: CRS-1KG-009 | E162: 1 | F162: 1 Kings | G162: 10 | H162: Primary Account | I162: Yes | J162: Yes | K162: Yes | L162: High | M162: High | N162: New main-spine continuation | O162: Future: 2 Chronicles 9 | P162: Primary account | Q162: SRC-TEXT-1KGS; SRC-KINGS-OVERVIEW; SRC-KINGS-BP; SRC-SOLOMON-OVERVIEW; SRC-DIVIDED-MONARCHY | R162: Needs Review | S162: Canonical-scope block for The queen of Sheba and Solomon's wealth.
A163: v0.2 | B163: Bible_Journey_Canon_Map_v0_2_Chronicles_Psalms_Job_1Kings.xlsx | C163: BLK-1KG-010-01 | D163: CRS-1KG-010 | E163: 1 | F163: 1 Kings | G163: 11 | H163: Primary Account | I163: Yes | J163: Yes | K163: Yes | L163: High | M163: High | N163: New main-spine continuation | P163: Primary account | Q163: SRC-TEXT-1KGS; SRC-KINGS-OVERVIEW; SRC-KINGS-BP; SRC-SOLOMON-OVERVIEW; SRC-DIVIDED-MONARCHY | R163: Needs Review | S163: Canonical-scope block for Solomon's decline and the division foretold.
A164: v0.2 | B164: Bible_Journey_Canon_Map_v0_2_Chronicles_Psalms_Job_1Kings.xlsx | C164: BLK-1KG-011-01 | D164: CRS-1KG-011 | E164: 1 | F164: 1 Kings | G164: 12 | H164: Primary Account | I164: Yes | J164: Yes | K164: Yes | L164: High | M164: High | N164: New main-spine continuation | O164: Future: 2 Chronicles 10 | P164: Primary account | Q164: SRC-TEXT-1KGS; SRC-KINGS-OVERVIEW; SRC-KINGS-BP; SRC-SOLOMON-OVERVIEW; SRC-DIVIDED-MONARCHY | R164: Needs Review | S164: Canonical-scope block for Rehoboam and Jeroboam: the kingdom divides.
A165: v0.2 | B165: Bible_Journey_Canon_Map_v0_2_Chronicles_Psalms_Job_1Kings.xlsx | C165: BLK-1KG-012-01 | D165: CRS-1KG-012 | E165: 1 | F165: 1 Kings | G165: 13 | H165: Primary Account | I165: Yes | J165: Yes | K165: Yes | L165: High | M165: High | N165: New main-spine continuation | P165: Primary account | Q165: SRC-TEXT-1KGS; SRC-KINGS-OVERVIEW; SRC-KINGS-BP; SRC-SOLOMON-OVERVIEW; SRC-DIVIDED-MONARCHY | R165: Needs Review | S165: Canonical-scope block for The man of God from Judah and Jeroboam's altar.
A166: v0.2 | B166: Bible_Journey_Canon_Map_v0_2_Chronicles_Psalms_Job_1Kings.xlsx | C166: BLK-1KG-013-01 | D166: CRS-1KG-013 | E166: 1 | F166: 1 Kings | G166: 14 | H166: Primary Account | I166: Yes | J166: Yes | K166: Yes | L166: High | M166: High | N166: New main-spine continuation | O166: Future: 2 Chronicles 12 | P166: Primary account | Q166: SRC-TEXT-1KGS; SRC-KINGS-OVERVIEW; SRC-KINGS-BP; SRC-SOLOMON-OVERVIEW; SRC-DIVIDED-MONARCHY | R166: Needs Review | S166: Canonical-scope block for Jeroboam's judgment and Rehoboam's reign.
A167: v0.2 | B167: Bible_Journey_Canon_Map_v0_2_Chronicles_Psalms_Job_1Kings.xlsx | C167: BLK-1KG-014-01 | D167: CRS-1KG-014 | E167: 1 | F167: 1 Kings | G167: 15 | H167: Primary Account | I167: Yes | J167: Yes | K167: Yes | L167: High | M167: High | N167: New main-spine continuation | O167: Future: 2 Chronicles 13-16 | P167: Primary account | Q167: SRC-TEXT-1KGS; SRC-KINGS-OVERVIEW; SRC-KINGS-BP; SRC-SOLOMON-OVERVIEW; SRC-DIVIDED-MONARCHY | R167: Needs Review | S167: Canonical-scope block for Abijam and Asa in Judah.
A168: v0.2 | B168: Bible_Journey_Canon_Map_v0_2_Chronicles_Psalms_Job_1Kings.xlsx | C168: BLK-1KG-015-01 | D168: CRS-1KG-015 | E168: 1 | F168: 1 Kings | G168: 16 | H168: Primary Account | I168: Yes | J168: Yes | K168: Yes | L168: High | M168: High | N168: New main-spine continuation | P168: Primary account | Q168: SRC-TEXT-1KGS; SRC-KINGS-OVERVIEW; SRC-KINGS-BP; SRC-SOLOMON-OVERVIEW; SRC-DIVIDED-MONARCHY | R168: Needs Review | S168: Canonical-scope block for Baasha, Elah, Zimri, Omri, and Ahab's rise.
A169: v0.2 | B169: Bible_Journey_Canon_Map_v0_2_Chronicles_Psalms_Job_1Kings.xlsx | C169: BLK-1KG-016-01 | D169: CRS-1KG-016 | E169: 1 | F169: 1 Kings | G169: 17 | H169: Primary Account | I169: Yes | J169: Yes | K169: Yes | L169: High | M169: High | N169: New main-spine continuation | P169: Primary account | Q169: SRC-TEXT-1KGS; SRC-KINGS-OVERVIEW; SRC-KINGS-BP; SRC-SOLOMON-OVERVIEW; SRC-DIVIDED-MONARCHY | R169: Needs Review | S169: Canonical-scope block for Elijah announces drought and is sustained.
A170: v0.2 | B170: Bible_Journey_Canon_Map_v0_2_Chronicles_Psalms_Job_1Kings.xlsx | C170: BLK-1KG-017-01 | D170: CRS-1KG-017 | E170: 1 | F170: 1 Kings | G170: 18 | H170: Primary Account | I170: Yes | J170: Yes | K170: Yes | L170: High | M170: High | N170: New main-spine continuation | P170: Primary account | Q170: SRC-TEXT-1KGS; SRC-KINGS-OVERVIEW; SRC-KINGS-BP; SRC-SOLOMON-OVERVIEW; SRC-DIVIDED-MONARCHY | R170: Needs Review | S170: Canonical-scope block for Elijah on Carmel.
A171: v0.2 | B171: Bible_Journey_Canon_Map_v0_2_Chronicles_Psalms_Job_1Kings.xlsx | C171: BLK-1KG-018-01 | D171: CRS-1KG-018 | E171: 1 | F171: 1 Kings | G171: 19 | H171: Primary Account | I171: Yes | J171: Yes | K171: Yes | L171: High | M171: High | N171: New main-spine continuation | P171: Primary account | Q171: SRC-TEXT-1KGS; SRC-KINGS-OVERVIEW; SRC-KINGS-BP; SRC-SOLOMON-OVERVIEW; SRC-DIVIDED-MONARCHY | R171: Needs Review | S171: Canonical-scope block for Elijah at Horeb and Elisha's call.
A172: v0.2 | B172: Bible_Journey_Canon_Map_v0_2_Chronicles_Psalms_Job_1Kings.xlsx | C172: BLK-1KG-019-01 | D172: CRS-1KG-019 | E172: 1 | F172: 1 Kings | G172: 20 | H172: Primary Account | I172: Yes | J172: Yes | K172: Yes | L172: High | M172: High | N172: New main-spine continuation | P172: Primary account | Q172: SRC-TEXT-1KGS; SRC-KINGS-OVERVIEW; SRC-KINGS-BP; SRC-SOLOMON-OVERVIEW; SRC-DIVIDED-MONARCHY | R172: Needs Review | S172: Canonical-scope block for Ahab's wars with Aram.
A173: v0.2 | B173: Bible_Journey_Canon_Map_v0_2_Chronicles_Psalms_Job_1Kings.xlsx | C173: BLK-1KG-020-01 | D173: CRS-1KG-020 | E173: 1 | F173: 1 Kings | G173: 21 | H173: Primary Account | I173: Yes | J173: Yes | K173: Yes | L173: High | M173: High | N173: New main-spine continuation | P173: Primary account | Q173: SRC-TEXT-1KGS; SRC-KINGS-OVERVIEW; SRC-KINGS-BP; SRC-SOLOMON-OVERVIEW; SRC-DIVIDED-MONARCHY | R173: Needs Review | S173: Canonical-scope block for Naboth's vineyard and Elijah's judgment.
A174: v0.2 | B174: Bible_Journey_Canon_Map_v0_2_Chronicles_Psalms_Job_1Kings.xlsx | C174: BLK-1KG-021-01 | D174: CRS-1KG-021 | E174: 1 | F174: 1 Kings | G174: 22 | H174: Primary Account | I174: Yes | J174: Yes | K174: Yes | L174: High | M174: High | N174: New main-spine continuation | O174: Future: 2 Chronicles 18 | P174: Primary account | Q174: SRC-TEXT-1KGS; SRC-KINGS-OVERVIEW; SRC-KINGS-BP; SRC-SOLOMON-OVERVIEW; SRC-DIVIDED-MONARCHY | R174: Needs Review | S174: Canonical-scope block for Micaiah, Ahab's death, and Jehoshaphat.
A175: v0.2 | B175: Bible_Journey_Canon_Map_v0_2_Chronicles_Psalms_Job_1Kings.xlsx | C175: BLK-1CH-001-01 | D175: CRS-1CH-001 | E175: 1 | F175: 1 Chronicles | G175: 1-2 | H175: Genealogical Context | I175: Yes | J175: Yes | K175: No | L175: High | M175: Unresolved | N175: Auxiliary collection / no fixed event placement | P175: Genealogical Context | Q175: SRC-TEXT-1CHR; SRC-CHRONICLES-OVERVIEW; SRC-CHRONICLES-BP | R175: Needs Review | S175: Canonical-scope block for Genealogies from Adam to Judah.
A176: v0.2 | B176: Bible_Journey_Canon_Map_v0_2_Chronicles_Psalms_Job_1Kings.xlsx | C176: BLK-1CH-002-01 | D176: CRS-1CH-002 | E176: 1 | F176: 1 Chronicles | G176: 3-4 | H176: Genealogical Context | I176: Yes | J176: Yes | K176: No | L176: High | M176: Unresolved | N176: Auxiliary collection / no fixed event placement | P176: Genealogical Context | Q176: SRC-TEXT-1CHR; SRC-CHRONICLES-OVERVIEW; SRC-CHRONICLES-BP | R176: Needs Review | S176: Canonical-scope block for Davidic line and clans of Judah.
A177: v0.2 | B177: Bible_Journey_Canon_Map_v0_2_Chronicles_Psalms_Job_1Kings.xlsx | C177: BLK-1CH-003-01 | D177: CRS-1CH-003 | E177: 1 | F177: 1 Chronicles | G177: 5 | H177: Genealogical Context | I177: Yes | J177: Yes | K177: No | L177: High | M177: Unresolved | N177: Auxiliary collection / no fixed event placement | P177: Genealogical Context | Q177: SRC-TEXT-1CHR; SRC-CHRONICLES-OVERVIEW; SRC-CHRONICLES-BP | R177: Needs Review | S177: Canonical-scope block for Transjordanian tribal lines.
A178: v0.2 | B178: Bible_Journey_Canon_Map_v0_2_Chronicles_Psalms_Job_1Kings.xlsx | C178: BLK-1CH-004-01 | D178: CRS-1CH-004 | E178: 1 | F178: 1 Chronicles | G178: 6 | H178: Genealogical Context | I178: Yes | J178: Yes | K178: No | L178: High | M178: Unresolved | N178: Auxiliary collection / no fixed event placement | P178: Genealogical Context | Q178: SRC-TEXT-1CHR; SRC-CHRONICLES-OVERVIEW; SRC-CHRONICLES-BP | R178: Needs Review | S178: Canonical-scope block for Levi, priests, and temple line.
A179: v0.2 | B179: Bible_Journey_Canon_Map_v0_2_Chronicles_Psalms_Job_1Kings.xlsx | C179: BLK-1CH-005-01 | D179: CRS-1CH-005 | E179: 1 | F179: 1 Chronicles | G179: 7-8 | H179: Genealogical Context | I179: Yes | J179: Yes | K179: No | L179: High | M179: Unresolved | N179: Auxiliary collection / no fixed event placement | P179: Genealogical Context | Q179: SRC-TEXT-1CHR; SRC-CHRONICLES-OVERVIEW; SRC-CHRONICLES-BP | R179: Needs Review | S179: Canonical-scope block for Tribal lines and Benjamin.
A180: v0.2 | B180: Bible_Journey_Canon_Map_v0_2_Chronicles_Psalms_Job_1Kings.xlsx | C180: BLK-1CH-006-01 | D180: CRS-1CH-006 | E180: 1 | F180: 1 Chronicles | G180: 9 | H180: Genealogical Context | I180: Yes | J180: Yes | K180: No | L180: High | M180: Unresolved | N180: Auxiliary collection / postexilic retrospective | P180: Genealogical Context | Q180: SRC-TEXT-1CHR; SRC-CHRONICLES-OVERVIEW; SRC-CHRONICLES-BP | R180: Needs Review | S180: Canonical-scope block for Postexilic Jerusalem and temple personnel.
A181: v0.2 | B181: Bible_Journey_Canon_Map_v0_2_Chronicles_Psalms_Job_1Kings.xlsx | C181: BLK-JOB-001-01 | D181: CRS-JOB-001 | E181: 1 | F181: Job | G181: 1-2 | H181: Primary Account | I181: Yes | J181: Yes | K181: Yes | L181: High | M181: Unresolved | N181: Auxiliary collection / chronology unresolved | P181: Primary account | Q181: SRC-TEXT-JOB; SRC-JOB-AUTHORSHIP; SRC-JOB-OVERVIEW | R181: Needs Review | S181: Canonical-scope block for Job's integrity, losses, and the heavenly challenge.
A182: v0.2 | B182: Bible_Journey_Canon_Map_v0_2_Chronicles_Psalms_Job_1Kings.xlsx | C182: BLK-JOB-002-01 | D182: CRS-JOB-002 | E182: 1 | F182: Job | G182: 3 | H182: Primary Account | I182: Yes | J182: Yes | K182: Yes | L182: High | M182: Unresolved | N182: Auxiliary collection / chronology unresolved | P182: Primary account | Q182: SRC-TEXT-JOB; SRC-JOB-AUTHORSHIP; SRC-JOB-OVERVIEW | R182: Needs Review | S182: Canonical-scope block for Job curses the day of his birth.
A183: v0.2 | B183: Bible_Journey_Canon_Map_v0_2_Chronicles_Psalms_Job_1Kings.xlsx | C183: BLK-JOB-003-01 | D183: CRS-JOB-003 | E183: 1 | F183: Job | G183: 4-14 | H183: Primary Account | I183: Yes | J183: Yes | K183: Yes | L183: High | M183: Unresolved | N183: Auxiliary collection / chronology unresolved | P183: Primary account | Q183: SRC-TEXT-JOB; SRC-JOB-AUTHORSHIP; SRC-JOB-OVERVIEW | R183: Needs Review | S183: Canonical-scope block for First cycle of speeches: Job and his friends.
A184: v0.2 | B184: Bible_Journey_Canon_Map_v0_2_Chronicles_Psalms_Job_1Kings.xlsx | C184: BLK-JOB-004-01 | D184: CRS-JOB-004 | E184: 1 | F184: Job | G184: 15-21 | H184: Primary Account | I184: Yes | J184: Yes | K184: Yes | L184: High | M184: Unresolved | N184: Auxiliary collection / chronology unresolved | P184: Primary account | Q184: SRC-TEXT-JOB; SRC-JOB-AUTHORSHIP; SRC-JOB-OVERVIEW | R184: Needs Review | S184: Canonical-scope block for Second cycle of speeches: Job and his friends.
A185: v0.2 | B185: Bible_Journey_Canon_Map_v0_2_Chronicles_Psalms_Job_1Kings.xlsx | C185: BLK-JOB-005-01 | D185: CRS-JOB-005 | E185: 1 | F185: Job | G185: 22-27 | H185: Primary Account | I185: Yes | J185: Yes | K185: Yes | L185: High | M185: Unresolved | N185: Auxiliary collection / chronology unresolved | P185: Primary account | Q185: SRC-TEXT-JOB; SRC-JOB-AUTHORSHIP; SRC-JOB-OVERVIEW | R185: Needs Review | S185: Canonical-scope block for Third cycle of speeches and Job's response.
A186: v0.2 | B186: Bible_Journey_Canon_Map_v0_2_Chronicles_Psalms_Job_1Kings.xlsx | C186: BLK-JOB-006-01 | D186: CRS-JOB-006 | E186: 1 | F186: Job | G186: 28 | H186: Primary Account | I186: Yes | J186: Yes | K186: Yes | L186: High | M186: Unresolved | N186: Auxiliary collection / chronology unresolved | P186: Primary account | Q186: SRC-TEXT-JOB; SRC-JOB-AUTHORSHIP; SRC-JOB-OVERVIEW | R186: Needs Review | S186: Canonical-scope block for The hymn to wisdom.
... A191: v0.2 | B191: Bible_Journey_Canon_Map_v0_2_Chronicles_Psalms_Job_1Kings.xlsx | C191: BLK-PSA-001-01 | D191: CRS-PSA-001 | E191: 1 | F191: Psalms | G191: 1-2 | H191: Poetic Connection | I191: Yes | J191: Yes | K191: No | L191: High | M191: Unresolved | N191: Poetry collection / no fixed event placement | P191: Poetic Connection | Q191: SRC-TEXT-PSALMS; SRC-PSALMS-OVERVIEW; SRC-PSALM-SUPERSCRIPTIONS | R191: Needs Review | S191: Canonical-scope block for Psalms 1-2: opening wisdom and royal framing.
A192: v0.2 | B192: Bible_Journey_Canon_Map_v0_2_Chronicles_Psalms_Job_1Kings.xlsx | C192: BLK-PSA-002-01 | D192: CRS-PSA-002 | E192: 1 | F192: Psalms | G192: 3 | H192: Poetic Connection | I192: Yes | J192: Yes | K192: No | L192: High | M192: Probable | N192: Attach to v0.1 event | O192: CRS-2SA-013 | P192: Poetic Connection | Q192: SRC-TEXT-PSALMS; SRC-PSALMS-OVERVIEW; SRC-PSALM-SUPERSCRIPTIONS | R192: Needs Review | S192: Canonical-scope block for Psalm 3: David flees Absalom.
A193: v0.2 | B193: Bible_Journey_Canon_Map_v0_2_Chronicles_Psalms_Job_1Kings.xlsx | C193: BLK-PSA-003-01 | D193: CRS-PSA-003 | E193: 1 | F193: Psalms | G193: 4-6 | H193: Poetic Connection | I193: Yes | J193: Yes | K193: No | L193: High | M193: Unresolved | N193: Poetry collection / broad Davidic window | P193: Poetic Connection | Q193: SRC-TEXT-PSALMS; SRC-PSALMS-OVERVIEW; SRC-PSALM-SUPERSCRIPTIONS | R193: Needs Review | S193: Canonical-scope block for Psalms 4-6: Davidic prayers without an identified event.
A194: v0.2 | B194: Bible_Journey_Canon_Map_v0_2_Chronicles_Psalms_Job_1Kings.xlsx | C194: BLK-PSA-004-01 | D194: CRS-PSA-004 | E194: 1 | F194: Psalms | G194: 7 | H194: Poetic Connection | I194: Yes | J194: Yes | K194: No | L194: High | M194: Debated | N194: Poetry connection / debated historical link | P194: Poetic Connection | Q194: SRC-TEXT-PSALMS; SRC-PSALMS-OVERVIEW; SRC-PSALM-SUPERSCRIPTIONS | R194: Needs Review | S194: Canonical-scope block for Psalm 7: Cush the Benjaminite.
A195: v0.2 | B195: Bible_Journey_Canon_Map_v0_2_Chronicles_Psalms_Job_1Kings.xlsx | C195: BLK-PSA-005-01 | D195: CRS-PSA-005 | E195: 1 | F195: Psalms | G195: 8-17 | H195: Poetic Connection | I195: Yes | J195: Yes | K195: No | L195: High | M195: Unresolved | N195: Poetry collection / broad Davidic window | P195: Poetic Connection | Q195: SRC-TEXT-PSALMS; SRC-PSALMS-OVERVIEW; SRC-PSALM-SUPERSCRIPTIONS | R195: Needs Review | S195: Canonical-scope block for Psalms 8-17: Davidic prayers and royal language.
A196: v0.2 | B196: Bible_Journey_Canon_Map_v0_2_Chronicles_Psalms_Job_1Kings.xlsx | C196: BLK-PSA-006-01 | D196: CRS-PSA-006 | E196: 1 | F196: Psalms | G196: 18 | H196: Poetic Connection | I196: Yes | J196: Yes | K196: No | L196: High | M196: Debated | N196: Attach to v0.1 event | O196: CRS-2SA-019 | P196: Poetic Connection | Q196: SRC-TEXT-PSALMS; SRC-PSALMS-OVERVIEW; SRC-PSALM-SUPERSCRIPTIONS | R196: Needs Review | S196: Canonical-scope block for Psalm 18: David's song of deliverance.
A197: v0.2 | B197: Bible_Journey_Canon_Map_v0_2_Chronicles_Psalms_Job_1Kings.xlsx | C197: BLK-PSA-007-01 | D197: CRS-PSA-007 | E197: 1 | F197: Psalms | G197: 19-29 | H197: Poetic Connection | I197: Yes | J197: Yes | K197: No | L197: High | M197: Unresolved | N197: Poetry collection / broad Davidic window | P197: Poetic Connection | Q197: SRC-TEXT-PSALMS; SRC-PSALMS-OVERVIEW; SRC-PSALM-SUPERSCRIPTIONS | R197: Needs Review | S197: Canonical-scope block for Psalms 19-29: Davidic prayers and royal psalms.
A198: v0.2 | B198: Bible_Journey_Canon_Map_v0_2_Chronicles_Psalms_Job_1Kings.xlsx | C198: BLK-PSA-008-01 | D198: CRS-PSA-008 | E198: 1 | F198: Psalms | G198: 30 | H198: Poetic Connection | I198: Yes | J198: Yes | K198: No | L198: High | M198: Debated | N198: Poetry connection / debated historical link | P198: Poetic Connection | Q198: SRC-TEXT-PSALMS; SRC-PSALMS-OVERVIEW; SRC-PSALM-SUPERSCRIPTIONS | R198: Needs Review | S198: Canonical-scope block for Psalm 30: dedication of a house.
A199: v0.2 | B199: Bible_Journey_Canon_Map_v0_2_Chronicles_Psalms_Job_1Kings.xlsx | C199: BLK-PSA-009-01 | D199: CRS-PSA-009 | E199: 1 | F199: Psalms | G199: 31-33 | H199: Poetic Connection | I199: Yes | J199: Yes | K199: No | L199: High | M199: Unresolved | N199: Poetry collection / broad Davidic window | P199: Poetic Connection | Q199: SRC-TEXT-PSALMS; SRC-PSALMS-OVERVIEW; SRC-PSALM-SUPERSCRIPTIONS | R199: Needs Review | S199: Canonical-scope block for Psalms 31-33: Davidic and communal prayers.
A200: v0.2 | B200: Bible_Journey_Canon_Map_v0_2_Chronicles_Psalms_Job_1Kings.xlsx | C200: BLK-PSA-010-01 | D200: CRS-PSA-010 | E200: 1 | F200: Psalms | G200: 34 | H200: Poetic Connection | I200: Yes | J200: Yes | K200: No | L200: High | M200: Probable | N200: Attach to v0.1 event | O200: CRS-1SA-011 | P200: Poetic Connection | Q200: SRC-TEXT-PSALMS; SRC-PSALMS-OVERVIEW; SRC-PSALM-SUPERSCRIPTIONS | R200: Needs Review | S200: Canonical-scope block for Psalm 34: David before Abimelech.
A201: v0.2 | B201: Bible_Journey_Canon_Map_v0_2_Chronicles_Psalms_Job_1Kings.xlsx | C201: BLK-PSA-011-01 | D201: CRS-PSA-011 | E201: 1 | F201: Psalms | G201: 35-50 | H201: Poetic Connection | I201: Yes | J201: Yes | K201: No | L201: High | M201: Unresolved | N201: Poetry collection / no fixed event placement | P201: Poetic Connection | Q201: SRC-TEXT-PSALMS; SRC-PSALMS-OVERVIEW; SRC-PSALM-SUPERSCRIPTIONS | R201: Needs Review | S201: Canonical-scope block for Psalms 35-50: prayers, royal psalms, and Asaph material.
A202: v0.2 | B202: Bible_Journey_Canon_Map_v0_2_Chronicles_Psalms_Job_1Kings.xlsx | C202: BLK-PSA-012-01 | D202: CRS-PSA-012 | E202: 1 | F202: Psalms | G202: 51 | H202: Poetic Connection | I202: Yes | J202: Yes | K202: No | L202: High | M202: Probable | N202: Attach to v0.1 event | O202: CRS-2SA-010 | P202: Poetic Connection | Q202: SRC-TEXT-PSALMS; SRC-PSALMS-OVERVIEW; SRC-PSALM-SUPERSCRIPTIONS | R202: Needs Review | S202: Canonical-scope block for Psalm 51: David after Nathan's confrontation.
A203: v0.2 | B203: Bible_Journey_Canon_Map_v0_2_Chronicles_Psalms_Job_1Kings.xlsx | C203: BLK-PSA-013-01 | D203: CRS-PSA-013 | E203: 1 | F203: Psalms | G203: 52 | H203: Poetic Connection | I203: Yes | J203: Yes | K203: No | L203: High | M203: Probable | N203: Attach to v0.1 event | O203: CRS-1SA-012 | P203: Poetic Connection | Q203: SRC-TEXT-PSALMS; SRC-PSALMS-OVERVIEW; SRC-PSALM-SUPERSCRIPTIONS | R203: Needs Review | S203: Canonical-scope block for Psalm 52: Doeg the Edomite.
A204: v0.2 | B204: Bible_Journey_Canon_Map_v0_2_Chronicles_Psalms_Job_1Kings.xlsx | C204: BLK-PSA-014-01 | D204: CRS-PSA-014 | E204: 1 | F204: Psalms | G204: 53 | H204: Poetic Connection | I204: Yes | J204: Yes | K204: No | L204: High | M204: Unresolved | N204: Poetry collection / broad Davidic window | P204: Poetic Connection | Q204: SRC-TEXT-PSALMS; SRC-PSALMS-OVERVIEW; SRC-PSALM-SUPERSCRIPTIONS | R204: Needs Review | S204: Canonical-scope block for Psalm 53: Davidic prayer without identified event.
A205: v0.2 | B205: Bible_Journey_Canon_Map_v0_2_Chronicles_Psalms_Job_1Kings.xlsx | C205: BLK-PSA-015-01 | D205: CRS-PSA-015 | E205: 1 | F205: Psalms | G205: 54 | H205: Poetic Connection | I205: Yes | J205: Yes | K205: No | L205: High | M205: Probable | N205: Attach to v0.1 event | O205: CRS-1SA-013 | P205: Poetic Connection | Q205: SRC-TEXT-PSALMS; SRC-PSALMS-OVERVIEW; SRC-PSALM-SUPERSCRIPTIONS | R205: Needs Review | S205: Canonical-scope block for Psalm 54: the Ziphites' report.
A206: v0.2 | B206: Bible_Journey_Canon_Map_v0_2_Chronicles_Psalms_Job_1Kings.xlsx | C206: BLK-PSA-016-01 | D206: CRS-PSA-016 | E206: 1 | F206: Psalms | G206: 55 | H206: Poetic Connection | I206: Yes | J206: Yes | K206: No | L206: High | M206: Unresolved | N206: Poetry collection / broad Davidic window | P206: Poetic Connection | Q206: SRC-TEXT-PSALMS; SRC-PSALMS-OVERVIEW; SRC-PSALM-SUPERSCRIPTIONS | R206: Needs Review | S206: Canonical-scope block for Psalm 55: Davidic prayer without identified event.
A207: v0.2 | B207: Bible_Journey_Canon_Map_v0_2_Chronicles_Psalms_Job_1Kings.xlsx | C207: BLK-PSA-017-01 | D207: CRS-PSA-017 | E207: 1 | F207: Psalms | G207: 56 | H207: Poetic Connection | I207: Yes | J207: Yes | K207: No | L207: High | M207: Probable | N207: Attach to v0.1 event | O207: CRS-1SA-011 | P207: Poetic Connection | Q207: SRC-TEXT-PSALMS; SRC-PSALMS-OVERVIEW; SRC-PSALM-SUPERSCRIPTIONS | R207: Needs Review | S207: Canonical-scope block for Psalm 56: David among the Philistines at Gath.
A208: v0.2 | B208: Bible_Journey_Canon_Map_v0_2_Chronicles_Psalms_Job_1Kings.xlsx | C208: BLK-PSA-018-01 | D208: CRS-PSA-018 | E208: 1 | F208: Psalms | G208: 57 | H208: Poetic Connection | I208: Yes | J208: Yes | K208: No | L208: High | M208: Debated | N208: Poetry connection / debated historical link | P208: Poetic Connection | Q208: SRC-TEXT-PSALMS; SRC-PSALMS-OVERVIEW; SRC-PSALM-SUPERSCRIPTIONS | R208: Needs Review | S208: Canonical-scope block for Psalm 57: David in the cave.
A209: v0.2 | B209: Bible_Journey_Canon_Map_v0_2_Chronicles_Psalms_Job_1Kings.xlsx | C209: BLK-PSA-019-01 | D209: CRS-PSA-019 | E209: 1 | F209: Psalms | G209: 58 | H209: Poetic Connection | I209: Yes | J209: Yes | K209: No | L209: High | M209: Unresolved | N209: Poetry collection / broad Davidic window | P209: Poetic Connection | Q209: SRC-TEXT-PSALMS; SRC-PSALMS-OVERVIEW; SRC-PSALM-SUPERSCRIPTIONS | R209: Needs Review | S209: Canonical-scope block for Psalm 58: Davidic prayer without identified event.
A210: v0.2 | B210: Bible_Journey_Canon_Map_v0_2_Chronicles_Psalms_Job_1Kings.xlsx | C210: BLK-PSA-020-01 | D210: CRS-PSA-020 | E210: 1 | F210: Psalms | G210: 59 | H210: Poetic Connection | I210: Yes | J210: Yes | K210: No | L210: High | M210: Probable | N210: Attach to v0.1 event | O210: CRS-1SA-009 | P210: Poetic Connection | Q210: SRC-TEXT-PSALMS; SRC-PSALMS-OVERVIEW; SRC-PSALM-SUPERSCRIPTIONS | R210: Needs Review | S210: Canonical-scope block for Psalm 59: escape from Saul's agents.
A211: v0.2 | B211: Bible_Journey_Canon_Map_v0_2_Chronicles_Psalms_Job_1Kings.xlsx | C211: BLK-PSA-021-01 | D211: CRS-PSA-021 | E211: 1 | F211: Psalms | G211: 60 | H211: Poetic Connection | I211: Yes | J211: Yes | K211: No | L211: High | M211: Probable | N211: Attach to v0.1 event | O211: CRS-2SA-006 | P211: Poetic Connection | Q211: SRC-TEXT-PSALMS; SRC-PSALMS-OVERVIEW; SRC-PSALM-SUPERSCRIPTIONS | R211: Needs Review | S211: Canonical-scope block for Psalm 60: David's victories over Aram and Edom.
A212: v0.2 | B212: Bible_Journey_Canon_Map_v0_2_Chronicles_Psalms_Job_1Kings.xlsx | C212: BLK-PSA-022-01 | D212: CRS-PSA-022 | E212: 1 | F212: Psalms | G212: 61-62 | H212: Poetic Connection | I212: Yes | J212: Yes | K212: No | L212: High | M212: Unresolved | N212: Poetry collection / broad Davidic window | P212: Poetic Connection | Q212: SRC-TEXT-PSALMS; SRC-PSALMS-OVERVIEW; SRC-PSALM-SUPERSCRIPTIONS | R212: Needs Review | S212: Canonical-scope block for Psalms 61-62: Davidic prayers without identified event.
A213: v0.2 | B213: Bible_Journey_Canon_Map_v0_2_Chronicles_Psalms_Job_1Kings.xlsx | C213: BLK-PSA-023-01 | D213: CRS-PSA-023 | E213: 1 | F213: Psalms | G213: 63 | H213: Poetic Connection | I213: Yes | J213: Yes | K213: No | L213: High | M213: Debated | N213: Poetry connection / debated historical link | P213: Poetic Connection | Q213: SRC-TEXT-PSALMS; SRC-PSALMS-OVERVIEW; SRC-PSALM-SUPERSCRIPTIONS | R213: Needs Review | S213: Canonical-scope block for Psalm 63: David in the wilderness of Judah.
A214: v0.2 | B214: Bible_Journey_Canon_Map_v0_2_Chronicles_Psalms_Job_1Kings.xlsx | C214: BLK-PSA-024-01 | D214: CRS-PSA-024 | E214: 1 | F214: Psalms | G214: 64-71 | H214: Poetic Connection | I214: Yes | J214: Yes | K214: No | L214: High | M214: Unresolved | N214: Poetry collection / broad Davidic window | P214: Poetic Connection | Q214: SRC-TEXT-PSALMS; SRC-PSALMS-OVERVIEW; SRC-PSALM-SUPERSCRIPTIONS | R214: Needs Review | S214: Canonical-scope block for Psalms 64-71: Davidic prayers and royal material.
A215: v0.2 | B215: Bible_Journey_Canon_Map_v0_2_Chronicles_Psalms_Job_1Kings.xlsx | C215: BLK-PSA-025-01 | D215: CRS-PSA-025 | E215: 1 | F215: Psalms | G215: 72 | H215: Poetic Connection | I215: Yes | J215: Yes | K215: No | L215: High | M215: Probable | N215: Solomonic window / no fixed event placement | O215: CRS-1KG-003 | P215: Poetic Connection | Q215: SRC-TEXT-PSALMS; SRC-PSALMS-OVERVIEW; SRC-PSALM-SUPERSCRIPTIONS | R215: Needs Review | S215: Canonical-scope block for Psalm 72: royal prayer associated with Solomon.
A216: v0.2 | B216: Bible_Journey_Canon_Map_v0_2_Chronicles_Psalms_Job_1Kings.xlsx | C216: BLK-PSA-026-01 | D216: CRS-PSA-026 | E216: 1 | F216: Psalms | G216: 73-89 | H216: Poetic Connection | I216: Yes | J216: Yes | K216: No | L216: High | M216: Unresolved | N216: Poetry collection / no fixed event placement | P216: Poetic Connection | Q216: SRC-TEXT-PSALMS; SRC-PSALMS-OVERVIEW; SRC-PSALM-SUPERSCRIPTIONS | R216: Needs Review | S216: Canonical-scope block for Psalms 73-89: Asaph, Korahite, and royal collections.
A217: v0.2 | B217: Bible_Journey_Canon_Map_v0_2_Chronicles_Psalms_Job_1Kings.xlsx | C217: BLK-PSA-027-01 | D217: CRS-PSA-027 | E217: 1 | F217: Psalms | G217: 90 | H217: Poetic Connection | I217: Yes | J217: Yes | K217: No | L217: High | M217: Debated | N217: Mosaic tradition / no fixed event placement | P217: Poetic Connection | Q217: SRC-TEXT-PSALMS; SRC-PSALMS-OVERVIEW; SRC-PSALM-SUPERSCRIPTIONS | R217: Needs Review | S217: Canonical-scope block for Psalm 90: prayer associated with Moses.
A218: v0.2 | B218: Bible_Journey_Canon_Map_v0_2_Chronicles_Psalms_Job_1Kings.xlsx | C218: BLK-PSA-028-01 | D218: CRS-PSA-028 | E218: 1 | F218: Psalms | G218: 91-95 | H218: Poetic Connection | I218: Yes | J218: Yes | K218: No | L218: High | M218: Unresolved | N218: Poetry collection / no fixed event placement | P218: Poetic Connection | Q218: SRC-TEXT-PSALMS; SRC-PSALMS-OVERVIEW; SRC-PSALM-SUPERSCRIPTIONS | R218: Needs Review | S218: Canonical-scope block for Psalms 91-95: Book IV opening collection.
A219: v0.2 | B219: Bible_Journey_Canon_Map_v0_2_Chronicles_Psalms_Job_1Kings.xlsx | C219: BLK-PSA-029-01 | D219: CRS-PSA-029 | E219: 1 | F219: Psalms | G219: 96 | H219: Poetic Connection | I219: Yes | J219: Yes | K219: No | L219: High | M219: High | N219: Textual reuse / linked liturgy | O219: CRS-1CH-012 | P219: Poetic Connection | Q219: SRC-TEXT-PSALMS; SRC-PSALMS-OVERVIEW; SRC-PSALM-SUPERSCRIPTIONS | R219: Needs Review | S219: Canonical-scope block for Psalm 96: worship text reused in Chronicles' ark liturgy.
A220: v0.2 | B220: Bible_Journey_Canon_Map_v0_2_Chronicles_Psalms_Job_1Kings.xlsx | C220: BLK-PSA-030-01 | D220: CRS-PSA-030 | E220: 1 | F220: Psalms | G220: 97-104 | H220: Poetic Connection | I220: Yes | J220: Yes | K220: No | L220: High | M220: Unresolved | N220: Poetry collection / no fixed event placement | P220: Poetic Connection | Q220: SRC-TEXT-PSALMS; SRC-PSALMS-OVERVIEW; SRC-PSALM-SUPERSCRIPTIONS | R220: Needs Review | S220: Canonical-scope block for Psalms 97-104: kingship, worship, and creation praise.
A221: v0.2 | B221: Bible_Journey_Canon_Map_v0_2_Chronicles_Psalms_Job_1Kings.xlsx | C221: BLK-PSA-031-01 | D221: CRS-PSA-031 | E221: 1 | F221: Psalms | G221: 105 | H221: Poetic Connection | I221: Yes | J221: Yes | K221: No | L221: High | M221: High | N221: Textual reuse / linked liturgy | O221: CRS-1CH-012 | P221: Poetic Connection | Q221: SRC-TEXT-PSALMS; SRC-PSALMS-OVERVIEW; SRC-PSALM-SUPERSCRIPTIONS | R221: Needs Review | S221: Canonical-scope block for Psalm 105: covenant-history text reused in Chronicles' ark liturgy.
A222: v0.2 | B222: Bible_Journey_Canon_Map_v0_2_Chronicles_Psalms_Job_1Kings.xlsx | C222: BLK-PSA-032-01 | D222: CRS-PSA-032 | E222: 1 | F222: Psalms | G222: 106 | H222: Poetic Connection | I222: Yes | J222: Yes | K222: No | L222: High | M222: Probable | N222: Textual reuse / linked liturgy | O222: CRS-1CH-012 | P222: Poetic Connection | Q222: SRC-TEXT-PSALMS; SRC-PSALMS-OVERVIEW; SRC-PSALM-SUPERSCRIPTIONS | R222: Needs Review | S222: Canonical-scope block for Psalm 106: thanksgiving and covenant memory linked to Chronicles' liturgy.
A223: v0.2 | B223: Bible_Journey_Canon_Map_v0_2_Chronicles_Psalms_Job_1Kings.xlsx | C223: BLK-PSA-033-01 | D223: CRS-PSA-033 | E223: 1 | F223: Psalms | G223: 107-121 | H223: Poetic Connection | I223: Yes | J223: Yes | K223: No | L223: High | M223: Unresolved | N223: Poetry collection / no fixed event placement | P223: Poetic Connection | Q223: SRC-TEXT-PSALMS; SRC-PSALMS-OVERVIEW; SRC-PSALM-SUPERSCRIPTIONS | R223: Needs Review | S223: Canonical-scope block for Psalms 107-121: restoration, royal, and pilgrimage collection.
A224: v0.2 | B224: Bible_Journey_Canon_Map_v0_2_Chronicles_Psalms_Job_1Kings.xlsx | C224: BLK-PSA-034-01 | D224: CRS-PSA-034 | E224: 1 | F224: Psalms | G224: 122 | H224: Poetic Connection | I224: Yes | J224: Yes | K224: No | L224: High | M224: Debated | N224: Poetry connection / debated historical link | P224: Poetic Connection | Q224: SRC-TEXT-PSALMS; SRC-PSALMS-OVERVIEW; SRC-PSALM-SUPERSCRIPTIONS | R224: Needs Review | S224: Canonical-scope block for Psalm 122: a Song of Ascents associated with David.
A225: v0.2 | B225: Bible_Journey_Canon_Map_v0_2_Chronicles_Psalms_Job_1Kings.xlsx | C225: BLK-PSA-035-01 | D225: CRS-PSA-035 | E225: 1 | F225: Psalms | G225: 123-126 | H225: Poetic Connection | I225: Yes | J225: Yes | K225: No | L225: High | M225: Unresolved | N225: Poetry collection / no fixed event placement | P225: Poetic Connection | Q225: SRC-TEXT-PSALMS; SRC-PSALMS-OVERVIEW; SRC-PSALM-SUPERSCRIPTIONS | R225: Needs Review | S225: Canonical-scope block for Psalms 123-126: Songs of Ascents.
A226: v0.2 | B226: Bible_Journey_Canon_Map_v0_2_Chronicles_Psalms_Job_1Kings.xlsx | C226: BLK-PSA-036-01 | D226: CRS-PSA-036 | E226: 1 | F226: Psalms | G226: 127 | H226: Poetic Connection | I226: Yes | J226: Yes | K226: No | L226: High | M226: Probable | N226: Solomonic window / no fixed event placement | O226: CRS-1KG-005 | P226: Poetic Connection | Q226: SRC-TEXT-PSALMS; SRC-PSALMS-OVERVIEW; SRC-PSALM-SUPERSCRIPTIONS | R226: Needs Review | S226: Canonical-scope block for Psalm 127: associated with Solomon.
A227: v0.2 | B227: Bible_Journey_Canon_Map_v0_2_Chronicles_Psalms_Job_1Kings.xlsx | C227: BLK-PSA-037-01 | D227: CRS-PSA-037 | E227: 1 | F227: Psalms | G227: 128-130 | H227: Poetic Connection | I227: Yes | J227: Yes | K227: No | L227: High | M227: Unresolved | N227: Poetry collection / no fixed event placement | P227: Poetic Connection | Q227: SRC-TEXT-PSALMS; SRC-PSALMS-OVERVIEW; SRC-PSALM-SUPERSCRIPTIONS | R227: Needs Review | S227: Canonical-scope block for Psalms 128-130: Songs of Ascents.
...

Sheet Master Chapter Coverage
A1: MASTER CHAPTER COVERAGE
A2: Canonical audit spine across all 66 books. Each chapter has one master record; split chapters require verse-level QA before release.
A4: Canonical Key | B4: Canonical Chapter Order | C4: Testament | D4: Book Order | E4: Book | F4: Chapter | G4: Map Version | H4: Source Workbook | I4: Source Coverage Sheet | J4: Local CRS ID | K4: Local Block ID(s) | L4: Source Coverage Status | M4: Source Note / QA | N4: Source Key(s) | O4: Source Row Count | P4: Master QA
A5: Genesis 1 | B5: 1 | C5: Old Testament | D5: 1 | E5: Genesis | F5: 1 | G5: v0.1 | H5: Bible_Journey_Canon_Map_v0_1_Genesis_to_2Samuel.xlsx | I5: Chapter Map | J5: CRS-GEN-001 | L5: Mapped | O5: 1 | P5: =IF(L5="MISSING","MISSING",IF(O5=1,"PASS","DUPLICATE")) -> PASS
A6: Genesis 2 | B6: 2 | C6: Old Testament | D6: 1 | E6: Genesis | F6: 2 | G6: v0.1 | H6: Bible_Journey_Canon_Map_v0_1_Genesis_to_2Samuel.xlsx | I6: Chapter Map | J6: CRS-GEN-001 | L6: Mapped | O6: 1 | P6: =IF(L6="MISSING","MISSING",IF(O6=1,"PASS","DUPLICATE")) -> PASS
A7: Genesis 3 | B7: 3 | C7: Old Testament | D7: 1 | E7: Genesis | F7: 3 | G7: v0.1 | H7: Bible_Journey_Canon_Map_v0_1_Genesis_to_2Samuel.xlsx | I7: Chapter Map | J7: CRS-GEN-001 | L7: Mapped | O7: 1 | P7: =IF(L7="MISSING","MISSING",IF(O7=1,"PASS","DUPLICATE")) -> PASS
A8: Genesis 4 | B8: 4 | C8: Old Testament | D8: 1 | E8: Genesis | F8: 4 | G8: v0.1 | H8: Bible_Journey_Canon_Map_v0_1_Genesis_to_2Samuel.xlsx | I8: Chapter Map | J8: CRS-GEN-002 | L8: Mapped | O8: 1 | P8: =IF(L8="MISSING","MISSING",IF(O8=1,"PASS","DUPLICATE")) -> PASS
A9: Genesis 5 | B9: 5 | C9: Old Testament | D9: 1 | E9: Genesis | F9: 5 | G9: v0.1 | H9: Bible_Journey_Canon_Map_v0_1_Genesis_to_2Samuel.xlsx | I9: Chapter Map | J9: CRS-GEN-002 | L9: Mapped | O9: 1 | P9: =IF(L9="MISSING","MISSING",IF(O9=1,"PASS","DUPLICATE")) -> PASS
A10: Genesis 6 | B10: 6 | C10: Old Testament | D10: 1 | E10: Genesis | F10: 6 | G10: v0.1 | H10: Bible_Journey_Canon_Map_v0_1_Genesis_to_2Samuel.xlsx | I10: Chapter Map | J10: CRS-GEN-003 | L10: Mapped | O10: 1 | P10: =IF(L10="MISSING","MISSING",IF(O10=1,"PASS","DUPLICATE")) -> PASS
A11: Genesis 7 | B11: 7 | C11: Old Testament | D11: 1 | E11: Genesis | F11: 7 | G11: v0.1 | H11: Bible_Journey_Canon_Map_v0_1_Genesis_to_2Samuel.xlsx | I11: Chapter Map | J11: CRS-GEN-003 | L11: Mapped | O11: 1 | P11: =IF(L11="MISSING","MISSING",IF(O11=1,"PASS","DUPLICATE")) -> PASS
A12: Genesis 8 | B12: 8 | C12: Old Testament | D12: 1 | E12: Genesis | F12: 8 | G12: v0.1 | H12: Bible_Journey_Canon_Map_v0_1_Genesis_to_2Samuel.xlsx | I12: Chapter Map | J12: CRS-GEN-003 | L12: Mapped | O12: 1 | P12: =IF(L12="MISSING","MISSING",IF(O12=1,"PASS","DUPLICATE")) -> PASS
A13: Genesis 9 | B13: 9 | C13: Old Testament | D13: 1 | E13: Genesis | F13: 9 | G13: v0.1 | H13: Bible_Journey_Canon_Map_v0_1_Genesis_to_2Samuel.xlsx | I13: Chapter Map | J13: CRS-GEN-003 | L13: Mapped | O13: 1 | P13: =IF(L13="MISSING","MISSING",IF(O13=1,"PASS","DUPLICATE")) -> PASS
A14: Genesis 10 | B14: 10 | C14: Old Testament | D14: 1 | E14: Genesis | F14: 10 | G14: v0.1 | H14: Bible_Journey_Canon_Map_v0_1_Genesis_to_2Samuel.xlsx | I14: Chapter Map | J14: CRS-GEN-004 | L14: Mapped | O14: 1 | P14: =IF(L14="MISSING","MISSING",IF(O14=1,"PASS","DUPLICATE")) -> PASS
A15: Genesis 11 | B15: 11 | C15: Old Testament | D15: 1 | E15: Genesis | F15: 11 | G15: v0.1 | H15: Bible_Journey_Canon_Map_v0_1_Genesis_to_2Samuel.xlsx | I15: Chapter Map | J15: CRS-GEN-004 | L15: Mapped | O15: 1 | P15: =IF(L15="MISSING","MISSING",IF(O15=1,"PASS","DUPLICATE")) -> PASS
A16: Genesis 12 | B16: 12 | C16: Old Testament | D16: 1 | E16: Genesis | F16: 12 | G16: v0.1 | H16: Bible_Journey_Canon_Map_v0_1_Genesis_to_2Samuel.xlsx | I16: Chapter Map | J16: CRS-GEN-005 | L16: Mapped | O16: 1 | P16: =IF(L16="MISSING","MISSING",IF(O16=1,"PASS","DUPLICATE")) -> PASS
... A297: 1 Kings 2 | B297: 293 | C297: Old Testament | D297: 11 | E297: 1 Kings | F297: 2 | G297: v0.2 | H297: Bible_Journey_Canon_Map_v0_2_Chronicles_Psalms_Job_1Kings.xlsx | I297: Chapter Map | J297: CRS-1KG-002 | L297: Mapped | O297: 1 | P297: =IF(L297="MISSING","MISSING",IF(O297=1,"PASS","DUPLICATE")) -> PASS
A298: 1 Kings 3 | B298: 294 | C298: Old Testament | D298: 11 | E298: 1 Kings | F298: 3 | G298: v0.2 | H298: Bible_Journey_Canon_Map_v0_2_Chronicles_Psalms_Job_1Kings.xlsx | I298: Chapter Map | J298: CRS-1KG-003 | L298: Mapped | M298: Future: 2 Chronicles 1 | O298: 1 | P298: =IF(L298="MISSING","MISSING",IF(O298=1,"PASS","DUPLICATE")) -> PASS
A299: 1 Kings 4 | B299: 295 | C299: Old Testament | D299: 11 | E299: 1 Kings | F299: 4 | G299: v0.2 | H299: Bible_Journey_Canon_Map_v0_2_Chronicles_Psalms_Job_1Kings.xlsx | I299: Chapter Map | J299: CRS-1KG-004 | L299: Mapped | O299: 1 | P299: =IF(L299="MISSING","MISSING",IF(O299=1,"PASS","DUPLICATE")) -> PASS
A300: 1 Kings 5 | B300: 296 | C300: Old Testament | D300: 11 | E300: 1 Kings | F300: 5 | G300: v0.2 | H300: Bible_Journey_Canon_Map_v0_2_Chronicles_Psalms_Job_1Kings.xlsx | I300: Chapter Map | J300: CRS-1KG-005 | L300: Mapped | M300: Future: 2 Chronicles 2-3 | O300: 1 | P300: =IF(L300="MISSING","MISSING",IF(O300=1,"PASS","DUPLICATE")) -> PASS
A301: 1 Kings 6 | B301: 297 | C301: Old Testament | D301: 11 | E301: 1 Kings | F301: 6 | G301: v0.2 | H301: Bible_Journey_Canon_Map_v0_2_Chronicles_Psalms_Job_1Kings.xlsx | I301: Chapter Map | J301: CRS-1KG-005 | L301: Mapped | M301: Future: 2 Chronicles 2-3 | O301: 1 | P301: =IF(L301="MISSING","MISSING",IF(O301=1,"PASS","DUPLICATE")) -> PASS
A302: 1 Kings 7 | B302: 298 | C302: Old Testament | D302: 11 | E302: 1 Kings | F302: 7 | G302: v0.2 | H302: Bible_Journey_Canon_Map_v0_2_Chronicles_Psalms_Job_1Kings.xlsx | I302: Chapter Map | J302: CRS-1KG-006 | L302: Mapped | O302: 1 | P302: =IF(L302="MISSING","MISSING",IF(O302=1,"PASS","DUPLICATE")) -> PASS
A303: 1 Kings 8 | B303: 299 | C303: Old Testament | D303: 11 | E303: 1 Kings | F303: 8 | G303: v0.2 | H303: Bible_Journey_Canon_Map_v0_2_Chronicles_Psalms_Job_1Kings.xlsx | I303: Chapter Map | J303: CRS-1KG-007 | L303: Mapped | M303: Future: 2 Chronicles 5-7 | O303: 1 | P303: =IF(L303="MISSING","MISSING",IF(O303=1,"PASS","DUPLICATE")) -> PASS
A304: 1 Kings 9 | B304: 300 | C304: Old Testament | D304: 11 | E304: 1 Kings | F304: 9 | G304: v0.2 | H304: Bible_Journey_Canon_Map_v0_2_Chronicles_Psalms_Job_1Kings.xlsx | I304: Chapter Map | J304: CRS-1KG-008 | L304: Mapped | O304: 1 | P304: =IF(L304="MISSING","MISSING",IF(O304=1,"PASS","DUPLICATE")) -> PASS
A305: 1 Kings 10 | B305: 301 | C305: Old Testament | D305: 11 | E305: 1 Kings | F305: 10 | G305: v0.2 | H305: Bible_Journey_Canon_Map_v0_2_Chronicles_Psalms_Job_1Kings.xlsx | I305: Chapter Map | J305: CRS-1KG-009 | L305: Mapped | M305: Future: 2 Chronicles 9 | O305: 1 | P305: =IF(L305="MISSING","MISSING",IF(O305=1,"PASS","DUPLICATE")) -> PASS
A306: 1 Kings 11 | B306: 302 | C306: Old Testament | D306: 11 | E306: 1 Kings | F306: 11 | G306: v0.2 | H306: Bible_Journey_Canon_Map_v0_2_Chronicles_Psalms_Job_1Kings.xlsx | I306: Chapter Map | J306: CRS-1KG-010 | L306: Mapped | O306: 1 | P306: =IF(L306="MISSING","MISSING",IF(O306=1,"PASS","DUPLICATE")) -> PASS
A307: 1 Kings 12 | B307: 303 | C307: Old Testament | D307: 11 | E307: 1 Kings | F307: 12 | G307: v0.2 | H307: Bible_Journey_Canon_Map_v0_2_Chronicles_Psalms_Job_1Kings.xlsx | I307: Chapter Map | J307: CRS-1KG-011 | L307: Mapped | M307: Future: 2 Chronicles 10 | O307: 1 | P307: =IF(L307="MISSING","MISSING",IF(O307=1,"PASS","DUPLICATE")) -> PASS
A308: 1 Kings 13 | B308: 304 | C308: Old Testament | D308: 11 | E308: 1 Kings | F308: 13 | G308: v0.2 | H308: Bible_Journey_Canon_Map_v0_2_Chronicles_Psalms_Job_1Kings.xlsx | I308: Chapter Map | J308: CRS-1KG-012 | L308: Mapped | O308: 1 | P308: =IF(L308="MISSING","MISSING",IF(O308=1,"PASS","DUPLICATE")) -> PASS
A309: 1 Kings 14 | B309: 305 | C309: Old Testament | D309: 11 | E309: 1 Kings | F309: 14 | G309: v0.2 | H309: Bible_Journey_Canon_Map_v0_2_Chronicles_Psalms_Job_1Kings.xlsx | I309: Chapter Map | J309: CRS-1KG-013 | L309: Mapped | M309: Future: 2 Chronicles 12 | O309: 1 | P309: =IF(L309="MISSING","MISSING",IF(O309=1,"PASS","DUPLICATE")) -> PASS
A310: 1 Kings 15 | B310: 306 | C310: Old Testament | D310: 11 | E310: 1 Kings | F310: 15 | G310: v0.2 | H310: Bible_Journey_Canon_Map_v0_2_Chronicles_Psalms_Job_1Kings.xlsx | I310: Chapter Map | J310: CRS-1KG-014 | L310: Mapped | M310: Future: 2 Chronicles 13-16 | O310: 1 | P310: =IF(L310="MISSING","MISSING",IF(O310=1,"PASS","DUPLICATE")) -> PASS
A311: 1 Kings 16 | B311: 307 | C311: Old Testament | D311: 11 | E311: 1 Kings | F311: 16 | G311: v0.2 | H311: Bible_Journey_Canon_Map_v0_2_Chronicles_Psalms_Job_1Kings.xlsx | I311: Chapter Map | J311: CRS-1KG-015 | L311: Mapped | O311: 1 | P311: =IF(L311="MISSING","MISSING",IF(O311=1,"PASS","DUPLICATE")) -> PASS
A312: 1 Kings 17 | B312: 308 | C312: Old Testament | D312: 11 | E312: 1 Kings | F312: 17 | G312: v0.2 | H312: Bible_Journey_Canon_Map_v0_2_Chronicles_Psalms_Job_1Kings.xlsx | I312: Chapter Map | J312: CRS-1KG-016 | L312: Mapped | O312: 1 | P312: =IF(L312="MISSING","MISSING",IF(O312=1,"PASS","DUPLICATE")) -> PASS
A313: 1 Kings 18 | B313: 309 | C313: Old Testament | D313: 11 | E313: 1 Kings | F313: 18 | G313: v0.2 | H313: Bible_Journey_Canon_Map_v0_2_Chronicles_Psalms_Job_1Kings.xlsx | I313: Chapter Map | J313: CRS-1KG-017 | L313: Mapped | O313: 1 | P313: =IF(L313="MISSING","MISSING",IF(O313=1,"PASS","DUPLICATE")) -> PASS
A314: 1 Kings 19 | B314: 310 | C314: Old Testament | D314: 11 | E314: 1 Kings | F314: 19 | G314: v0.2 | H314: Bible_Journey_Canon_Map_v0_2_Chronicles_Psalms_Job_1Kings.xlsx | I314: Chapter Map | J314: CRS-1KG-018 | L314: Mapped | O314: 1 | P314: =IF(L314="MISSING","MISSING",IF(O314=1,"PASS","DUPLICATE")) -> PASS
A315: 1 Kings 20 | B315: 311 | C315: Old Testament | D315: 11 | E315: 1 Kings | F315: 20 | G315: v0.2 | H315: Bible_Journey_Canon_Map_v0_2_Chronicles_Psalms_Job_1Kings.xlsx | I315: Chapter Map | J315: CRS-1KG-019 | L315: Mapped | O315: 1 | P315: =IF(L315="MISSING","MISSING",IF(O315=1,"PASS","DUPLICATE")) -> PASS
A316: 1 Kings 21 | B316: 312 | C316: Old Testament | D316: 11 | E316: 1 Kings | F316: 21 | G316: v0.2 | H316: Bible_Journey_Canon_Map_v0_2_Chronicles_Psalms_Job_1Kings.xlsx | I316: Chapter Map | J316: CRS-1KG-020 | L316: Mapped | O316: 1 | P316: =IF(L316="MISSING","MISSING",IF(O316=1,"PASS","DUPLICATE")) -> PASS
A317: 1 Kings 22 | B317: 313 | C317: Old Testament | D317: 11 | E317: 1 Kings | F317: 22 | G317: v0.2 | H317: Bible_Journey_Canon_Map_v0_2_Chronicles_Psalms_Job_1Kings.xlsx | I317: Chapter Map | J317: CRS-1KG-021 | L317: Mapped | M317: Future: 2 Chronicles 18 | O317: 1 | P317: =IF(L317="MISSING","MISSING",IF(O317=1,"PASS","DUPLICATE")) -> PASS
A318: 2 Kings 1 | B318: 314 | C318: Old Testament | D318: 12 | E318: 2 Kings | F318: 1 | G318: v0.3 | H318: Bible_Journey_Canon_Map_v0_3_2Chronicles_Wisdom_2Kings.xlsx | I318: Chapter Map | J318: CRS-2K-001 | L318: Mapped | M318: Ahaziah's inquiry and Elijah's judgment. No Chronicles parallel. | O318: 1 | P318: =IF(L318="MISSING","MISSING",IF(O318=1,"PASS","DUPLICATE")) -> PASS
A319: 2 Kings 2 | B319: 315 | C319: Old Testament | D319: 12 | E319: 2 Kings | F319: 2 | G319: v0.3 | H319: Bible_Journey_Canon_Map_v0_3_2Chronicles_Wisdom_2Kings.xlsx | I319: Chapter Map | J319: CRS-2K-002 | L319: Mapped | M319: Elijah's departure and the public transition to Elisha. | O319: 1 | P319: =IF(L319="MISSING","MISSING",IF(O319=1,"PASS","DUPLICATE")) -> PASS
A320: 2 Kings 3 | B320: 316 | C320: Old Testament | D320: 12 | E320: 2 Kings | F320: 3 | G320: v0.3 | H320: Bible_Journey_Canon_Map_v0_3_2Chronicles_Wisdom_2Kings.xlsx | I320: Chapter Map | J320: CRS-2K-003 | L320: Mapped | M320: A coalition campaign narrated through the role of Elisha. | O320: 1 | P320: =IF(L320="MISSING","MISSING",IF(O320=1,"PASS","DUPLICATE")) -> PASS
A321: 2 Kings 4 | B321: 317 | C321: Old Testament | D321: 12 | E321: 2 Kings | F321: 4 | G321: v0.3 | H321: Bible_Journey_Canon_Map_v0_3_2Chronicles_Wisdom_2Kings.xlsx | I321: Chapter Map | J321: CRS-2K-004 | L321: Mapped | M321: A linked cycle of Elisha narratives; retain as one canonical chapter for the first mapping pass. | O321: 1 | P321: =IF(L321="MISSING","MISSING",IF(O321=1,"PASS","DUPLICATE")) -> PASS
A322: 2 Kings 5 | B322: 318 | C322: Old Testament | D322: 12 | E322: 2 Kings | F322: 5 | G322: v0.3 | H322: Bible_Journey_Canon_Map_v0_3_2Chronicles_Wisdom_2Kings.xlsx | I322: Chapter Map | J322: CRS-2K-005 | L322: Mapped | M322: A distinct healing and mission-to-Aram narrative. | O322: 1 | P322: =IF(L322="MISSING","MISSING",IF(O322=1,"PASS","DUPLICATE")) -> PASS
A323: 2 Kings 6 | B323: 319 | C323: Old Testament | D323: 12 | E323: 2 Kings | F323: 6 | G323: v0.3 | H323: Bible_Journey_Canon_Map_v0_3_2Chronicles_Wisdom_2Kings.xlsx | I323: Chapter Map | J323: CRS-2K-006 | L323: Mapped | M323: Contains multiple scenes; future scene-level splits may refine this chapter. | O323: 1 | P323: =IF(L323="MISSING","MISSING",IF(O323=1,"PASS","DUPLICATE")) -> PASS
A324: 2 Kings 7 | B324: 320 | C324: Old Testament | D324: 12 | E324: 2 Kings | F324: 7 | G324: v0.3 | H324: Bible_Journey_Canon_Map_v0_3_2Chronicles_Wisdom_2Kings.xlsx | I324: Chapter Map | J324: CRS-2K-007 | L324: Mapped | M324: A discrete narrative continuation of the siege introduced in 2 Kings 6. | O324: 1 | P324: =IF(L324="MISSING","MISSING",IF(O324=1,"PASS","DUPLICATE")) -> PASS
A325: 2 Kings 8 | B325: 321 | C325: Old Testament | D325: 12 | E325: 2 Kings | F325: 8 | G325: v0.3 | H325: Bible_Journey_Canon_Map_v0_3_2Chronicles_Wisdom_2Kings.xlsx | I325: Chapter Map | J325: CRS-2K-008A / CRS-2K-008B | L325: Mapped with scene split | M325: 2 Kings 8:1-15 belongs to CRS-2K-008A; 2 Kings 8:16-29 belongs to CRS-2K-008B. | O325: 1 | P325: =IF(L325="MISSING","MISSING",IF(O325=1,"PASS","DUPLICATE")) -> PASS
A326: 2 Kings 9 | B326: 322 | C326: Old Testament | D326: 12 | E326: 2 Kings | F326: 9 | G326: v0.3 | H326: Bible_Journey_Canon_Map_v0_3_2Chronicles_Wisdom_2Kings.xlsx | I326: Chapter Map | J326: CRS-2K-009 | L326: Mapped | M326: Jehu's anointing and overthrow of Joram / Jezebel sequence. | O326: 1 | P326: =IF(L326="MISSING","MISSING",IF(O326=1,"PASS","DUPLICATE")) -> PASS
A327: 2 Kings 10 | B327: 323 | C327: Old Testament | D327: 12 | E327: 2 Kings | F327: 10 | G327: v0.3 | H327: Bible_Journey_Canon_Map_v0_3_2Chronicles_Wisdom_2Kings.xlsx | I327: Chapter Map | J327: CRS-2K-010 | L327: Mapped | M327: Jehu's purge, cultic reforms, and northern reign assessment. | O327: 1 | P327: =IF(L327="MISSING","MISSING",IF(O327=1,"PASS","DUPLICATE")) -> PASS
A328: 2 Kings 11 | B328: 324 | C328: Old Testament | D328: 12 | E328: 2 Kings | F328: 11 | G328: v0.3 | H328: Bible_Journey_Canon_Map_v0_3_2Chronicles_Wisdom_2Kings.xlsx | I328: Chapter Map | J328: CRS-2K-011 | L328: Mapped | M328: Linked to 2 Chronicles 22:10-12 and 23; preserve all accounts as distinct blocks. | O328: 1 | P328: =IF(L328="MISSING","MISSING",IF(O328=1,"PASS","DUPLICATE")) -> PASS
... A407: 2 Chronicles 36 | B407: 403 | C407: Old Testament | D407: 14 | E407: 2 Chronicles | F407: 36 | G407: v0.3 | H407: Bible_Journey_Canon_Map_v0_3_2Chronicles_Wisdom_2Kings.xlsx | I407: Chapter Map | J407: CRS-2K-024 / CRS-2K-025 | L407: Mapped with scene split | M407: 2 Chronicles 36:1-21 belongs to CRS-2K-024; 36:22-23 belongs to CRS-2K-025 as a bridge to Ezra. | O407: 1 | P407: =IF(L407="MISSING","MISSING",IF(O407=1,"PASS","DUPLICATE")) -> PASS
A408: Ezra 1 | B408: 404 | C408: Old Testament | D408: 15 | E408: Ezra | F408: 1 | G408: v0.5 | H408: Bible_Journey_Canon_Map_v0_5_Exile_Return_Persia.xlsx | I408: Coverage Audit | J408: CRS-05-022 | K408: BLK-05-022 | L408: Covered | M408: Single reading block | O408: 1 | P408: =IF(L408="MISSING","MISSING",IF(O408=1,"PASS","DUPLICATE")) -> PASS
A409: Ezra 2 | B409: 405 | C409: Old Testament | D409: 15 | E409: Ezra | F409: 2 | G409: v0.5 | H409: Bible_Journey_Canon_Map_v0_5_Exile_Return_Persia.xlsx | I409: Coverage Audit | J409: CRS-05-023 | K409: BLK-05-023 | L409: Covered | M409: Single reading block | O409: 1 | P409: =IF(L409="MISSING","MISSING",IF(O409=1,"PASS","DUPLICATE")) -> PASS
A410: Ezra 3 | B410: 406 | C410: Old Testament | D410: 15 | E410: Ezra | F410: 3 | G410: v0.5 | H410: Bible_Journey_Canon_Map_v0_5_Exile_Return_Persia.xlsx | I410: Coverage Audit | J410: CRS-05-023 | K410: BLK-05-023 | L410: Covered | M410: Single reading block | O410: 1 | P410: =IF(L410="MISSING","MISSING",IF(O410=1,"PASS","DUPLICATE")) -> PASS
A411: Ezra 4 | B411: 407 | C411: Old Testament | D411: 15 | E411: Ezra | F411: 4 | G411: v0.5 | H411: Bible_Journey_Canon_Map_v0_5_Exile_Return_Persia.xlsx | I411: Coverage Audit | J411: CRS-05-024 | K411: BLK-05-024, BLK-05-027, BLK-05-034, BLK-05-035 | L411: Covered | M411: Split across reading blocks | O411: 1 | P411: =IF(L411="MISSING","MISSING",IF(O411=1,"PASS","DUPLICATE")) -> PASS
A412: Ezra 5 | B412: 408 | C412: Old Testament | D412: 15 | E412: Ezra | F412: 5 | G412: v0.5 | H412: Bible_Journey_Canon_Map_v0_5_Exile_Return_Persia.xlsx | I412: Coverage Audit | J412: CRS-05-027 | K412: BLK-05-027, BLK-05-031 | L412: Covered | M412: Split across reading blocks | O412: 1 | P412: =IF(L412="MISSING","MISSING",IF(O412=1,"PASS","DUPLICATE")) -> PASS
A413: Ezra 6 | B413: 409 | C413: Old Testament | D413: 15 | E413: Ezra | F413: 6 | G413: v0.5 | H413: Bible_Journey_Canon_Map_v0_5_Exile_Return_Persia.xlsx | I413: Coverage Audit | J413: CRS-05-032 | K413: BLK-05-032 | L413: Covered | M413: Single reading block | O413: 1 | P413: =IF(L413="MISSING","MISSING",IF(O413=1,"PASS","DUPLICATE")) -> PASS
A414: Ezra 7 | B414: 410 | C414: Old Testament | D414: 15 | E414: Ezra | F414: 7 | G414: v0.5 | H414: Bible_Journey_Canon_Map_v0_5_Exile_Return_Persia.xlsx | I414: Coverage Audit | J414: CRS-05-036 | K414: BLK-05-036 | L414: Covered | M414: Single reading block | O414: 1 | P414: =IF(L414="MISSING","MISSING",IF(O414=1,"PASS","DUPLICATE")) -> PASS
A415: Ezra 8 | B415: 411 | C415: Old Testament | D415: 15 | E415: Ezra | F415: 8 | G415: v0.5 | H415: Bible_Journey_Canon_Map_v0_5_Exile_Return_Persia.xlsx | I415: Coverage Audit | J415: CRS-05-036 | K415: BLK-05-036 | L415: Covered | M415: Single reading block | O415: 1 | P415: =IF(L415="MISSING","MISSING",IF(O415=1,"PASS","DUPLICATE")) -> PASS
A416: Ezra 9 | B416: 412 | C416: Old Testament | D416: 15 | E416: Ezra | F416: 9 | G416: v0.5 | H416: Bible_Journey_Canon_Map_v0_5_Exile_Return_Persia.xlsx | I416: Coverage Audit | J416: CRS-05-037 | K416: BLK-05-037 | L416: Covered | M416: Single reading block | O416: 1 | P416: =IF(L416="MISSING","MISSING",IF(O416=1,"PASS","DUPLICATE")) -> PASS
A417: Ezra 10 | B417: 413 | C417: Old Testament | D417: 15 | E417: Ezra | F417: 10 | G417: v0.5 | H417: Bible_Journey_Canon_Map_v0_5_Exile_Return_Persia.xlsx | I417: Coverage Audit | J417: CRS-05-037 | K417: BLK-05-037 | L417: Covered | M417: Single reading block | O417: 1 | P417: =IF(L417="MISSING","MISSING",IF(O417=1,"PASS","DUPLICATE")) -> PASS
A418: Nehemiah 1 | B418: 414 | C418: Old Testament | D418: 16 | E418: Nehemiah | F418: 1 | G418: v0.5 | H418: Bible_Journey_Canon_Map_v0_5_Exile_Return_Persia.xlsx | I418: Coverage Audit | J418: CRS-05-038 | K418: BLK-05-038 | L418: Covered | M418: Single reading block | O418: 1 | P418: =IF(L418="MISSING","MISSING",IF(O418=1,"PASS","DUPLICATE")) -> PASS
A419: Nehemiah 2 | B419: 415 | C419: Old Testament | D419: 16 | E419: Nehemiah | F419: 2 | G419: v0.5 | H419: Bible_Journey_Canon_Map_v0_5_Exile_Return_Persia.xlsx | I419: Coverage Audit | J419: CRS-05-038 | K419: BLK-05-038 | L419: Covered | M419: Single reading block | O419: 1 | P419: =IF(L419="MISSING","MISSING",IF(O419=1,"PASS","DUPLICATE")) -> PASS
... A440: Esther 10 | B440: 436 | C440: Old Testament | D440: 17 | E440: Esther | F440: 10 | G440: v0.6 | H440: Bible_Journey_Canon_Map_v0_6_Esther_Intertestamental_Bridge.xlsx | I440: Coverage Audit | J440: CRS-06-004 | K440: BLK-06-004 | L440: Covered | M440: Single canonical block | O440: 1 | P440: =IF(L440="MISSING","MISSING",IF(O440=1,"PASS","DUPLICATE")) -> PASS
A441: Job 1 | B441: 437 | C441: Old Testament | D441: 18 | E441: Job | F441: 1 | G441: v0.2 | H441: Bible_Journey_Canon_Map_v0_2_Chronicles_Psalms_Job_1Kings.xlsx | I441: Chapter Map | J441: CRS-JOB-001 | L441: Mapped | M441: Book-level sequence is intact; position in global chronology is unresolved. | O441: 1 | P441: =IF(L441="MISSING","MISSING",IF(O441=1,"PASS","DUPLICATE")) -> PASS
A442: Job 2 | B442: 438 | C442: Old Testament | D442: 18 | E442: Job | F442: 2 | G442: v0.2 | H442: Bible_Journey_Canon_Map_v0_2_Chronicles_Psalms_Job_1Kings.xlsx | I442: Chapter Map | J442: CRS-JOB-001 | L442: Mapped | M442: Book-level sequence is intact; position in global chronology is unresolved. | O442: 1 | P442: =IF(L442="MISSING","MISSING",IF(O442=1,"PASS","DUPLICATE")) -> PASS
A443: Job 3 | B443: 439 | C443: Old Testament | D443: 18 | E443: Job | F443: 3 | G443: v0.2 | H443: Bible_Journey_Canon_Map_v0_2_Chronicles_Psalms_Job_1Kings.xlsx | I443: Chapter Map | J443: CRS-JOB-002 | L443: Mapped | M443: Book-level sequence is intact; position in global chronology is unresolved. | O443: 1 | P443: =IF(L443="MISSING","MISSING",IF(O443=1,"PASS","DUPLICATE")) -> PASS
A444: Job 4 | B444: 440 | C444: Old Testament | D444: 18 | E444: Job | F444: 4 | G444: v0.2 | H444: Bible_Journey_Canon_Map_v0_2_Chronicles_Psalms_Job_1Kings.xlsx | I444: Chapter Map | J444: CRS-JOB-003 | L444: Mapped | M444: Book-level sequence is intact; position in global chronology is unresolved. | O444: 1 | P444: =IF(L444="MISSING","MISSING",IF(O444=1,"PASS","DUPLICATE")) -> PASS
A445: Job 5 | B445: 441 | C445: Old Testament | D445: 18 | E445: Job | F445: 5 | G445: v0.2 | H445: Bible_Journey_Canon_Map_v0_2_Chronicles_Psalms_Job_1Kings.xlsx | I445: Chapter Map | J445: CRS-JOB-003 | L445: Mapped | M445: Book-level sequence is intact; position in global chronology is unresolved. | O445: 1 | P445: =IF(L445="MISSING","MISSING",IF(O445=1,"PASS","DUPLICATE")) -> PASS
A446: Job 6 | B446: 442 | C446: Old Testament | D446: 18 | E446: Job | F446: 6 | G446: v0.2 | H446: Bible_Journey_Canon_Map_v0_2_Chronicles_Psalms_Job_1Kings.xlsx | I446: Chapter Map | J446: CRS-JOB-003 | L446: Mapped | M446: Book-level sequence is intact; position in global chronology is unresolved. | O446: 1 | P446: =IF(L446="MISSING","MISSING",IF(O446=1,"PASS","DUPLICATE")) -> PASS
A447: Job 7 | B447: 443 | C447: Old Testament | D447: 18 | E447: Job | F447: 7 | G447: v0.2 | H447: Bible_Journey_Canon_Map_v0_2_Chronicles_Psalms_Job_1Kings.xlsx | I447: Chapter Map | J447: CRS-JOB-003 | L447: Mapped | M447: Book-level sequence is intact; position in global chronology is unresolved. | O447: 1 | P447: =IF(L447="MISSING","MISSING",IF(O447=1,"PASS","DUPLICATE")) -> PASS
A448: Job 8 | B448: 444 | C448: Old Testament | D448: 18 | E448: Job | F448: 8 | G448: v0.2 | H448: Bible_Journey_Canon_Map_v0_2_Chronicles_Psalms_Job_1Kings.xlsx | I448: Chapter Map | J448: CRS-JOB-003 | L448: Mapped | M448: Book-level sequence is intact; position in global chronology is unresolved. | O448: 1 | P448: =IF(L448="MISSING","MISSING",IF(O448=1,"PASS","DUPLICATE")) -> PASS
A449: Job 9 | B449: 445 | C449: Old Testament | D449: 18 | E449: Job | F449: 9 | G449: v0.2 | H449: Bible_Journey_Canon_Map_v0_2_Chronicles_Psalms_Job_1Kings.xlsx | I449: Chapter Map | J449: CRS-JOB-003 | L449: Mapped | M449: Book-level sequence is intact; position in global chronology is unresolved. | O449: 1 | P449: =IF(L449="MISSING","MISSING",IF(O449=1,"PASS","DUPLICATE")) -> PASS
A450: Job 10 | B450: 446 | C450: Old Testament | D450: 18 | E450: Job | F450: 10 | G450: v0.2 | H450: Bible_Journey_Canon_Map_v0_2_Chronicles_Psalms_Job_1Kings.xlsx | I450: Chapter Map | J450: CRS-JOB-003 | L450: Mapped | M450: Book-level sequence is intact; position in global chronology is unresolved. | O450: 1 | P450: =IF(L450="MISSING","MISSING",IF(O450=1,"PASS","DUPLICATE")) -> PASS
A451: Job 11 | B451: 447 | C451: Old Testament | D451: 18 | E451: Job | F451: 11 | G451: v0.2 | H451: Bible_Journey_Canon_Map_v0_2_Chronicles_Psalms_Job_1Kings.xlsx | I451: Chapter Map | J451: CRS-JOB-003 | L451: Mapped | M451: Book-level sequence is intact; position in global chronology is unresolved. | O451: 1 | P451: =IF(L451="MISSING","MISSING",IF(O451=1,"PASS","DUPLICATE")) -> PASS
A452: Job 12 | B452: 448 | C452: Old Testament | D452: 18 | E452: Job | F452: 12 | G452: v0.2 | H452: Bible_Journey_Canon_Map_v0_2_Chronicles_Psalms_Job_1Kings.xlsx | I452: Chapter Map | J452: CRS-JOB-003 | L452: Mapped | M452: Book-level sequence is intact; position in global chronology is unresolved. | O452: 1 | P452: =IF(L452="MISSING","MISSING",IF(O452=1,"PASS","DUPLICATE")) -> PASS
... A683: Song of Songs 8 | B683: 679 | C683: Old Testament | D683: 22 | E683: Song of Songs | F683: 8 | G683: v0.3 | H683: Bible_Journey_Canon_Map_v0_3_2Chronicles_Wisdom_2Kings.xlsx | I683: Chapter Map | J683: CRS-WIS-003 | L683: Mapped with disclosed uncertainty | M683: Placed in the traditional Solomonic association window while the app clearly distinguishes tradition from settled historical authorship. | O683: 1 | P683: =IF(L683="MISSING","MISSING",IF(O683=1,"PASS","DUPLICATE")) -> PASS
A684: Isaiah 1 | B684: 680 | C684: Old Testament | D684: 23 | E684: Isaiah | F684: 1 | G684: v0.4 | H684: Bible_Journey_Canon_Map_v0_4_Prophets_Exile.xlsx | I684: Chapter Map | J684: CRS-04-008 | K684: RB-04-008 | L684: Main Stream | M684: Not reviewed | N684: S1; S2; S3; S7 | O684: 1 | P684: =IF(L684="MISSING","MISSING",IF(O684=1,"PASS","DUPLICATE")) -> PASS
A685: Isaiah 2 | B685: 681 | C685: Old Testament | D685: 23 | E685: Isaiah | F685: 2 | G685: v0.4 | H685: Bible_Journey_Canon_Map_v0_4_Prophets_Exile.xlsx | I685: Chapter Map | J685: CRS-04-008 | K685: RB-04-008 | L685: Main Stream | M685: Not reviewed | N685: S1; S2; S3; S7 | O685: 1 | P685: =IF(L685="MISSING","MISSING",IF(O685=1,"PASS","DUPLICATE")) -> PASS
A686: Isaiah 3 | B686: 682 | C686: Old Testament | D686: 23 | E686: Isaiah | F686: 3 | G686: v0.4 | H686: Bible_Journey_Canon_Map_v0_4_Prophets_Exile.xlsx | I686: Chapter Map | J686: CRS-04-008 | K686: RB-04-008 | L686: Main Stream | M686: Not reviewed | N686: S1; S2; S3; S7 | O686: 1 | P686: =IF(L686="MISSING","MISSING",IF(O686=1,"PASS","DUPLICATE")) -> PASS
A687: Isaiah 4 | B687: 683 | C687: Old Testament | D687: 23 | E687: Isaiah | F687: 4 | G687: v0.4 | H687: Bible_Journey_Canon_Map_v0_4_Prophets_Exile.xlsx | I687: Chapter Map | J687: CRS-04-008 | K687: RB-04-008 | L687: Main Stream | M687: Not reviewed | N687: S1; S2; S3; S7 | O687: 1 | P687: =IF(L687="MISSING","MISSING",IF(O687=1,"PASS","DUPLICATE")) -> PASS
A688: Isaiah 5 | B688: 684 | C688: Old Testament | D688: 23 | E688: Isaiah | F688: 5 | G688: v0.4 | H688: Bible_Journey_Canon_Map_v0_4_Prophets_Exile.xlsx | I688: Chapter Map | J688: CRS-04-008 | K688: RB-04-008 | L688: Main Stream | M688: Not reviewed | N688: S1; S2; S3; S7 | O688: 1 | P688: =IF(L688="MISSING","MISSING",IF(O688=1,"PASS","DUPLICATE")) -> PASS
A689: Isaiah 6 | B689: 685 | C689: Old Testament | D689: 23 | E689: Isaiah | F689: 6 | G689: v0.4 | H689: Bible_Journey_Canon_Map_v0_4_Prophets_Exile.xlsx | I689: Chapter Map | J689: CRS-04-009 | K689: RB-04-009 | L689: Main Stream | M689: Not reviewed | N689: S1; S2; S3 | O689: 1 | P689: =IF(L689="MISSING","MISSING",IF(O689=1,"PASS","DUPLICATE")) -> PASS
A690: Isaiah 7 | B690: 686 | C690: Old Testament | D690: 23 | E690: Isaiah | F690: 7 | G690: v0.4 | H690: Bible_Journey_Canon_Map_v0_4_Prophets_Exile.xlsx | I690: Chapter Map | J690: CRS-04-013 | K690: RB-04-013 | L690: Main Stream | M690: Not reviewed | N690: S1; S3; S11 | O690: 1 | P690: =IF(L690="MISSING","MISSING",IF(O690=1,"PASS","DUPLICATE")) -> PASS
A691: Isaiah 8 | B691: 687 | C691: Old Testament | D691: 23 | E691: Isaiah | F691: 8 | G691: v0.4 | H691: Bible_Journey_Canon_Map_v0_4_Prophets_Exile.xlsx | I691: Chapter Map | J691: CRS-04-013 | K691: RB-04-013 | L691: Main Stream | M691: Not reviewed | N691: S1; S3; S11 | O691: 1 | P691: =IF(L691="MISSING","MISSING",IF(O691=1,"PASS","DUPLICATE")) -> PASS
A692: Isaiah 9 | B692: 688 | C692: Old Testament | D692: 23 | E692: Isaiah | F692: 9 | G692: v0.4 | H692: Bible_Journey_Canon_Map_v0_4_Prophets_Exile.xlsx | I692: Chapter Map | J692: CRS-04-013 | K692: RB-04-013 | L692: Main Stream | M692: Not reviewed | N692: S1; S3; S11 | O692: 1 | P692: =IF(L692="MISSING","MISSING",IF(O692=1,"PASS","DUPLICATE")) -> PASS
A693: Isaiah 10 | B693: 689 | C693: Old Testament | D693: 23 | E693: Isaiah | F693: 10 | G693: v0.4 | H693: Bible_Journey_Canon_Map_v0_4_Prophets_Exile.xlsx | I693: Chapter Map | J693: CRS-04-013 | K693: RB-04-013 | L693: Main Stream | M693: Not reviewed | N693: S1; S3; S11 | O693: 1 | P693: =IF(L693="MISSING","MISSING",IF(O693=1,"PASS","DUPLICATE")) -> PASS
A694: Isaiah 11 | B694: 690 | C694: Old Testament | D694: 23 | E694: Isaiah | F694: 11 | G694: v0.4 | H694: Bible_Journey_Canon_Map_v0_4_Prophets_Exile.xlsx | I694: Chapter Map | J694: CRS-04-013 | K694: RB-04-013 | L694: Main Stream | M694: Not reviewed | N694: S1; S3; S11 | O694: 1 | P694: =IF(L694="MISSING","MISSING",IF(O694=1,"PASS","DUPLICATE")) -> PASS
A695: Isaiah 12 | B695: 691 | C695: Old Testament | D695: 23 | E695: Isaiah | F695: 12 | G695: v0.4 | H695: Bible_Journey_Canon_Map_v0_4_Prophets_Exile.xlsx | I695: Chapter Map | J695: CRS-04-013 | K695: RB-04-013 | L695: Main Stream | M695: Not reviewed | N695: S1; S3; S11 | O695: 1 | P695: =IF(L695="MISSING","MISSING",IF(O695=1,"PASS","DUPLICATE")) -> PASS
... A806: Lamentations 5 | B806: 802 | C806: Old Testament | D806: 25 | E806: Lamentations | F806: 5 | G806: v0.4 | H806: Bible_Journey_Canon_Map_v0_4_Prophets_Exile.xlsx | I806: Chapter Map | J806: CRS-04-045 | K806: RB-04-047 | L806: Main Stream | M806: Not reviewed | N806: S5; S7 | O806: 1 | P806: =IF(L806="MISSING","MISSING",IF(O806=1,"PASS","DUPLICATE")) -> PASS
A807: Ezekiel 1 | B807: 803 | C807: Old Testament | D807: 26 | E807: Ezekiel | F807: 1 | G807: v0.5 | H807: Bible_Journey_Canon_Map_v0_5_Exile_Return_Persia.xlsx | I807: Coverage Audit | J807: CRS-05-004 | K807: BLK-05-004 | L807: Covered | M807: Single reading block | O807: 1 | P807: =IF(L807="MISSING","MISSING",IF(O807=1,"PASS","DUPLICATE")) -> PASS
A808: Ezekiel 2 | B808: 804 | C808: Old Testament | D808: 26 | E808: Ezekiel | F808: 2 | G808: v0.5 | H808: Bible_Journey_Canon_Map_v0_5_Exile_Return_Persia.xlsx | I808: Coverage Audit | J808: CRS-05-004 | K808: BLK-05-004 | L808: Covered | M808: Single reading block | O808: 1 | P808: =IF(L808="MISSING","MISSING",IF(O808=1,"PASS","DUPLICATE")) -> PASS
A809: Ezekiel 3 | B809: 805 | C809: Old Testament | D809: 26 | E809: Ezekiel | F809: 3 | G809: v0.5 | H809: Bible_Journey_Canon_Map_v0_5_Exile_Return_Persia.xlsx | I809: Coverage Audit | J809: CRS-05-004 | K809: BLK-05-004, BLK-05-005 | L809: Covered | M809: Split across reading blocks | O809: 1 | P809: =IF(L809="MISSING","MISSING",IF(O809=1,"PASS","DUPLICATE")) -> PASS
A810: Ezekiel 4 | B810: 806 | C810: Old Testament | D810: 26 | E810: Ezekiel | F810: 4 | G810: v0.5 | H810: Bible_Journey_Canon_Map_v0_5_Exile_Return_Persia.xlsx | I810: Coverage Audit | J810: CRS-05-005 | K810: BLK-05-005 | L810: Covered | M810: Single reading block | O810: 1 | P810: =IF(L810="MISSING","MISSING",IF(O810=1,"PASS","DUPLICATE")) -> PASS
A811: Ezekiel 5 | B811: 807 | C811: Old Testament | D811: 26 | E811: Ezekiel | F811: 5 | G811: v0.5 | H811: Bible_Journey_Canon_Map_v0_5_Exile_Return_Persia.xlsx | I811: Coverage Audit | J811: CRS-05-005 | K811: BLK-05-005 | L811: Covered | M811: Single reading block | O811: 1 | P811: =IF(L811="MISSING","MISSING",IF(O811=1,"PASS","DUPLICATE")) -> PASS
A812: Ezekiel 6 | B812: 808 | C812: Old Testament | D812: 26 | E812: Ezekiel | F812: 6 | G812: v0.5 | H812: Bible_Journey_Canon_Map_v0_5_Exile_Return_Persia.xlsx | I812: Coverage Audit | J812: CRS-05-005 | K812: BLK-05-005 | L812: Covered | M812: Single reading block | O812: 1 | P812: =IF(L812="MISSING","MISSING",IF(O812=1,"PASS","DUPLICATE")) -> PASS
A813: Ezekiel 7 | B813: 809 | C813: Old Testament | D813: 26 | E813: Ezekiel | F813: 7 | G813: v0.5 | H813: Bible_Journey_Canon_Map_v0_5_Exile_Return_Persia.xlsx | I813: Coverage Audit | J813: CRS-05-005 | K813: BLK-05-005 | L813: Covered | M813: Single reading block | O813: 1 | P813: =IF(L813="MISSING","MISSING",IF(O813=1,"PASS","DUPLICATE")) -> PASS
A814: Ezekiel 8 | B814: 810 | C814: Old Testament | D814: 26 | E814: Ezekiel | F814: 8 | G814: v0.5 | H814: Bible_Journey_Canon_Map_v0_5_Exile_Return_Persia.xlsx | I814: Coverage Audit | J814: CRS-05-006 | K814: BLK-05-006 | L814: Covered | M814: Single reading block | O814: 1 | P814: =IF(L814="MISSING","MISSING",IF(O814=1,"PASS","DUPLICATE")) -> PASS
A815: Ezekiel 9 | B815: 811 | C815: Old Testament | D815: 26 | E815: Ezekiel | F815: 9 | G815: v0.5 | H815: Bible_Journey_Canon_Map_v0_5_Exile_Return_Persia.xlsx | I815: Coverage Audit | J815: CRS-05-006 | K815: BLK-05-006 | L815: Covered | M815: Single reading block | O815: 1 | P815: =IF(L815="MISSING","MISSING",IF(O815=1,"PASS","DUPLICATE")) -> PASS
A816: Ezekiel 10 | B816: 812 | C816: Old Testament | D816: 26 | E816: Ezekiel | F816: 10 | G816: v0.5 | H816: Bible_Journey_Canon_Map_v0_5_Exile_Return_Persia.xlsx | I816: Coverage Audit | J816: CRS-05-006 | K816: BLK-05-006 | L816: Covered | M816: Single reading block | O816: 1 | P816: =IF(L816="MISSING","MISSING",IF(O816=1,"PASS","DUPLICATE")) -> PASS
A817: Ezekiel 11 | B817: 813 | C817: Old Testament | D817: 26 | E817: Ezekiel | F817: 11 | G817: v0.5 | H817: Bible_Journey_Canon_Map_v0_5_Exile_Return_Persia.xlsx | I817: Coverage Audit | J817: CRS-05-006 | K817: BLK-05-006 | L817: Covered | M817: Single reading block | O817: 1 | P817: =IF(L817="MISSING","MISSING",IF(O817=1,"PASS","DUPLICATE")) -> PASS
A818: Ezekiel 12 | B818: 814 | C818: Old Testament | D818: 26 | E818: Ezekiel | F818: 12 | G818: v0.5 | H818: Bible_Journey_Canon_Map_v0_5_Exile_Return_Persia.xlsx | I818: Coverage Audit | J818: CRS-05-007 | K818: BLK-05-007 | L818: Covered | M818: Single reading block | O818: 1 | P818: =IF(L818="MISSING","MISSING",IF(O818=1,"PASS","DUPLICATE")) -> PASS
... A866: Daniel 12 | B866: 862 | C866: Old Testament | D866: 27 | E866: Daniel | F866: 12 | G866: v0.5 | H866: Bible_Journey_Canon_Map_v0_5_Exile_Return_Persia.xlsx | I866: Coverage Audit | J866: CRS-05-025 | K866: BLK-05-025 | L866: Covered | M866: Single reading block | O866: 1 | P866: =IF(L866="MISSING","MISSING",IF(O866=1,"PASS","DUPLICATE")) -> PASS
...

Sheet Book Catalog
A1: BOOK CATALOG
A2: Canonical baseline for the Protestant 66-book / 1,189-chapter coverage audit. Other canon profiles should be added as separate expected-coverage catalogs.
A4: Testament | B4: Canonical Book Order | C4: Book | D4: Expected Chapters | E4: Cumulative Start Chapter | F4: Cumulative End Chapter
A5: Old Testament | B5: 1 | C5: Genesis | D5: 50 | E5: 1 | F5: 50
A6: Old Testament | B6: 2 | C6: Exodus | D6: 40 | E6: 51 | F6: 90
A7: Old Testament | B7: 3 | C7: Leviticus | D7: 27 | E7: 91 | F7: 117
A8: Old Testament | B8: 4 | C8: Numbers | D8: 36 | E8: 118 | F8: 153
A9: Old Testament | B9: 5 | C9: Deuteronomy | D9: 34 | E9: 154 | F9: 187
A10: Old Testament | B10: 6 | C10: Joshua | D10: 24 | E10: 188 | F10: 211
A11: Old Testament | B11: 7 | C11: Judges | D11: 21 | E11: 212 | F11: 232
A12: Old Testament | B12: 8 | C12: Ruth | D12: 4 | E12: 233 | F12: 236
A13: Old Testament | B13: 9 | C13: 1 Samuel | D13: 31 | E13: 237 | F13: 267
A14: Old Testament | B14: 10 | C14: 2 Samuel | D14: 24 | E14: 268 | F14: 291
A15: Old Testament | B15: 11 | C15: 1 Kings | D15: 22 | E15: 292 | F15: 313
A16: Old Testament | B16: 12 | C16: 2 Kings | D16: 25 | E16: 314 | F16: 338
... A70: New Testament | B70: 66 | C70: Revelation | D70: 22 | E70: 1168 | F70: 1189

Sheet Book Summary
A1: BOOK SUMMARY
A2: Formula-driven audit by canonical book. PASS means expected chapter count equals mapped chapter count and no duplicate source-map rows remain in master coverage.
A4: Testament | B4: Book Order | C4: Book | D4: Expected Chapters | E4: Mapped Chapters | F4: Duplicate Source Rows | G4: Book QA | H4: Coverage %
A5: Old Testament | B5: 1 | C5: Genesis | D5: 50 | E5: =COUNTIF('Master Chapter Coverage'!$E$5:$E$2000,C5) -> 50 | F5: =COUNTIFS('Master Chapter Coverage'!$E$5:$E$2000,C5,'Master Chapter Coverage'!$P$5:$P$2000,"DUPLICATE") -> 0 | G5: =IF(AND(E5=D5,F5=0),"PASS","REVIEW") -> PASS | H5: =IFERROR(E5/D5,0) -> 1
A6: Old Testament | B6: 2 | C6: Exodus | D6: 40 | E6: =COUNTIF('Master Chapter Coverage'!$E$5:$E$2000,C6) -> 40 | F6: =COUNTIFS('Master Chapter Coverage'!$E$5:$E$2000,C6,'Master Chapter Coverage'!$P$5:$P$2000,"DUPLICATE") -> 0 | G6: =IF(AND(E6=D6,F6=0),"PASS","REVIEW") -> PASS | H6: =IFERROR(E6/D6,0) -> 1
A7: Old Testament | B7: 3 | C7: Leviticus | D7: 27 | E7: =COUNTIF('Master Chapter Coverage'!$E$5:$E$2000,C7) -> 27 | F7: =COUNTIFS('Master Chapter Coverage'!$E$5:$E$2000,C7,'Master Chapter Coverage'!$P$5:$P$2000,"DUPLICATE") -> 0 | G7: =IF(AND(E7=D7,F7=0),"PASS","REVIEW") -> PASS | H7: =IFERROR(E7/D7,0) -> 1
A8: Old Testament | B8: 4 | C8: Numbers | D8: 36 | E8: =COUNTIF('Master Chapter Coverage'!$E$5:$E$2000,C8) -> 36 | F8: =COUNTIFS('Master Chapter Coverage'!$E$5:$E$2000,C8,'Master Chapter Coverage'!$P$5:$P$2000,"DUPLICATE") -> 0 | G8: =IF(AND(E8=D8,F8=0),"PASS","REVIEW") -> PASS | H8: =IFERROR(E8/D8,0) -> 1
A9: Old Testament | B9: 5 | C9: Deuteronomy | D9: 34 | E9: =COUNTIF('Master Chapter Coverage'!$E$5:$E$2000,C9) -> 34 | F9: =COUNTIFS('Master Chapter Coverage'!$E$5:$E$2000,C9,'Master Chapter Coverage'!$P$5:$P$2000,"DUPLICATE") -> 0 | G9: =IF(AND(E9=D9,F9=0),"PASS","REVIEW") -> PASS | H9: =IFERROR(E9/D9,0) -> 1
A10: Old Testament | B10: 6 | C10: Joshua | D10: 24 | E10: =COUNTIF('Master Chapter Coverage'!$E$5:$E$2000,C10) -> 24 | F10: =COUNTIFS('Master Chapter Coverage'!$E$5:$E$2000,C10,'Master Chapter Coverage'!$P$5:$P$2000,"DUPLICATE") -> 0 | G10: =IF(AND(E10=D10,F10=0),"PASS","REVIEW") -> PASS | H10: =IFERROR(E10/D10,0) -> 1
A11: Old Testament | B11: 7 | C11: Judges | D11: 21 | E11: =COUNTIF('Master Chapter Coverage'!$E$5:$E$2000,C11) -> 21 | F11: =COUNTIFS('Master Chapter Coverage'!$E$5:$E$2000,C11,'Master Chapter Coverage'!$P$5:$P$2000,"DUPLICATE") -> 0 | G11: =IF(AND(E11=D11,F11=0),"PASS","REVIEW") -> PASS | H11: =IFERROR(E11/D11,0) -> 1
A12: Old Testament | B12: 8 | C12: Ruth | D12: 4 | E12: =COUNTIF('Master Chapter Coverage'!$E$5:$E$2000,C12) -> 4 | F12: =COUNTIFS('Master Chapter Coverage'!$E$5:$E$2000,C12,'Master Chapter Coverage'!$P$5:$P$2000,"DUPLICATE") -> 0 | G12: =IF(AND(E12=D12,F12=0),"PASS","REVIEW") -> PASS | H12: =IFERROR(E12/D12,0) -> 1
A13: Old Testament | B13: 9 | C13: 1 Samuel | D13: 31 | E13: =COUNTIF('Master Chapter Coverage'!$E$5:$E$2000,C13) -> 31 | F13: =COUNTIFS('Master Chapter Coverage'!$E$5:$E$2000,C13,'Master Chapter Coverage'!$P$5:$P$2000,"DUPLICATE") -> 0 | G13: =IF(AND(E13=D13,F13=0),"PASS","REVIEW") -> PASS | H13: =IFERROR(E13/D13,0) -> 1
A14: Old Testament | B14: 10 | C14: 2 Samuel | D14: 24 | E14: =COUNTIF('Master Chapter Coverage'!$E$5:$E$2000,C14) -> 24 | F14: =COUNTIFS('Master Chapter Coverage'!$E$5:$E$2000,C14,'Master Chapter Coverage'!$P$5:$P$2000,"DUPLICATE") -> 0 | G14: =IF(AND(E14=D14,F14=0),"PASS","REVIEW") -> PASS | H14: =IFERROR(E14/D14,0) -> 1
A15: Old Testament | B15: 11 | C15: 1 Kings | D15: 22 | E15: =COUNTIF('Master Chapter Coverage'!$E$5:$E$2000,C15) -> 22 | F15: =COUNTIFS('Master Chapter Coverage'!$E$5:$E$2000,C15,'Master Chapter Coverage'!$P$5:$P$2000,"DUPLICATE") -> 0 | G15: =IF(AND(E15=D15,F15=0),"PASS","REVIEW") -> PASS | H15: =IFERROR(E15/D15,0) -> 1
A16: Old Testament | B16: 12 | C16: 2 Kings | D16: 25 | E16: =COUNTIF('Master Chapter Coverage'!$E$5:$E$2000,C16) -> 25 | F16: =COUNTIFS('Master Chapter Coverage'!$E$5:$E$2000,C16,'Master Chapter Coverage'!$P$5:$P$2000,"DUPLICATE") -> 0 | G16: =IF(AND(E16=D16,F16=0),"PASS","REVIEW") -> PASS | H16: =IFERROR(E16/D16,0) -> 1
... A70: New Testament | B70: 66 | C70: Revelation | D70: 22 | E70: =COUNTIF('Master Chapter Coverage'!$E$5:$E$2000,C70) -> 22 | F70: =COUNTIFS('Master Chapter Coverage'!$E$5:$E$2000,C70,'Master Chapter Coverage'!$P$5:$P$2000,"DUPLICATE") -> 0 | G70: =IF(AND(E70=D70,F70=0),"PASS","REVIEW") -> PASS | H70: =IFERROR(E70/D70,0) -> 1

Sheet Master Link Registry
A1: MASTER LINK REGISTRY
A2: Traceability registry for cross-map attachments, parallel accounts, context bridges, harmony policies, and study rules. This is dependency input, not final render order.
A4: Map Version | B4: Source Workbook | C4: Source Sheet | D4: Local Record ID | E4: Anchor / From | F4: Target / Related | G4: Relationship / Policy | H4: Confidence | I4: Status / Gate | J4: Source Key(s) | K4: Raw Source Summary
A5: v0.2 | B5: Bible_Journey_Canon_Map_v0_2_Chronicles_Psalms_Job_1Kings.xlsx | C5: Link Ledger | D5: RES-1CH-010 | E5: 1 Chronicles 10 | F5: CRS-1SA-021 | G5: Parallel Account | H5: High | I5: Draft | K5: resolution id: RES-1CH-010 | source crs: CRS-1CH-007 | scope passage: 1 Chronicles 10 | relationship: Parallel Account | target map: Canon Map v0.1 | target crs: CRS-1SA-021 | target passage: 1 Samuel 31 | placement confidence: High | status: Draft | notes: Chronicles retells Saul's death with distinct framing.
A6: v0.2 | B6: Bible_Journey_Canon_Map_v0_2_Chronicles_Psalms_Job_1Kings.xlsx | C6: Link Ledger | D6: RES-1CH-011 | E6: 1 Chronicles 11 | F6: CRS-2SA-003 | G6: Parallel / Complementary Account | H6: High | I6: Draft | K6: resolution id: RES-1CH-011 | source crs: CRS-1CH-008 | scope passage: 1 Chronicles 11 | relationship: Parallel / Complementary Account | target map: Canon Map v0.1 | target crs: CRS-2SA-003 | target passage: 2 Samuel 5 | placement confidence: High | status: Draft | notes: A later verse-level model should distinguish city capture from the warrior list.
A7: v0.2 | B7: Bible_Journey_Canon_Map_v0_2_Chronicles_Psalms_Job_1Kings.xlsx | C7: Link Ledger | D7: RES-1CH-012 | E7: 1 Chronicles 12 | F7: CRS-1SA-011–020; CRS-2SA-001 | G7: Supplementary / Composite | H7: Probable | I7: Needs Research | K7: resolution id: RES-1CH-012 | source crs: CRS-1CH-009 | scope passage: 1 Chronicles 12 | relationship: Supplementary / Composite | target map: Canon Map v0.1 | target crs: CRS-1SA-011–020; CRS-2SA-001 | target passage: 1 Samuel 21–31; 2 Samuel 1–2 | placement confidence: Probable | status: Needs Research | notes: Chapter aggregates groups linked to distinct moments; not a one-event parallel.
A8: v0.2 | B8: Bible_Journey_Canon_Map_v0_2_Chronicles_Psalms_Job_1Kings.xlsx | C8: Link Ledger | D8: RES-1CH-013 | E8: 1 Chronicles 13 | F8: CRS-2SA-004 | G8: Parallel Account | H8: High | I8: Open | K8: resolution id: RES-1CH-013 | source crs: CRS-1CH-010 | scope passage: 1 Chronicles 13 | relationship: Parallel Account | target map: Canon Map v0.1 | target crs: CRS-2SA-004 | target passage: 2 Samuel 6:1-11 | placement confidence: High | status: Open | notes: Verse-level split is mandatory for correct Complete Chronological Reading.
A9: v0.2 | B9: Bible_Journey_Canon_Map_v0_2_Chronicles_Psalms_Job_1Kings.xlsx | C9: Link Ledger | D9: RES-1CH-014 | E9: 1 Chronicles 14 | F9: CRS-2SA-003 | G9: Parallel Account | H9: High | I9: Open | K9: resolution id: RES-1CH-014 | source crs: CRS-1CH-011 | scope passage: 1 Chronicles 14 | relationship: Parallel Account | target map: Canon Map v0.1 | target crs: CRS-2SA-003 | target passage: 2 Samuel 5:11-25 | placement confidence: High | status: Open | notes: Needs verse-level boundaries in 2 Samuel 5.
A10: v0.2 | B10: Bible_Journey_Canon_Map_v0_2_Chronicles_Psalms_Job_1Kings.xlsx | C10: Link Ledger | D10: RES-1CH-015 | E10: 1 Chronicles 15-16 | F10: CRS-2SA-004 | G10: Complementary Account | H10: High | I10: Open | K10: resolution id: RES-1CH-015 | source crs: CRS-1CH-012 | scope passage: 1 Chronicles 15-16 | relationship: Complementary Account | target map: Canon Map v0.1 | target crs: CRS-2SA-004 | target passage: 2 Samuel 6:12-19 | placement confidence: High | status: Open | notes: Exact stream sequencing depends on splitting 2 Samuel 6.
A11: v0.2 | B11: Bible_Journey_Canon_Map_v0_2_Chronicles_Psalms_Job_1Kings.xlsx | C11: Link Ledger | D11: RES-1CH-017 | E11: 1 Chronicles 17 | F11: CRS-2SA-005 | G11: Parallel Account | H11: High | I11: Draft | K11: resolution id: RES-1CH-017 | source crs: CRS-1CH-013 | scope passage: 1 Chronicles 17 | relationship: Parallel Account | target map: Canon Map v0.1 | target crs: CRS-2SA-005 | target passage: 2 Samuel 7 | placement confidence: High | status: Draft | notes: Compare view should preserve different wording and emphasis.
A12: v0.2 | B12: Bible_Journey_Canon_Map_v0_2_Chronicles_Psalms_Job_1Kings.xlsx | C12: Link Ledger | D12: RES-1CH-018 | E12: 1 Chronicles 18 | F12: CRS-2SA-006 | G12: Parallel Account | H12: High | I12: Draft | K12: resolution id: RES-1CH-018 | source crs: CRS-1CH-014 | scope passage: 1 Chronicles 18 | relationship: Parallel Account | target map: Canon Map v0.1 | target crs: CRS-2SA-006 | target passage: 2 Samuel 8 | placement confidence: High | status: Draft | notes: Chronicles and Samuel order details should remain separately readable.
A13: v0.2 | B13: Bible_Journey_Canon_Map_v0_2_Chronicles_Psalms_Job_1Kings.xlsx | C13: Link Ledger | D13: RES-1CH-019 | E13: 1 Chronicles 19 | F13: CRS-2SA-008 | G13: Parallel Account | H13: High | I13: Draft | K13: resolution id: RES-1CH-019 | source crs: CRS-1CH-015 | scope passage: 1 Chronicles 19 | relationship: Parallel Account | target map: Canon Map v0.1 | target crs: CRS-2SA-008 | target passage: 2 Samuel 10 | placement confidence: High | status: Draft | notes: No verse-level split currently required.
A14: v0.2 | B14: Bible_Journey_Canon_Map_v0_2_Chronicles_Psalms_Job_1Kings.xlsx | C14: Link Ledger | D14: RES-1CH-020 | E14: 1 Chronicles 20 | F14: CRS-2SA-010; CRS-2SA-018 | G14: Complementary / Composite | H14: Debated | I14: Open | K14: resolution id: RES-1CH-020 | source crs: CRS-1CH-016 | scope passage: 1 Chronicles 20 | relationship: Complementary / Composite | target map: Canon Map v0.1 | target crs: CRS-2SA-010; CRS-2SA-018 | target passage: 2 Samuel 12:26-31; 21:18-22 | placement confidence: Debated | status: Open | notes: Current chapter-level treatment cannot give a single precise chronological location.
A15: v0.2 | B15: Bible_Journey_Canon_Map_v0_2_Chronicles_Psalms_Job_1Kings.xlsx | C15: Link Ledger | D15: RES-1CH-021 | E15: 1 Chronicles 21 | F15: CRS-2SA-021 | G15: Parallel Account | H15: Debated | I15: Draft | K15: resolution id: RES-1CH-021 | source crs: CRS-1CH-017 | scope passage: 1 Chronicles 21 | relationship: Parallel Account | target map: Canon Map v0.1 | target crs: CRS-2SA-021 | target passage: 2 Samuel 24 | placement confidence: Debated | status: Draft | notes: Event relationship high; relative position in David's final narrative remains debated.
A16: v0.2 | B16: Bible_Journey_Canon_Map_v0_2_Chronicles_Psalms_Job_1Kings.xlsx | C16: Link Ledger | D16: RES-1CH-028 | E16: 1 Chronicles 28-29 | F16: CRS-1KG-001; CRS-1KG-002 | G16: Complementary / Bridge | H16: Probable | I16: Open | K16: resolution id: RES-1CH-028 | source crs: CRS-1CH-020 | scope passage: 1 Chronicles 28-29 | relationship: Complementary / Bridge | target map: Canon Map v0.2 | target crs: CRS-1KG-001; CRS-1KG-002 | target passage: 1 Kings 1-2 | placement confidence: Probable | status: Open | notes: Needs specialist review for exact interleaving versus sequential bridge treatment.
... A72: v0.2 | B72: Bible_Journey_Canon_Map_v0_2_Chronicles_Psalms_Job_1Kings.xlsx | C72: Integration Resolution | D72: RES-1KG-021 | E72: 1 Kings 22 | F72: Future Canon Map v0.3 | G72: Future Parallel | H72: High | I72: Open | K72: resolution id: RES-1KG-021 | source crs id: CRS-1KG-021 | scope passage: 1 Kings 22 | relationship: Future Parallel | target map: Future Canon Map v0.3 | target crs id: TBD | target passage: 2 Chronicles 18 | full stream rule: Attach Micaiah/Ahab material. | narrative flow rule: Surface as parallel account. | compare eligible: Yes | verse-level split needed: No | placement confidence: High | status: Open
A73: v0.2 | B73: Bible_Journey_Canon_Map_v0_2_Chronicles_Psalms_Job_1Kings.xlsx | C73: Psalm Placement Policy | D73: PSA-POL-001 | G73: PSA-POL-001 | K73: policy id: PSA-POL-001 | category: Named narrative superscription | evidence basis: Psalm heading names a person/place/episode. | full stream behavior: Attach as a 'Related Psalm' with Probable or Debated label. | narrative flow behavior: Show card after primary narrative; do not auto-complete. | compare / study behavior: Show full passage, heading, and source note. | examples: Psalms 3, 34, 51, 52, 54, 56, 59, 60 | risk control: No synthetic chronology; show uncertainty.
A74: v0.2 | B74: Bible_Journey_Canon_Map_v0_2_Chronicles_Psalms_Job_1Kings.xlsx | C74: Psalm Placement Policy | D74: PSA-POL-002 | G74: PSA-POL-002 | K74: policy id: PSA-POL-002 | category: Parallel textual tradition | evidence basis: A psalm and narrative chapter are closely related textual traditions. | full stream behavior: Label 'Parallel song tradition.' | narrative flow behavior: Keep optional in Narrative Flow. | compare / study behavior: Offer side-by-side / compare text. | examples: Psalm 18 and 2 Samuel 22 | risk control: Never merge the texts.
A75: v0.2 | B75: Bible_Journey_Canon_Map_v0_2_Chronicles_Psalms_Job_1Kings.xlsx | C75: Psalm Placement Policy | D75: PSA-POL-003 | G75: PSA-POL-003 | K75: policy id: PSA-POL-003 | category: Chronicles liturgical reuse | evidence basis: Chronicles contains material corresponding to Psalms text. | full stream behavior: Label 'Related liturgy / shared text.' | narrative flow behavior: Show after 1 Chronicles 16 as optional related reading. | compare / study behavior: Show textual alignment with caveat. | examples: Psalms 96, 105, 106 and 1 Chronicles 16 | risk control: Do not claim date or direction of dependence by default.
A76: v0.2 | B76: Bible_Journey_Canon_Map_v0_2_Chronicles_Psalms_Job_1Kings.xlsx | C76: Psalm Placement Policy | D76: PSA-POL-004 | G76: PSA-POL-004 | K76: policy id: PSA-POL-004 | category: Broad Davidic or Solomonic attribution | evidence basis: Heading names David/Solomon without a specific event. | full stream behavior: Place in broad named window, with no exact date. | narrative flow behavior: Offer in a collection window, not as a forced interruption. | compare / study behavior: Show heading and editorial note. | examples: Psalms 4-6, 72, 127, 138-145 | risk control: Do not translate attribution into a historical episode.
A77: v0.2 | B77: Bible_Journey_Canon_Map_v0_2_Chronicles_Psalms_Job_1Kings.xlsx | C77: Psalm Placement Policy | D77: PSA-POL-005 | G77: PSA-POL-005 | K77: policy id: PSA-POL-005 | category: Psalter literary collection | evidence basis: Psalm belongs to book/collection with no secure event link. | full stream behavior: Keep collection accessible in Full Stream via disclosed non-fixed window. | narrative flow behavior: Offer as a 'Psalter collection' checkpoint. | compare / study behavior: Show literary context and related themes. | examples: Psalms 73-89; 91-95; 107-121 | risk control: Avoid fake chronology.
A78: v0.2 | B78: Bible_Journey_Canon_Map_v0_2_Chronicles_Psalms_Job_1Kings.xlsx | C78: Psalm Placement Policy | D78: PSA-POL-006 | G78: PSA-POL-006 | K78: policy id: PSA-POL-006 | category: Mosaic/pilgrimage/exilic tradition | evidence basis: Heading/genre suggests broad tradition but not a dated event. | full stream behavior: Use disclosed broad tradition label. | narrative flow behavior: Do not break Narrative Flow automatically. | compare / study behavior: Show options to explore tradition/history. | examples: Psalms 90; 120-134; 137 | risk control: No precise event placement.
A79: v0.2 | B79: Bible_Journey_Canon_Map_v0_2_Chronicles_Psalms_Job_1Kings.xlsx | C79: Psalm Placement Policy | D79: PSA-POL-007 | G79: PSA-POL-007 | K79: policy id: PSA-POL-007 | category: Unresolved global placement | evidence basis: No defensible single placement in Bible Stream. | full stream behavior: Map content and disclose that global chronology is unresolved. | narrative flow behavior: Place in an auxiliary collection queue with a visible completion state. | compare / study behavior: Explain method and alternatives. | examples: Many Psalter collections | risk control: Coverage never equals false certainty.
A80: v0.3 | B80: Bible_Journey_Canon_Map_v0_3_2Chronicles_Wisdom_2Kings.xlsx | C80: Link Ledger | D80: RES-BR-2CH-001 | E80: 2 Chronicles 1 | F80: Canon Map v0.2 / 1 Kings 3 | G80: Complementary Account | H80: High | I80: Draft | J80: SRC-CANON-TEXT; SRC-CHRONICLES-OVERVIEW; SRC-KINGS-OVERVIEW | K80: resolution id: RES-BR-2CH-001 | scope passage: 2 Chronicles 1 | relationship: Complementary Account | target map: Canon Map v0.2 | target crs: Canon Map v0.2 / 1 Kings 3 | target passage: 1 Kings 3 | placement confidence: High | status: Draft | notes: Chronicles retells Solomon's worship at Gibeon and request for wisdom with its own framing. | source ids: SRC-CANON-TEXT; SRC-CHRONICLES-OVERVIEW; SRC-KINGS-OVERVIEW
A81: v0.3 | B81: Bible_Journey_Canon_Map_v0_3_2Chronicles_Wisdom_2Kings.xlsx | C81: Link Ledger | D81: RES-BR-2CH-002 | E81: 2 Chronicles 2-4 | F81: Canon Map v0.2 / 1 Kings 5-7 | G81: Complementary Account | H81: High | I81: Draft | J81: SRC-CANON-TEXT; SRC-CHRONICLES-OVERVIEW; SRC-KINGS-OVERVIEW | K81: resolution id: RES-BR-2CH-002 | scope passage: 2 Chronicles 2-4 | relationship: Complementary Account | target map: Canon Map v0.2 | target crs: Canon Map v0.2 / 1 Kings 5-7 | target passage: 1 Kings 5-7 | placement confidence: High | status: Draft | notes: Chronicles expands the temple workforce, materials, furnishings, and dedication preparation. | source ids: SRC-CANON-TEXT; SRC-CHRONICLES-OVERVIEW; SRC-KINGS-OVERVIEW
A82: v0.3 | B82: Bible_Journey_Canon_Map_v0_3_2Chronicles_Wisdom_2Kings.xlsx | C82: Link Ledger | D82: RES-BR-2CH-003 | E82: 2 Chronicles 5-7 | F82: Canon Map v0.2 / 1 Kings 8-9 | G82: Complementary Account | H82: High | I82: Draft | J82: SRC-CANON-TEXT; SRC-CHRONICLES-OVERVIEW; SRC-KINGS-OVERVIEW | K82: resolution id: RES-BR-2CH-003 | scope passage: 2 Chronicles 5-7 | relationship: Complementary Account | target map: Canon Map v0.2 | target crs: Canon Map v0.2 / 1 Kings 8-9 | target passage: 1 Kings 8-9 | placement confidence: High | status: Draft | notes: Chronicles presents the dedication, Solomon's prayer, fire, feast, and divine response with distinct emphases. | source ids: SRC-CANON-TEXT; SRC-CHRONICLES-OVERVIEW; SRC-KINGS-OVERVIEW
A83: v0.3 | B83: Bible_Journey_Canon_Map_v0_3_2Chronicles_Wisdom_2Kings.xlsx | C83: Link Ledger | D83: RES-BR-2CH-004 | E83: 2 Chronicles 8 | F83: Canon Map v0.2 / 1 Kings 9 | G83: Complementary Account | H83: High | I83: Draft | J83: SRC-CANON-TEXT; SRC-CHRONICLES-OVERVIEW; SRC-KINGS-OVERVIEW | K83: resolution id: RES-BR-2CH-004 | scope passage: 2 Chronicles 8 | relationship: Complementary Account | target map: Canon Map v0.2 | target crs: Canon Map v0.2 / 1 Kings 9 | target passage: 1 Kings 9 | placement confidence: High | status: Draft | notes: Chronicles pairs building projects with worship administration and international trade. | source ids: SRC-CANON-TEXT; SRC-CHRONICLES-OVERVIEW; SRC-KINGS-OVERVIEW
A84: v0.3 | B84: Bible_Journey_Canon_Map_v0_3_2Chronicles_Wisdom_2Kings.xlsx | C84: Link Ledger | D84: RES-BR-2CH-005 | E84: 2 Chronicles 9 | F84: Canon Map v0.2 / 1 Kings 10-11 | G84: Complementary Account | H84: High | I84: Draft | J84: SRC-CANON-TEXT; SRC-CHRONICLES-OVERVIEW; SRC-KINGS-OVERVIEW | K84: resolution id: RES-BR-2CH-005 | scope passage: 2 Chronicles 9 | relationship: Complementary Account | target map: Canon Map v0.2 | target crs: Canon Map v0.2 / 1 Kings 10-11 | target passage: 1 Kings 10-11 | placement confidence: High | status: Draft | notes: Chronicles narrates the visit of the Queen of Sheba, wealth, and Solomon's death; it omits much of Kings' negative assessment. | source ids: SRC-CANON-TEXT; SRC-CHRONICLES-OVERVIEW; SRC-KINGS-OVERVIEW
A85: v0.3 | B85: Bible_Journey_Canon_Map_v0_3_2Chronicles_Wisdom_2Kings.xlsx | C85: Link Ledger | D85: RES-BR-2CH-006 | E85: 2 Chronicles 10 | F85: Canon Map v0.2 / 1 Kings 12:1-24 | G85: Parallel Account | H85: High | I85: Draft | J85: SRC-CANON-TEXT; SRC-CHRONICLES-OVERVIEW; SRC-KINGS-OVERVIEW | K85: resolution id: RES-BR-2CH-006 | scope passage: 2 Chronicles 10 | relationship: Parallel Account | target map: Canon Map v0.2 | target crs: Canon Map v0.2 / 1 Kings 12:1-24 | target passage: 1 Kings 12:1-24 | placement confidence: High | status: Draft | notes: Chronicles' division account parallels the early Rehoboam narrative in Kings. | source ids: SRC-CANON-TEXT; SRC-CHRONICLES-OVERVIEW; SRC-KINGS-OVERVIEW
A86: v0.3 | B86: Bible_Journey_Canon_Map_v0_3_2Chronicles_Wisdom_2Kings.xlsx | C86: Link Ledger | D86: RES-BR-2CH-007 | E86: 2 Chronicles 11 | F86: Canon Map v0.2 / Rehoboam window | G86: Complementary Account | H86: High | I86: Draft | J86: SRC-CANON-TEXT; SRC-CHRONICLES-OVERVIEW | K86: resolution id: RES-BR-2CH-007 | scope passage: 2 Chronicles 11 | relationship: Complementary Account | target map: Canon Map v0.2 | target crs: Canon Map v0.2 / Rehoboam window | target passage: Rehoboam window | placement confidence: High | status: Draft | notes: Chronicles adds fortifications, migration, and domestic material not presented in the same way in Kings. | source ids: SRC-CANON-TEXT; SRC-CHRONICLES-OVERVIEW
A87: v0.3 | B87: Bible_Journey_Canon_Map_v0_3_2Chronicles_Wisdom_2Kings.xlsx | C87: Link Ledger | D87: RES-BR-2CH-008 | E87: 2 Chronicles 12 | F87: Canon Map v0.2 / 1 Kings 14:25-28 | G87: Complementary Account | H87: High | I87: Draft | J87: SRC-CANON-TEXT; SRC-CHRONICLES-OVERVIEW; SRC-KINGS-OVERVIEW | K87: resolution id: RES-BR-2CH-008 | scope passage: 2 Chronicles 12 | relationship: Complementary Account | target map: Canon Map v0.2 | target crs: Canon Map v0.2 / 1 Kings 14:25-28 | target passage: 1 Kings 14:25-28 | placement confidence: High | status: Draft | notes: Chronicles gives a fuller theological and narrative presentation of the Shishak invasion. | source ids: SRC-CANON-TEXT; SRC-CHRONICLES-OVERVIEW; SRC-KINGS-OVERVIEW
A88: v0.3 | B88: Bible_Journey_Canon_Map_v0_3_2Chronicles_Wisdom_2Kings.xlsx | C88: Link Ledger | D88: RES-BR-2CH-009 | E88: 2 Chronicles 13 | F88: Canon Map v0.2 / 1 Kings 15:1-8 | G88: Complementary Account | H88: High | I88: Draft | J88: SRC-CANON-TEXT; SRC-CHRONICLES-OVERVIEW; SRC-KINGS-OVERVIEW | K88: resolution id: RES-BR-2CH-009 | scope passage: 2 Chronicles 13 | relationship: Complementary Account | target map: Canon Map v0.2 | target crs: Canon Map v0.2 / 1 Kings 15:1-8 | target passage: 1 Kings 15:1-8 | placement confidence: High | status: Draft | notes: Chronicles contains extended material about Abijah not preserved in Kings. | source ids: SRC-CANON-TEXT; SRC-CHRONICLES-OVERVIEW; SRC-KINGS-OVERVIEW
A89: v0.3 | B89: Bible_Journey_Canon_Map_v0_3_2Chronicles_Wisdom_2Kings.xlsx | C89: Link Ledger | D89: RES-BR-2CH-010 | E89: 2 Chronicles 14-15 | F89: Canon Map v0.2 / 1 Kings 15:9-24 | G89: Complementary Account | H89: High | I89: Draft | J89: SRC-CANON-TEXT; SRC-CHRONICLES-OVERVIEW | K89: resolution id: RES-BR-2CH-010 | scope passage: 2 Chronicles 14-15 | relationship: Complementary Account | target map: Canon Map v0.2 | target crs: Canon Map v0.2 / 1 Kings 15:9-24 | target passage: 1 Kings 15:9-24 | placement confidence: High | status: Draft | notes: Chronicles adds reform, covenant, and conflict narratives not mirrored in Kings. | source ids: SRC-CANON-TEXT; SRC-CHRONICLES-OVERVIEW
A90: v0.3 | B90: Bible_Journey_Canon_Map_v0_3_2Chronicles_Wisdom_2Kings.xlsx | C90: Link Ledger | D90: RES-BR-2CH-011 | E90: 2 Chronicles 16 | F90: Canon Map v0.2 / 1 Kings 15:16-24 | G90: Complementary Account | H90: High | I90: Draft | J90: SRC-CANON-TEXT; SRC-CHRONICLES-OVERVIEW; SRC-KINGS-OVERVIEW | K90: resolution id: RES-BR-2CH-011 | scope passage: 2 Chronicles 16 | relationship: Complementary Account | target map: Canon Map v0.2 | target crs: Canon Map v0.2 / 1 Kings 15:16-24 | target passage: 1 Kings 15:16-24 | placement confidence: High | status: Draft | notes: Chronicles closely relates to Kings' account but adds Hanani's rebuke and illness/death detail. | source ids: SRC-CANON-TEXT; SRC-CHRONICLES-OVERVIEW; SRC-KINGS-OVERVIEW
A91: v0.3 | B91: Bible_Journey_Canon_Map_v0_3_2Chronicles_Wisdom_2Kings.xlsx | C91: Link Ledger | D91: RES-BR-2CH-012 | E91: 2 Chronicles 17 | F91: Canon Map v0.2 / 1 Kings 22:41-50 | G91: Complementary Account | H91: High | I91: Draft | J91: SRC-CANON-TEXT; SRC-CHRONICLES-OVERVIEW | K91: resolution id: RES-BR-2CH-012 | scope passage: 2 Chronicles 17 | relationship: Complementary Account | target map: Canon Map v0.2 | target crs: Canon Map v0.2 / 1 Kings 22:41-50 | target passage: 1 Kings 22:41-50 | placement confidence: High | status: Draft | notes: Chronicles adds detailed teaching, judicial, and defensive programs. | source ids: SRC-CANON-TEXT; SRC-CHRONICLES-OVERVIEW
... A149: v0.3 | B149: Bible_Journey_Canon_Map_v0_3_2Chronicles_Wisdom_2Kings.xlsx | C149: Integration Resolution | D149: RES-WIS-HEZ-001 | E149: Proverbs 25-29 | F149: Canon Map v0.3 | G149: Collection / editorial context | H149: Probable | I149: Draft | J149: SRC-CANON-TEXT; SRC-WISDOM-CANON; SRC-WHO-WROTE | K149: resolution id: RES-WIS-HEZ-001 | scope passage: Proverbs 25-29 | relationship: Collection / editorial context | target map: Canon Map v0.3 | target crs / final home: CRS-2K-018 | target passage: 2 Kings 18:1-12; 2 Chronicles 29-31 | placement confidence: Probable | status: Draft | full stream behavior: Read as an intact wisdom collection inside the disclosed Hezekian collection note; it does not retell the event. | narrative flow behavior: Optional contextual branch. Retain pending when omitted. | compare behavior: No parallel-text comparison; surface 'Why this appears here' instead. | notes: The heading in Proverbs 25:1 supports a Hezekian collection association, not a composition date for every proverb. | source ids: SRC-CANON-TEXT; SRC-WISDOM-CANON; SRC-WHO-WROTE | owner: Editorial
A150: v0.3 | B150: Bible_Journey_Canon_Map_v0_3_2Chronicles_Wisdom_2Kings.xlsx | C150: Wisdom Placement Policy | D150: WIS-001 | F150: SRC-WISDOM-CANON; SRC-WHO-WROTE | G150: WIS-001 | H150: Unresolved | I150: Draft | K150: policy id: WIS-001 | content: Proverbs 1-24 | default bible stream placement: Disclosed Solomonic Wisdom Interlude after Solomon's reign material | why: Traditional association with Solomon is meaningful for navigation but not a settled composition chronology. | placement confidence: Unresolved | narrative flow default: Off by default; show as an optional wisdom chapter | compare accounts: No | user-facing wording: 'Traditionally associated with Solomon; historical composition and individual settings remain debated.' | sources: SRC-WISDOM-CANON; SRC-WHO-WROTE | status: Draft
A151: v0.3 | B151: Bible_Journey_Canon_Map_v0_3_2Chronicles_Wisdom_2Kings.xlsx | C151: Wisdom Placement Policy | D151: WIS-002 | F151: SRC-WISDOM-CANON; SRC-WHO-WROTE; SRC-SONG | G151: WIS-002 | H151: Unresolved | I151: Draft | K151: policy id: WIS-002 | content: Song of Songs 1-8 | default bible stream placement: Disclosed Solomonic Wisdom Interlude | why: Traditional Solomonic association is not sufficient to present the work as a dated narrative episode. | placement confidence: Unresolved | narrative flow default: Off by default; offer through Wisdom and Poetry | compare accounts: No | user-facing wording: 'Placed beside the Solomonic tradition as a study arrangement, not as a claim about a specific moment in Solomon's life.' | sources: SRC-WISDOM-CANON; SRC-WHO-WROTE; SRC-SONG | status: Draft
A152: v0.3 | B152: Bible_Journey_Canon_Map_v0_3_2Chronicles_Wisdom_2Kings.xlsx | C152: Wisdom Placement Policy | D152: WIS-003 | F152: SRC-WISDOM-CANON; SRC-WHO-WROTE | G152: WIS-003 | H152: Unresolved | I152: Draft | K152: policy id: WIS-003 | content: Ecclesiastes 1-12 | default bible stream placement: Disclosed Solomonic Wisdom Interlude | why: The traditional association should not be converted into a 'late-life Solomon' factual claim. | placement confidence: Unresolved | narrative flow default: Off by default; offer through Wisdom and Poetry | compare accounts: No | user-facing wording: 'Traditionally associated with Solomon. The app does not present it as a verified autobiography or dated final-life journal.' | sources: SRC-WISDOM-CANON; SRC-WHO-WROTE | status: Draft
A153: v0.3 | B153: Bible_Journey_Canon_Map_v0_3_2Chronicles_Wisdom_2Kings.xlsx | C153: Wisdom Placement Policy | D153: WIS-004 | F153: SRC-CANON-TEXT; SRC-WISDOM-CANON; SRC-WHO-WROTE | G153: WIS-004 | H153: Probable | I153: Draft | K153: policy id: WIS-004 | content: Proverbs 25-29 | default bible stream placement: Hezekiah collection note within CRS-2K-018 | why: The superscription names the officials of Hezekiah as copyists/collectors; it does not date every saying. | placement confidence: Probable | narrative flow default: Optional linked context after Hezekiah reforms | compare accounts: No | user-facing wording: 'This collection is associated with the men of Hezekiah. That association describes collection history, not the date of every proverb.' | sources: SRC-CANON-TEXT; SRC-WISDOM-CANON; SRC-WHO-WROTE | status: Draft
A154: v0.3 | B154: Bible_Journey_Canon_Map_v0_3_2Chronicles_Wisdom_2Kings.xlsx | C154: Wisdom Placement Policy | D154: WIS-005 | F154: SRC-CANON-TEXT; SRC-WISDOM-CANON | G154: WIS-005 | H154: Unresolved | I154: Draft | K154: policy id: WIS-005 | content: Proverbs 30 | default bible stream placement: Wisdom Library / no fixed event placement | why: The collection is attributed in the text to Agur, not framed as a dated episode in Solomon's life. | placement confidence: Unresolved | narrative flow default: Off by default | compare accounts: No | user-facing wording: 'No single historical placement is asserted.' | sources: SRC-CANON-TEXT; SRC-WISDOM-CANON | status: Draft
A155: v0.3 | B155: Bible_Journey_Canon_Map_v0_3_2Chronicles_Wisdom_2Kings.xlsx | C155: Wisdom Placement Policy | D155: WIS-006 | F155: SRC-CANON-TEXT; SRC-WISDOM-CANON | G155: WIS-006 | H155: Unresolved | I155: Draft | K155: policy id: WIS-006 | content: Proverbs 31 | default bible stream placement: Wisdom Library / no fixed event placement | why: The collection names Lemuel and his mother; the app will not silently recast it as Solomon material. | placement confidence: Unresolved | narrative flow default: Off by default | compare accounts: No | user-facing wording: 'No single historical placement is asserted.' | sources: SRC-CANON-TEXT; SRC-WISDOM-CANON | status: Draft
A156: v0.4 | B156: Bible_Journey_Canon_Map_v0_4_Prophets_Exile.xlsx | C156: Link Ledger | D156: LNK-04-001 | E156: v0.3 | F156: CRS-04-001 to CRS-04-007 | H156: High | I156: Draft | K156: link id: LNK-04-001 | from map: v0.3 | from anchor: 2 Kings 14:23-29 | to crs / block: CRS-04-001 to CRS-04-007 | link type: Prophetic overlay | complete behavior: Read all in complete mode | narrative behavior: Offer main spine continuation + overlay queue | confidence: High | status: Draft
A157: v0.4 | B157: Bible_Journey_Canon_Map_v0_4_Prophets_Exile.xlsx | C157: Link Ledger | D157: LNK-04-002 | E157: v0.3 | F157: CRS-04-008 to CRS-04-015 | H157: High | I157: Draft | K157: link id: LNK-04-002 | from map: v0.3 | from anchor: 2 Kings 15-16 / 2 Chronicles 26-28 | to crs / block: CRS-04-008 to CRS-04-015 | link type: Prophetic overlay | complete behavior: Read all in complete mode | narrative behavior: Keep oracle collections available but may defer marked collections | compare group: Ahaz / Isaiah | confidence: High | status: Draft
A158: v0.4 | B158: Bible_Journey_Canon_Map_v0_4_Prophets_Exile.xlsx | C158: Link Ledger | D158: LNK-04-003 | E158: v0.3 | F158: CRS-04-016 to CRS-04-018 | H158: High | I158: Draft | K158: link id: LNK-04-003 | from map: v0.3 | from anchor: 2 Kings 18-20 / 2 Chronicles 29-32 | to crs / block: CRS-04-016 to CRS-04-018 | link type: Parallel + context | complete behavior: Read Kings/Chronicles/Isaiah blocks sequentially | narrative behavior: Present historical spine then optional overlay | compare group: Hezekiah / Assyria | confidence: High | status: Draft
A159: v0.4 | B159: Bible_Journey_Canon_Map_v0_4_Prophets_Exile.xlsx | C159: Link Ledger | D159: LNK-04-004 | E159: v0.3 | F159: CRS-04-019 to CRS-04-022 | H159: Mixed | I159: Draft | K159: link id: LNK-04-004 | from map: v0.3 | from anchor: 2 Kings 22-23 / 2 Chronicles 34-35 | to crs / block: CRS-04-019 to CRS-04-022 | link type: Prophetic overlay | complete behavior: Read all required blocks | narrative behavior: Present Josiah story with prophet context drawers | confidence: Mixed | status: Draft
A160: v0.4 | B160: Bible_Journey_Canon_Map_v0_4_Prophets_Exile.xlsx | C160: Link Ledger | D160: LNK-04-005 | E160: v0.3 | F160: CRS-04-023 to CRS-04-029 | H160: Mixed | I160: Draft | K160: link id: LNK-04-005 | from map: v0.3 | from anchor: 2 Kings 23:36-24:17 / 2 Chronicles 36:5-10 | to crs / block: CRS-04-023 to CRS-04-029 | link type: Chronological grouping | complete behavior: Read all including nation oracles | narrative behavior: Defer Jeremiah 46-51 only; retain pending status | confidence: Mixed | status: Draft
A161: v0.4 | B161: Bible_Journey_Canon_Map_v0_4_Prophets_Exile.xlsx | C161: Link Ledger | D161: LNK-04-006 | E161: v0.3 | F161: CRS-04-030 to CRS-04-045 | H161: High | I161: Draft | K161: link id: LNK-04-006 | from map: v0.3 | from anchor: 2 Kings 24:18-25:30 / 2 Chronicles 36:11-23 | to crs / block: CRS-04-030 to CRS-04-045 | link type: Parallel + aftermath | complete behavior: Read all blocks | narrative behavior: Keep poetic response after historical fall | compare group: Jerusalem fall | confidence: High | status: Draft
A162: v0.4 | B162: Bible_Journey_Canon_Map_v0_4_Prophets_Exile.xlsx | C162: Link Ledger | D162: LNK-04-007 | E162: future v0.5 | F162: CRS-04-046 to CRS-04-052 | H162: Probable | I162: Draft | K162: link id: LNK-04-007 | from map: future v0.5 | from anchor: Exile / Return nodes | to crs / block: CRS-04-046 to CRS-04-052 | link type: Future dependency | complete behavior: Read in current v0.4 order | narrative behavior: Show transition card explaining future historical modules | confidence: Probable | status: Draft
A163: v0.4 | B163: Bible_Journey_Canon_Map_v0_4_Prophets_Exile.xlsx | C163: Integration Resolution | D163: Integration Resolution-159 | E163: 2 Kings 14:23-29 / Jeroboam II | F163: CRS-04-001 to CRS-04-007 | G163: Read prophetic books as overlays on reigns, not as detached books after Kings. | H163: High / mixed at detail level | J163: S1; S8; S9; S7 | K163: integration id: INT-04-01 | kings / chronicles anchor: 2 Kings 14:23-29 / Jeroboam II | crs sets to insert: CRS-04-001 to CRS-04-007 | mode behavior: Complete reads all; Narrative may defer non-narrative collections only. | compare accounts behavior: No direct parallel account for Amos/Hosea; show historical anchor card. | primary editorial rule: Read prophetic books as overlays on reigns, not as detached books after Kings. | confidence: High / mixed at detail level | open dependency: v0.3 anchor IDs must be reconciled to canonical 2 Kings units. | source ids: S1; S8; S9; S7 | review state: Not reviewed
A164: v0.4 | B164: Bible_Journey_Canon_Map_v0_4_Prophets_Exile.xlsx | C164: Integration Resolution | D164: Integration Resolution-160 | E164: 2 Kings 15-16 / 2 Chronicles 26-28 | F164: CRS-04-008 to CRS-04-015 | G164: Historical reign anchor is distinct from exact oracle dating. | H164: High at reign level; debated at unit level | J164: S1; S2; S3; S11; S7 | K164: integration id: INT-04-02 | kings / chronicles anchor: 2 Kings 15-16 / 2 Chronicles 26-28 | crs sets to insert: CRS-04-008 to CRS-04-015 | mode behavior: Continue from Kings/Chronicles into Isaiah and Micah blocks, then return to the historical spine. | compare accounts behavior: Compare is offered only for explicit narrative parallels such as Ahaz / Isaiah 7 context, not for all oracle collections. | primary editorial rule: Historical reign anchor is distinct from exact oracle dating. | confidence: High at reign level; debated at unit level | open dependency: Need source-review notes for Isaiah 13-35 sequence. | source ids: S1; S2; S3; S11; S7 | review state: Not reviewed
A165: v0.4 | B165: Bible_Journey_Canon_Map_v0_4_Prophets_Exile.xlsx | C165: Integration Resolution | D165: Integration Resolution-161 | E165: 2 Kings 18-20 / 2 Chronicles 29-32 | F165: CRS-04-016 to CRS-04-018 | G165: Never splice verses. Keep the illness and envoys sequence visibly debated. | H165: High for parallels; debated for full ordering | J165: S1; S2; S3; S7 | K165: integration id: INT-04-03 | kings / chronicles anchor: 2 Kings 18-20 / 2 Chronicles 29-32 | crs sets to insert: CRS-04-016 to CRS-04-018 | mode behavior: Complete reads Isaiah 28-39 in the documented anchor sequence; Narrative Flow presents contextual cards and retains unread status when deferred. | compare accounts behavior: Compare Accounts: Kings / Isaiah 36-39 / Chronicles preserved as intact blocks. | primary editorial rule: Never splice verses. Keep the illness and envoys sequence visibly debated. | confidence: High for parallels; debated for full ordering | open dependency: Cross-link to v0.3 Hezekiah CRS must be exact before implementation. | source ids: S1; S2; S3; S7 | review state: Not reviewed
A166: v0.4 | B166: Bible_Journey_Canon_Map_v0_4_Prophets_Exile.xlsx | C166: Integration Resolution | D166: Integration Resolution-162 | E166: 2 Kings 21-23 / 2 Chronicles 33-35 | F166: CRS-04-019 to CRS-04-022 | G166: Maintain different certainty for Nahum vs Zephaniah vs early Jeremiah. | H166: Mixed | J166: S1; S5; S7 | K166: integration id: INT-04-04 | kings / chronicles anchor: 2 Kings 21-23 / 2 Chronicles 33-35 | crs sets to insert: CRS-04-019 to CRS-04-022 | mode behavior: Insert Nahum, Zephaniah, and early Jeremiah as overlays around late Assyrian collapse and Josiah. | compare accounts behavior: No synthetic comparison; offer historical context drawer. | primary editorial rule: Maintain different certainty for Nahum vs Zephaniah vs early Jeremiah. | confidence: Mixed | open dependency: Habakkuk is intentionally outside v0.4 and must be added in v0.5. | source ids: S1; S5; S7 | review state: Not reviewed
A167: v0.4 | B167: Bible_Journey_Canon_Map_v0_4_Prophets_Exile.xlsx | C167: Integration Resolution | D167: Integration Resolution-163 | E167: 2 Kings 23:36-24:17 / 2 Chronicles 36:5-10 | F167: CRS-04-023 to CRS-04-029 | G167: Treat Jeremiah 46-51 as a collection, not one dated speech. | H167: Mixed | J167: S1; S5; S6; S7 | K167: integration id: INT-04-05 | kings / chronicles anchor: 2 Kings 23:36-24:17 / 2 Chronicles 36:5-10 | crs sets to insert: CRS-04-023 to CRS-04-029 | mode behavior: Complete reads all Jeremiah blocks; Narrative Flow can defer 46-51 to collection pass and must show it as pending. | compare accounts behavior: Compare only where a real parallel historical account exists. | primary editorial rule: Treat Jeremiah 46-51 as a collection, not one dated speech. | confidence: Mixed | open dependency: Detailed dating of Jer 7 / 26 relation and oracle collections requires review. | source ids: S1; S5; S6; S7 | review state: Not reviewed
A168: v0.4 | B168: Bible_Journey_Canon_Map_v0_4_Prophets_Exile.xlsx | C168: Integration Resolution | D168: Integration Resolution-164 | E168: 2 Kings 24:18-25:30 / 2 Chronicles 36:11-23 | F168: CRS-04-030 to CRS-04-045 | G168: Separate historical accounts from poetic response; do not market Lamentations as a real-time diary. | H168: High on anchor; mixed on collections | J168: S1; S5; S6; S7 | K168: integration id: INT-04-06 | kings / chronicles anchor: 2 Kings 24:18-25:30 / 2 Chronicles 36:11-23 | crs sets to insert: CRS-04-030 to CRS-04-045 | mode behavior: Integrate Zedekiah, fall, aftermath, Jeremiah 52, and Lamentations before the exilic bridge. | compare accounts behavior: Compare Accounts available for fall and aftermath narratives. | primary editorial rule: Separate historical accounts from poetic response; do not market Lamentations as a real-time diary. | confidence: High on anchor; mixed on collections | open dependency: Ezekiel, Daniel, Obadiah, and Habakkuk are deferred to future canon maps. | source ids: S1; S5; S6; S7 | review state: Not reviewed
A169: v0.4 | B169: Bible_Journey_Canon_Map_v0_4_Prophets_Exile.xlsx | C169: Integration Resolution | D169: Integration Resolution-165 | E169: Exile / return bridge | F169: CRS-04-046 to CRS-04-052 | G169: Use 'common scholarly placement' wording throughout. | H169: Probable / debated | J169: S2; S4; S10; S12; S7 | K169: integration id: INT-04-07 | kings / chronicles anchor: Exile / return bridge | crs sets to insert: CRS-04-046 to CRS-04-052 | mode behavior: Use a documented horizon sequence: Lamentations -> Isaiah 40-55 -> Isaiah 56-66 -> Joel unresolved node. | compare accounts behavior: No Compare Accounts until future Ezra/Nehemiah / Haggai / Zechariah maps exist. | primary editorial rule: Use 'common scholarly placement' wording throughout. | confidence: Probable / debated | open dependency: Future map must reconcile Isaiah 56-66 and Joel with Ezra-Nehemiah history. | source ids: S2; S4; S10; S12; S7 | review state: Not reviewed
A170: v0.4 | B170: Bible_Journey_Canon_Map_v0_4_Prophets_Exile.xlsx | C170: Prophetic Placement | D170: Prophetic Placement-166 | E170: 2 Kings 14:23-29 | F170: Jeroboam II / Northern Kingdom expansion | H170: Probable | J170: S1; S8; S7 | K170: book / corpus: Jonah | chapters: 1-4 | historical horizon in stream: Jeroboam II / Northern Kingdom expansion | main narrative anchor: 2 Kings 14:23-29 | placement confidence: Probable | what the app may say: Jonah is linked to Jeroboam II by name in Kings; the book is read here as a transparent study placement. | what the app must not claim: That the narrative book's final composition date is fixed by 2 Kings 14:25. | source ids: S1; S8; S7 | review state: Not reviewed
A171: v0.4 | B171: Bible_Journey_Canon_Map_v0_4_Prophets_Exile.xlsx | C171: Prophetic Placement | D171: Prophetic Placement-167 | E171: Jeroboam II / Uzziah | F171: Eighth-century northern prosperity | H171: High | J171: S1; S8; S9; S7 | K171: book / corpus: Amos | chapters: 1-9 | historical horizon in stream: Eighth-century northern prosperity | main narrative anchor: Jeroboam II / Uzziah | placement confidence: High | what the app may say: Amos addresses prosperous northern Israel in the eighth-century horizon. | what the app must not claim: That every oracle can be placed on a precise timeline within Jeroboam II's reign. | source ids: S1; S8; S9; S7 | review state: Not reviewed
